Workbook

Sheet Từ viết tắt
B1: Từ viết tắt | C1: Tên Tiếng Anh | D1: Tiếng Việt
B2: CORSIA | C2: Carbon Offsetting and Reduction Scheme
B3: EU-ETS | C3: EU Emissions Trading System
B4: UK-ETS | C4: UK Emissions Trading Scheme
A5: 1 | B5: {=_xlfn.UNIQUE('Nguồn dữ liệu'!C2:C102)} -> Report Pro | D5: Hệ thống báo cáo phục vụ Khối DV của TCT
A6: 2 | B6: CLM | D6: Hệ thống quản lý khách hàng thường xuyên
A7: 3 | B7: FIMS | D7: Phần mềm khai thác dữ liệu chuyến bay phục vụ điều hành khai thác
A8: 4 | B8: EU-ETS | D8: Phần mềm
A9: 5 | B9: PMS | D9: Phần mềm kế hoạch ngắn hạn
A10: 6 | B10: CMS | D10: Phần mềm quản lý hợp đồng
A11: 7 | B11: SkyHR | D11: Phần mềm Quản trị nhân lực
A12: 8 | B12: TOSS
A13: 8 | B13: Netlines | D13: Hệ thống điều hành bay
A14: 9 | B14: RPS | D14: Hệ thống phân tích hiệu quả đường bay
A15: 10 | B15: VHAT | D15: Website Văn hóa an toàn
A16: 11 | B16: LMS | D16: Phần mềm quản lý chuỗi cung ứng vật tư vật phẩm phục vụ hành khách
A17: 12 | B17: ANCM | D17: Phần mềm quản lý quy trình kiểm soát và thanh toán chi phí điều hành bay, bay qua, hạ cất cánh

Sheet 95 Chỉ tiêu
Q1: UAT | W1: Quản lý KPI
S2: Quản lý KPI
A3: STT | B3: PIC CQĐV | C3: PIC VNA | D3: Phase | E3: Mã GRI (GRI Code) | F3: Trụ cột | G3: Topic | H3: Tên chỉ tiêu (VN) | I3: Tên chỉ tiêu (EN) | J3: Disclosure (Vi) | K3: Disclosure (En) | L3: Yêu cầu của GRI | M3: Note | N3: Nguồn dữ liệu | O3: Biểu mẫu | P3: Mức độ ưu tiên | Q3: Nhập liệu | R3: Dashboard | S3: Có KPI (Yes/No) | T3: Mã KPI | U3: Tên KPI | V3: KPI đạt khi | W3: Nguồn lấy dữ liệu KH/mục tiêu (KPI) | X3: KPI nhập dữ liệu theo tháng/ năm | Y3: Có đưa KPI lên báo cáo nội bộ không (Yes/No) | Z3: Ghi chú | AA3: Công thức tính toán có hệ số
A4: =ROW()-2 -> 2 | B4: Tổ dịch vụ | C4: MS Hương | D4: Phase 1 | E4: Airline B-1 | F4: Social | G4: Customer Experience | H4: Sự hài lòng của khách hàng (NPS Net Promotor Score) | I4: Customer satisfaction (NPS Net Promotor Score) | K4: Customer satisfaction | M4: Dashboard | N4: Report Pro | Q4: N/A | R4: 2 | S4: Yes | T4: 1. Airline B-1-01 2. Airline B-1-02 | U4: 1. NPS (DOM) 2. NPS (INT) | V4: ≥ KH | W4: Nhập thủ công | X4: - Năm | Y4: Yes | Z4: Note: có 2 KPI cho từng phạm vi DOM và INT
A5: =ROW()-2 -> 3 | B5: TTBSV | D5: Phase 1 | E5: Airline B-2 | F5: Social | G5: Customer Experience | K5: Customer engagement | M5: Dashboard | N5: CLM | Q5: N/A | R5: 1 | S5: No | T5: Airline B-2 | U5: Customer engagement/Tương tác khách hàng | V5: > KH | Y5: No | Z5: Không cung cấp do số liệu nhạy cảm
A6: =ROW()-2 -> 4 | B6: TCNL | D6: Phase 1 | E6: Airline D-1 | F6: Social | G6: Labor Conditions | H6: Ngày công mất do đình công | I6: Working days lost to strikes | K6: Working days lost to strikes | M6: Dashboard | N6: Excel | O6: Airline D-1 Số vụ đình công | P6: 1 | Q6: 1 | R6: 1 | S6: Yes | T6: Airline D-1 | U6: Số ngày công mất do đình công | V6: = KH | W6: Nhập thủ công | X6: - Năm | Y6: No
A7: =ROW()-2 -> 5 | B7: Ban ATCL | C7: Mr Đàn | D7: Phase 1 | E7: Airline E-1 | F7: Environment | G7: Noise | H7: Tiếng ồn | I7: Noise Compliance | J7: Tiếng ồn | K7: Noise | M7: Dashboard | N7: Excel | O7: Ban ATCL - Airline E-1 - form tiếng ồn | P7: 1 | Q7: 1 | R7: 2 | S7: Yes | T7: Airline E-1-C4 Airline E-1-C14 Airline E-1-C13 | U7: 1. C4 2. C14 3. C13 | W7: Nhập thủ công | X7: - Năm | Y7: No
A8: =ROW()-2 -> 6 | B8: Ban TT | D8: Phase 1 | E8: Airline F-1 | F8: Social | G8: People and Development | H8: Tham gia hoạt động tình nguyện | I8: Volunteering during working hours | K8: Volunteering during working hours | M8: Dashboard | N8: Excel | O8: Airline F-1 - Volunteering during working hours (Scope: Corporate Communications Department) - Tham gia hoạt động tình nguyện (Phạm vi hiện tại: Ban Truyền thông) | P8: 1 | Q8: 1 | R8: 2 | S8: No | U8: 2. C14 | Y8: No
A9: =ROW()-2 -> 7 | B9: TCNL | D9: Phase 1 | E9: Airline F-2 | F9: Social | G9: People and Development | H9: Mức độ hài lòng của nhân viên | I9: Employee satisfaction | K9: Employee satisfaction | M9: Dashboard | N9: Excel | O9: Airline F-2 - Employee satisfaction - Mức độ hài lòng của nhân viên | P9: 1 | Q9: 1 | R9: 1 | S9: No | T9: Airline F-2 | U9: 3. C13 | Y9: No
A10: =ROW()-2 -> 8 | B10: Ban ATCL | D10: Phase 2 | E10: Airlines C-1 | F10: Environment | G10: Energy and Emissions | K10: Significant spills | T10: Airlines C-1
A11: =ROW()-2 -> 9 | B11: TCNL | D11: Phase 1 | E11: GRI 201-3 | F11: Social | G11: Labor Conditions | J11: Cam kết chi trả lương hưu và phúc lợi | K11: Defined benefit plan obligations and other retirement plans | M11: Text only (báo cáo tĩnh) | T11: GRI 201-3
A12: =ROW()-2 -> 10 | B12: Tổ Thư ký | D12: Phase 1 | E12: GRI 201-4 | F12: Governance | G12: Conduct and Compliance | J12: Trợ cấp/tài trợ nhận từ chính phủ | K12: Financial assistance received from government | L12: =VLOOKUP(#REF!,'29 Chỉ tiêu Text'!$C$2:$F$30,4,0) -> #REF! | M12: Text only (báo cáo tĩnh) | T12: GRI 201-4
A13: =ROW()-2 -> 11 | B13: TCNL | D13: Phase 1 | E13: GRI 202-1 | F13: Social | G13: Labor Conditions | H13: Tỷ lệ lương khởi điểm so với lương tối thiểu vùng 1 | I13: Ratios of standard entry-level wage by gender compared to local minimum wage | K13: Ratios of standard entry-level wage by gender compared to local minimum wage | M13: Dashboard | N13: Excel | O13: GRI 202-1 - Ratios of standard entry level wage by gender compared to local minimum wage - Tỷ lệ lương khởi điểm so với lương tối thiểu vùng 1 | P13: 1 | Q13: 1 | R13: 1 | S13: Yes | T13: GRI 202-1-01 GRI 202-1-02 GRI 202-1-03 | U13: 1. Tỷ lệ lương khởi điểm phi công Việt Nam so với lương tối thiểu vùng 2. Tỷ lệ lương khởi điểm tiếp viên cơ hữu so với lương tối thiểu vùng 3. Tỷ lệ lương khởi điểm lao động mặt đất so với lương tối thiểu vùng | V13: ≥ KH | W13: Nhập thủ công | X13: - Năm | Y13: No
A14: =ROW()-2 -> 12 | B14: TCNL | D14: Phase 1 | E14: GRI 202-2 | F14: Social | G14: Labor Conditions | H14: Tỷ lệ lãnh đạo cấp cao là người bản địa | I14: Proportion of senior management hired from the local community | K14: Proportion of senior management hired from the local community | M14: Dashboard | N14: Excel | O14: GRI 202-2 - Tỷ lệ lãnh đạo cấp cao là người bản địa | P14: 1 | Q14: 1 | R14: 1 | S14: Yes | T14: GRI 202-2 | U14: Tỷ lệ lãnh đạo cấp cao là người Việt Nam tại Việt Nam | V14: = KH | W14: Nhập thủ công | X14: - Năm | Y14: No
A15: =ROW()-2 -> 13 | B15: Tổ Thư ký | D15: Phase 1 | E15: GRI 204-1 | F15: Social | G15: Supply Chain Sustainability | K15: Proportion of spending on local suppliers | N15: CMS | Q15: N/A | R15: 2 | S15: No | T15: GRI 204-1 | Y15: No
A16: =ROW()-2 -> 14 | B16: Tổ Thư ký | D16: Phase 1 | E16: GRI 205-2 | F16: Governance | G16: Conduct and Compliance | J16: Truyền thông, đào tạo về chống tham nhũng | K16: Communication and training about anti-corruption policies and procedures | L16: =VLOOKUP(#REF!,'29 Chỉ tiêu Text'!$C$2:$F$30,4,0) -> #REF! | M16: Text only (báo cáo tĩnh) | T16: GRI 205-2
A17: =ROW()-2 -> 15 | B17: Tổ Thư ký | D17: Phase 1 | E17: GRI 205-3 | F17: Governance | G17: Conduct and Compliance | J17: Sự cố tham nhũng xác nhận và biện pháp xử lý | K17: Confirmed incidents of corruption and actions taken | L17: =VLOOKUP(#REF!,'29 Chỉ tiêu Text'!$C$2:$F$30,4,0) -> #REF! | M17: Text only (báo cáo tĩnh) | T17: GRI 205-3
A18: =ROW()-2 -> 16 | B18: Tổ Thư ký | D18: Phase 1 | E18: GRI 206-1 | F18: Governance | G18: Conduct and Compliance | J18: Vụ kiện về cạnh tranh không lành mạnh, độc quyền | K18: Legal actions for anti-competitive behavior, anti-trust, and monopoly practices | L18: =VLOOKUP(#REF!,'29 Chỉ tiêu Text'!$C$2:$F$30,4,0) -> #REF! | M18: Text only (báo cáo tĩnh) | T18: GRI 206-1
A19: =ROW()-2 -> 17 | B19: Tổ Thư ký | D19: Phase 1 | E19: GRI 2-10 | F19: Governance | G19: Conduct and Compliance | J19: Quy trình đề cử, lựa chọn cơ quan quản lý cao nhất | K19: Nomination and selection of the highest governance body | L19: =VLOOKUP(#REF!,'29 Chỉ tiêu Text'!$C$2:$F$30,4,0) -> #REF! | M19: Text only (báo cáo tĩnh) | T19: GRI 2-10
A20: =ROW()-2 -> 18 | B20: Tổ Thư ký | D20: Phase 1 | E20: GRI 2-11 | F20: Governance | G20: Conduct and Compliance | J20: Chủ tịch HĐQT | K20: Chair of the highest governance body | L20: =VLOOKUP(#REF!,'29 Chỉ tiêu Text'!$C$2:$F$30,4,0) -> #REF! | M20: Text only (báo cáo tĩnh) | T20: GRI 2-11
A21: =ROW()-2 -> 19 | B21: Tổ Thư ký | D21: Phase 1 | E21: GRI 2-12 | F21: Governance | G21: Conduct and Compliance | J21: Vai trò của HĐQT trong giám sát quản lý tác động | K21: Role of the highest governance body in overseeing the management of impacts | L21: =VLOOKUP(#REF!,'29 Chỉ tiêu Text'!$C$2:$F$30,4,0) -> #REF! | M21: Text only (báo cáo tĩnh) | T21: GRI 2-12
A22: =ROW()-2 -> 20 | B22: Tổ Thư ký | D22: Phase 1 | E22: GRI 2-13 | F22: Governance | G22: Conduct and Compliance | J22: Ủy quyền trách nhiệm quản lý các tác động | K22: Delegating authority | L22: =VLOOKUP(#REF!,'29 Chỉ tiêu Text'!$C$2:$F$30,4,0) -> #REF! | M22: Text only (báo cáo tĩnh) | T22: GRI 2-13
A23: =ROW()-2 -> 21 | B23: Tổ Thư ký | D23: Phase 1 | E23: GRI 2-14 | F23: Governance | J23: Vai trò của cơ quan quản trị cao nhất trong báo cáo bền vững | L23: =VLOOKUP(#REF!,'29 Chỉ tiêu Text'!$C$2:$F$30,4,0) -> #REF!
A24: =ROW()-2 -> 22 | B24: Tổ Thư ký | D24: Phase 1 | E24: GRI 2-15 | F24: Governance | G24: Conduct and Compliance | J24: Xung đột lợi ích | K24: Conflicts of interest | L24: =VLOOKUP(#REF!,'29 Chỉ tiêu Text'!$C$2:$F$30,4,0) -> #REF! | M24: Text only (báo cáo tĩnh) | T24: GRI 2-15
A25: =ROW()-2 -> 23 | B25: Tổ Thư ký | D25: Phase 1 | E25: GRI 2-16 | F25: Governance | J25: Báo cáo các mối quan ngại nghiêm trọng | L25: =VLOOKUP(#REF!,'29 Chỉ tiêu Text'!$C$2:$F$30,4,0) -> #REF!
A26: =ROW()-2 -> 24 | B26: Tổ Thư ký | D26: Phase 1 | E26: GRI 2-17 | F26: Governance | J26: Kiến thức tập thể của cơ quan quản lý cao nhất | L26: =VLOOKUP(#REF!,'29 Chỉ tiêu Text'!$C$2:$F$30,4,0) -> #REF!
A27: =ROW()-2 -> 25 | B27: Tổ Thư ký | D27: Phase 1 | E27: GRI 2-18 | F27: Governance | J27: Đánh giá hiệu quả hoạt động của cơ quan quản trị cao nhất | L27: =VLOOKUP(#REF!,'29 Chỉ tiêu Text'!$C$2:$F$30,4,0) -> #REF!
A28: =ROW()-2 -> 26 | B28: TCNL | D28: Phase 2 | E28: GRI 2-21 | F28: Social | G28: Labor Conditions | K28: Annual total compensation ratio | T28: GRI 2-21
A29: =ROW()-2 -> 27 | B29: Tổ Thư ký | D29: Phase 1 | E29: GRI 2-23 | F29: Governance | G29: Conduct and Compliance | J29: Các cam kết về chính sách | K29: Policy commitments | L29: =VLOOKUP(#REF!,'29 Chỉ tiêu Text'!$C$2:$F$30,4,0) -> #REF! | M29: Text only (báo cáo tĩnh) | T29: GRI 2-23
A30: =ROW()-2 -> 28 | B30: Tổ Thư ký | D30: Phase 1 | E30: GRI 2-24 | F30: Governance | J30: Lồng ghép các cam kết chính sách | L30: =VLOOKUP(#REF!,'29 Chỉ tiêu Text'!$C$2:$F$30,4,0) -> #REF!
A31: =ROW()-2 -> 29 | B31: Tổ Thư ký | D31: Phase 1 | E31: GRI 2-25 | F31: Governance | J31: Quy trình khắc phục các tác động tiêu cực | L31: =VLOOKUP(#REF!,'29 Chỉ tiêu Text'!$C$2:$F$30,4,0) -> #REF!
A32: =ROW()-2 -> 30 | B32: Tổ Thư ký | D32: Phase 1 | E32: GRI 2-26 | F32: Governance | G32: Conduct and Compliance | J32: Cơ chế tham vấn, phản ánh các vấn đề đạo đức | K32: Mechanisms for seeking advice and raising concerns about ethics | L32: =VLOOKUP(#REF!,'29 Chỉ tiêu Text'!$C$2:$F$30,4,0) -> #REF! | M32: Text only (báo cáo tĩnh) | T32: GRI 2-26
A33: =ROW()-2 -> 31 | B33: Tổ Thư ký | D33: Phase 1 | E33: GRI 2-27 | F33: Governance | J33: Tuân thủ pháp luật và các quy định | L33: =VLOOKUP(#REF!,'29 Chỉ tiêu Text'!$C$2:$F$30,4,0) -> #REF!
A34: =ROW()-2 -> 32 | B34: Tổ Thư ký | D34: Phase 1 | E34: GRI 2-29 | F34: Governance | G34: Conduct and Compliance | J34: Tiếp cận đối thoại các bên liên quan | K34: Approach to stakeholder engagement | L34: =VLOOKUP(#REF!,'29 Chỉ tiêu Text'!$C$2:$F$30,4,0) -> #REF! | M34: Text only (báo cáo tĩnh) | T34: GRI 2-29
A35: =ROW()-2 -> 33 | B35: TCNL | D35: Phase 1 | E35: GRI 2-30 | F35: Social | G35: Labor Conditions | J35: Thỏa ước lao động tập thể | K35: Collective bargaining agreements | M35: Text only (báo cáo tĩnh) | T35: GRI 2-30
A36: =ROW()-2 -> 34 | B36: TCNL | D36: Phase 2 | E36: GRI 2-6 | F36: Social | G36: Labor Conditions | K36: Activities, value chain and other business relationships | T36: GRI 2-6
A37: =ROW()-2 -> 35 | B37: Tổ dịch vụ | D37: Phase 2 | E37: GRI 2-6 | F37: Social | G37: Supply Chain Sustainability | K37: Activities, value chain and other business relationships | T37: GRI 2-6
A38: =ROW()-2 -> 36 | B38: TCNL | D38: Phase 1 | E38: GRI 2-7 | F38: Social | G38: Labor Conditions | H38: Quy mô tổ chức | I38: Scale of the organization | K38: Scale of the organization | M38: Dashboard | N38: Skyhr | Q38: N/A | R38: 2 | S38: Yes | T38: GRI 2-7-01 GRI 2-7-02 | U38: 1. Lao động 31/12 - Number of employees as of December 31 2. Lao động sử dụng bình quân năm - Average Employee | V38: ≥ KH | W38: Nhập thủ công | X38: - Năm | Y38: No
A39: =ROW()-2 -> 37 | B39: Tổ Thư ký | D39: Phase 1 | E39: GRI 2-9 | F39: Governance | G39: Conduct and Compliance | J39: Cơ cấu và thành phần quản trị | K39: Governance structure and composition | L39: =VLOOKUP(#REF!,'29 Chỉ tiêu Text'!$C$2:$F$30,4,0) -> #REF! | M39: Text only (báo cáo tĩnh) | T39: GRI 2-9
A40: =ROW()-2 -> 38 | B40: Tổ dịch vụ | D40: Phase 2 | E40: GRI 301-1 | F40: Environment | G40: Waste and Effluents | K40: Materials used by weight or volume | T40: GRI 301-1
A41: =ROW()-2 -> 39 | B41: Tổ dịch vụ | D41: Phase 2 | E41: GRI 301-2 | F41: Environment | G41: Waste and Effluents | K41: Recycled input materials used | T41: GRI 301-2
A42: =ROW()-2 -> 40 | B42: Tổ dịch vụ | D42: Phase 2 | E42: GRI 301-3 | F42: Environment | G42: Waste and Effluents | K42: Reclaimed products and their packaging materials | T42: GRI 301-3
A43: =ROW()-2 -> 41 | B43: Tổ khai thác | D43: Phase 1 | E43: GRI 302-1 | F43: Environment | G43: Energy and Emissions | H43: Năng lượng tiêu thụ trong tổ chức | I43: Energy consumption within the organization | K43: Energy consumption within the organization | M43: Dashboard | N43: FIMS + ANCM | Q43: Pending | R43: Pending | S43: Yes | T43: GRI 302-1 | U43: Energy consumption within the organization/Năng lượng tiêu thụ trong tổ chức | V43: < KH | W43: PMS | X43: - Năm | Y43: Yes | Z43: Lấy Số KH từ nguồn pms
A44: =ROW()-2 -> 42 | B44: Tổ Khai thác | D44: Phase 2 | E44: GRI 302-2 | F44: Environment | G44: Energy and Emissions | K44: Energy consumption outside of the organization | T44: GRI 302-2
A45: =ROW()-2 -> 43 | B45: Tổ khai thác | D45: Phase 1 | E45: GRI 302-4 | F45: Environment | G45: Energy and Emissions | H45: Giảm tiêu thụ năng lượng | I45: Reduction of energy consumption | K45: Reduction of energy consumption | M45: Dashboard | N45: Excel | O45: Tổ Khai thác - GRI 302-4 - Giảm tiêu thụ năng lượng | P45: 2 | Q45: 2 | R45: 2 | S45: Yes | T45: GRI 302-4 | U45: Reduction of energy consumption/Giảm tiêu thụ năng lượng | V45: ≥ KH | W45: Nhập thủ công | X45: - Năm | Y45: Yes | Z45: Note: có tổng cộng 2 KPI, KPI sau được tính toán dựa trên KPI ban đầu | AA45: - Có 1 hệ số quy đổi từ Kg sang Lít
A46: =ROW()-2 -> 44 | B46: Tổ dịch vụ | D46: Phase 2 | E46: GRI 303-1 | F46: Environment | G46: Energy and Emissions | K46: Interactions with water as a shared resource | T46: GRI 303-1
A47: =ROW()-2 -> 45 | B47: Tổ dịch vụ | D47: Phase 2 | E47: GRI 303-2 | F47: Environment | G47: Energy and Emissions | K47: Management of water discharge-related impacts | T47: GRI 303-2
A48: =ROW()-2 -> 46 | B48: Tổ dịch vụ | C48: Mr Hải | D48: Phase 1 | E48: GRI 303-3 | F48: Environment | G48: Energy and Emissions | H48: Lượng nước cấp lên | I48: Water Withdrawal | K48: Water withdrawal | M48: Dashboard | N48: Excel + Acars + FIMS | P48: 2 | Q48: 2 | R48: 2 | S48: Yes | T48: GRI 303-3 | U48: Water withdrawal/Lượng nước cấp lên | V48: < KH | W48: Nhập thủ công | X48: - Năm | Y48: Yes | Z48: Hiện chưa đưa lên báo cáo nội bộ, bổ sung vào các năm tới
A49: =ROW()-2 -> 47 | B49: Tổ dịch vụ | C49: Mr Hải | D49: Phase 2 | E49: GRI 303-4 | F49: Environment | G49: Energy and Emissions | K49: Water discharge | T49: GRI 303-4
A50: =ROW()-2 -> 48 | B50: Tổ dịch vụ | C50: Mr Hải | D50: Phase 1 | E50: GRI 303-5 | F50: Environment | G50: Energy and Emissions | H50: Lượng nước tiêu thụ | I50: Water Consumption | K50: Water consumption | M50: Dashboard | N50: Excel + Acars + FIMS | P50: 2 | Q50: 2 | R50: 2 | S50: Yes | T50: GRI 303-5 | U50: Water consumption/Lượng nước tiêu thụ | V50: < KH | W50: Nhập thủ công | X50: - Năm | Y50: Yes | Z50: Hiện chưa đưa lên báo cáo nội bộ, bổ sung vào các năm tới
A51: =ROW()-2 -> 49 | B51: Tổ khai thác | D51: Phase 1 | E51: GRI 305-1 | F51: Environment | G51: Energy and Emissions | H51: Phát thải khí nhà kính trực tiếp (Phạm vi 1) | I51: Direct (Scope 1) GHG emissions | K51: Direct (Scope 1) GHG emissions | M51: Dashboard | N51: FIMS + ANCM PMS | Q51: Pending | R51: Pending | S51: Yes | T51: GRI 305-1 | U51: Direct (Scope 1) GHG emissions/Phát thải khí nhà kính trực tiếp (Phạm vi 1) | V51: ≤ KH | W51: Nhập thủ công | X51: - Năm | Y51: Yes | AA51: Có 3 hệ số: - Hệ số phát thải CO2 của nhiên liệu Jet A-1 - Hệ số quy đổi từ Kg sang Tấn - Hệ số quy đổi từ Lít sang Kg
A52: =ROW()-2 -> 50 | B52: Tổ dịch vụ | D52: Phase 2 | E52: GRI 305-2 | F52: Environment | G52: Energy and Emissions | K52: Energy indirect (Scope 2) GHG emissions | T52: GRI 305-2
A53: =ROW()-2 -> 51 | B53: Tổ khai thác | D53: Phase 2 | E53: GRI 305-3 | F53: Environment | G53: Energy and Emissions | K53: Other indirect (Scope 3) GHG emissions | T53: GRI 305-3
A54: =ROW()-2 -> 52 | B54: Tổ khai thác | D54: Phase 1 | E54: GRI 305-4 | F54: Environment | G54: Energy and Emissions | H54: Cường độ phát thải khí nhà kính | I54: GHG Emissions Intensity | K54: GHG emissions intensity | M54: Dashboard | N54: FIMS + EU_ETS + RPS | Q54: Pending | R54: Pending | S54: Yes | T54: GRI 305-4 | U54: GHG emissions intensity/Cường độ phát thải khí nhà kính | V54: ≤ KH | W54: Nhập thủ công | X54: - Năm | Y54: Yes
A55: =ROW()-2 -> 53 | B55: Tổ khai thác | D55: Phase 1 | E55: GRI 305-5 | F55: Environment | G55: Energy and Emissions | H55: Giảm phát thải khí nhà kính | I55: Reduction of GHG Emissions | K55: Reduction of GHG emissions | M55: Dashboard | N55: ANCM +Excel | P55: 2 | Q55: 2 | R55: Pending | S55: Yes | T55: GRI 305-5 | U55: Reduction of GHG emissions/Giảm phát thải khí nhà kính | V55: ≤ KH | W55: Nhập thủ công | X55: - Năm | Y55: Yes
A56: =ROW()-2 -> 54 | B56: Ban ATCL | D56: Phase 2 | E56: GRI 305-6 | F56: Environment | G56: Energy and Emissions | K56: Emissions of ozone-depleting substances (ODS) | T56: GRI 305-6
A57: =ROW()-2 -> 55 | B57: Tổ Khai thác | D57: Phase 2 | E57: GRI 305-7 | F57: Environment | G57: Energy and Emissions | K57: Nitrogen oxides (NOX), sulfur oxides (SOX), and other significant air emissions | M57: Phase 2 do Tổ Khai thác chưa có công thức tính | Q57: Pending | R57: Pending | T57: GRI 305-7
A58: =ROW()-2 -> 56 | B58: Tổ dịch vụ | D58: Phase 2 | E58: GRI 306-1 | F58: Environment | G58: Waste and Effluents | K58: Waste generation and significant waste-related impacts | T58: GRI 306-1
A59: =ROW()-2 -> 57 | B59: Tổ dịch vụ | D59: Phase 2 | E59: GRI 306-3 | F59: Environment | G59: Waste and Effluents | K59: Waste generated | T59: GRI 306-3
A60: =ROW()-2 -> 58 | B60: Tổ dịch vụ | D60: Phase 2 | E60: GRI 306-4 | F60: Environment | G60: Waste and Effluents | K60: Waste diverted from disposal | T60: GRI 306-4
A61: =ROW()-2 -> 59 | B61: Tổ dịch vụ | D61: Phase 2 | E61: GRI 306-5 | F61: Environment | G61: Waste and Effluents | K61: Waste directed to disposal | T61: GRI 306-5
A62: =ROW()-2 -> 60 | B62: Tổ dịch vụ | D62: Phase 2 | E62: GRI 308-2 | F62: Social | G62: Supply Chain Sustainability | K62: Negative environmental impacts in the supply chain and actions taken | T62: GRI 308-2
A63: =ROW()-2 -> 61 | B63: Tổ dịch vụ | D63: Phase 2 | E63: GRI 308-2 | F63: Environment | G63: Waste and Effluents | K63: Negative environmental impacts in the supply chain and actions taken | T63: GRI 308-2
A64: =ROW()-2 -> 62 | B64: Tổ Thư ký | D64: Phase 1 | E64: GRI 3-3 | F64: Governance | G64: Conduct and Compliance | J64: Quản lý các chủ đề trọng yếu | K64: Management of material topics | L64: =VLOOKUP(#REF!,'29 Chỉ tiêu Text'!$C$2:$F$30,4,0) -> #REF! | M64: Text only (báo cáo tĩnh) | T64: GRI 3-3
A65: =ROW()-2 -> 63 | B65: Ban ATCL | D65: Phase 2 | E65: GRI 3-3 | F65: Environment | G65: Noise | J65: Quản lý các chủ đề trọng yếu | K65: Management of material topics | T65: GRI 3-3
A66: =ROW()-2 -> 64 | B66: TCNL | D66: Phase 2 | E66: GRI 3-3 | F66: Social | G66: Labor Conditions | J66: Quản lý các chủ đề trọng yếu | K66: Management of material topics | T66: GRI 3-3
A67: =ROW()-2 -> 65 | B67: TCNL | D67: Phase 2 | E67: GRI 3-3 | F67: Social | G67: People and Development | J67: Quản lý các chủ đề trọng yếu | K67: Management of material topics | T67: GRI 3-3
A68: =ROW()-2 -> 66 | B68: Tổ dịch vụ | D68: Phase 2 | E68: GRI 3-3 | F68: Social | G68: Customer Experience | J68: Quản lý các chủ đề trọng yếu | K68: Management of material topics | T68: GRI 3-3
A69: =ROW()-2 -> 67 | B69: Tổ dịch vụ | D69: Phase 2 | E69: GRI 3-3 | F69: Social | G69: Supply Chain Sustainability | J69: Quản lý các chủ đề trọng yếu | K69: Management of material topics | T69: GRI 3-3
A70: =ROW()-2 -> 68 | B70: Tổ dịch vụ | D70: Phase 2 | E70: GRI 3-3 | F70: Environment | G70: Waste and Effluents | J70: Quản lý các chủ đề trọng yếu | K70: Management of material topics | T70: GRI 3-3
A71: =ROW()-2 -> 69 | B71: Tổ khai thác | D71: Phase 2 | E71: GRI 3-3 | F71: Environment | G71: Energy and Emissions | J71: Quản lý các chủ đề trọng yếu | K71: Management of material topics | T71: GRI 3-3
A72: =ROW()-2 -> 70 | B72: TCNL | D72: Phase 1 | E72: GRI 401-1 | F72: Social | G72: Labor Conditions | H72: Tuyển dụng và nghỉ việc | I72: New employee hires and employee turnover | K72: New employee hires and employee turnover | M72: Dashboard | N72: Skyhr | Q72: N/A | R72: 1 | S72: Yes | T72: GRI 401-1-01 GRI 401-1-02 | U72: 1. Tuyển dụng mới - New Hires 2. Tỷ lệ thôi việc tự nguyện - Voluntary Turnover Rate | V72: Tuyển mới: ≥ KH Nghỉ việc: ≤ KH | W72: Nhập thủ công | X72: - Năm | Y72: No
A73: =ROW()-2 -> 71 | B73: TCNL | D73: Phase 1 | E73: GRI 401-2 | F73: Social | G73: Labor Conditions | J73: Phúc lợi cho nhân viên toàn thời gian | K73: Benefits provided to full-time employees that are not provided to temporary or part-time employees | M73: Text only (báo cáo tĩnh) | T73: GRI 401-2
A74: =ROW()-2 -> 72 | B74: TCNL | D74: Phase 2 | E74: GRI 401-3 | F74: Social | G74: Labor Conditions | K74: Parental leave | T74: GRI 401-3
A75: =ROW()-2 -> 73 | B75: TCNL | D75: Phase 2 | E75: GRI 402-1 | F75: Social | G75: Labor Conditions | K75: Minimum notice periods regarding operational changes | T75: GRI 402-1
A76: =ROW()-2 -> 74 | B76: TCNL | D76: Phase 2 | E76: GRI 403 | F76: Social | G76: People and Development | K76: Occupational Health and Safety | T76: GRI 403 (all)
A77: =ROW()-2 -> 75 | B77: TCNL | D77: Phase 1 | E77: GRI 403-10 | F77: Social | G77: Labor Conditions | J77: Sự cố phân biệt đối xử và biện pháp xử lý | K77: Work-related ill-health | M77: Text only (báo cáo tĩnh) | T77: GRI 403-10
A78: =ROW()-2 -> 76 | B78: Ban ATCL | C78: Mr Đàn | D78: Phase 1 | E78: GRI 403-2 | F78: Social | G78: Labor Conditions | H78: Nhận diện mối nguy, phân tích rủi ro và điều tra sự cố | I78: Hazard identification, risk assessment, and incident investigation | K78: Hazard identification, risk assessment, and incident investigation | M78: Dashboard | N78: -VHAT | Q78: N/A | R78: 1 | S78: No | T78: GRI 403-2
A79: =ROW()-2 -> 77 | B79: TCNL | D79: Phase 1 | E79: GRI 403-4 | F79: Social | G79: Labor Conditions | J79: Các chương trình NLĐ tham gia, đóng góp ý kiến và trao đổi về các chính sách sức khỏe và an toàn nghề nghiệp | K79: Worker participation, consultation, and communication on occupational health and safety | M79: Text only (báo cáo tĩnh) | T79: GRI 403-4
A80: =ROW()-2 -> 78 | B80: TCNL | D80: Phase 1 | E80: GRI 403-9 | F80: Social | G80: Labor Conditions | H80: Thương tật do lao động | I80: Work-related Injuries | K80: Work-related injuries | M80: Dashboard | N80: Excel | O80: GRI 403-9 - form thống kê thương tật | P80: 2 | Q80: 2 | R80: 2 | S80: No | T80: GRI 403-9
A81: =ROW()-2 -> 79 | B81: TCNL | D81: Phase 1 | E81: GRI 404-2 | F81: Social | G81: People and Development | H81: Chương trình nâng cao kỹ năng | I81: Programs for upgrading employee skills and transition assistance programs | K81: Programs for upgrading employee skills and transition assistance programs | M81: Dashboard | N81: Skyhr | Q81: N/A | R81: 2 | S81: No | T81: GRI 404-2
A82: =ROW()-2 -> 80 | B82: TCNL | D82: Phase 1 | E82: GRI 404-3 | F82: Social | G82: People and Development | J82: Phát triển nghề nghiệp | K82: Percentage of employees receiving regular performance and career development reviews | M82: Text only (báo cáo tĩnh) | T82: GRI 404-3
A83: =ROW()-2 -> 81 | B83: TCNL | D83: Phase 1 | E83: GRI 405-1 | F83: Social | G83: Labor Conditions | H83: Đa dạng trong quản trị | I83: Diversity of governance bodies and employees | K83: Diversity of governance bodies and employees | M83: Dashboard | N83: Skyhr | Q83: N/A | R83: 1 | S83: No | T83: GRI 405-1 | U83: Diversity of governance bodies and employees/Đa dạng trong cơ quan quản trị | V83: ≥ KH | W83: Nhập thủ công | Y83: No
A84: =ROW()-2 -> 82 | B84: TCNL | D84: Phase 2 | E84: GRI 405-2 | F84: Social | G84: Labor Conditions | K84: Ratio of basic salary and remuneration of women to men | T84: GRI 405-2
A85: =ROW()-2 -> 83 | B85: TCNL | D85: Phase 1 | E85: GRI 406-1 | F85: Social | G85: Labor Conditions | J85: Sự cố phân biệt đối xử và biện pháp xử lý | K85: Incidents of discrimination and corrective actions taken | M85: Text only (báo cáo tĩnh) | T85: GRI 406-1
A86: =ROW()-2 -> 84 | B86: Tổ dịch vụ | C86: MS Hiền | D86: Phase 1 | E86: GRI 406-1 | F86: Social | G86: Customer Experience | H86: Sự cố phân biệt đối xử và biện pháp xử lý (Phần khách hàng) | I86: Incidents of discrimination and corrective actions taken (Customers) | J86: Sự cố phân biệt đối xử và biện pháp xử lý | K86: Incidents of discrimination and corrective actions taken | M86: Dashboard | N86: Report Pro | Q86: N/A | R86: 2 | S86: Yes | T86: GRI 406-1 | U86: Incidents of discrimination and corrective actions taken/Số sự cố phân biệt đối xử và biện pháp xử lý | V86: ≤ KH | W86: Nhập thủ công | X86: - Năm | Y86: Yes | Z86: chỉ với phần khách hàng
A87: =ROW()-2 -> 85 | B87: TCNL | D87: Phase 2 | E87: GRI 407-1 | F87: Social | G87: Labor Conditions | K87: Operations and suppliers in which the right to freedom of association and collective bargaining may be at risk | T87: GRI 407-1
A88: =ROW()-2 -> 86 | B88: TCNL | D88: Phase 2 | E88: GRI 408-1 | F88: Social | G88: Labor Conditions | K88: Operations and suppliers at significant risk for incidents of child labor | T88: GRI 408-1
A89: =ROW()-2 -> 87 | B89: TCNL | D89: Phase 2 | E89: GRI 409-1 | F89: Social | G89: Labor Conditions | K89: Operations and suppliers at significant risk for incidents of forced or compulsory labor | T89: GRI 409-1
A90: =ROW()-2 -> 88 | B90: TCNL | D90: Phase 2 | E90: GRI 412-1 | F90: Social | G90: Labor Conditions | K90: Operations that have been subject to human rights reviews or impact assessments | T90: GRI 412-1
A91: =ROW()-2 -> 89 | B91: Ban ATCL | D91: Phase 2 | E91: GRI 413-2 | F91: Environment | G91: Noise | K91: Operations with significant actual and potential negative impacts on local communities | T91: GRI 413-2
A92: =ROW()-2 -> 90 | B92: TCNL | D92: Phase 2 | E92: GRI 414-1 | F92: Social | G92: Labor Conditions | K92: New suppliers that were screened using social criteria | T92: GRI 414-1
A93: =ROW()-2 -> 91 | B93: TCNL | D93: Phase 2 | E93: GRI 414-2 | F93: Social | G93: Labor Conditions | K93: Negative social impacts in the supply chain and actions taken | T93: GRI 414-2
A94: =ROW()-2 -> 92 | B94: Tổ dịch vụ | D94: Phase 2 | E94: GRI 414-2 | F94: Social | G94: Supply Chain Sustainability | K94: Negative social impacts in the supply chain and actions taken | T94: GRI 414-2
A95: =ROW()-2 -> 93 | B95: Tổ Thư ký | D95: Phase 1 | E95: GRI 415-1 | F95: Governance | G95: Conduct and Compliance | J95: Đóng góp cho các hoạt động chính trị | K95: Political contributions | L95: =VLOOKUP(#REF!,'29 Chỉ tiêu Text'!$C$2:$F$30,4,0) -> #REF! | M95: Text only (báo cáo tĩnh) | T95: GRI 415-1
A96: =ROW()-2 -> 94 | B96: Tổ dịch vụ | C96: MS Hiền | D96: Phase 1 | E96: GRI 416-1 | F96: Environment | G96: Customer Experience | H96: Đánh giá tác động sức khỏe và an toàn của các sản phẩm/dịch vụ | I96: Assessment of the health and safety impacts of product and service categories | K96: Assessment of the health and safety impacts of product and service categories | M96: Dashboard | N96: Excel | O96: GRI 416-1 - Danh mục VSTB GRI 416-1 - Danh mục suất ăn GRI 416-1 - Phân nhóm vật tư vật phẩm | P96: 2 | Q96: 2 | R96: 2 | S96: Yes | T96: GRI 416-1 | U96: Tỷ lệ sản phẩm được đánh giá trước khai thác/Percentage of Products Assessed Before Being Put into Service | V96: >=KH | W96: Nhập thủ công | Y96: No
A97: =ROW()-2 -> 95 | B97: Tổ dịch vụ | C97: Nguyễn Thị Hằng | D97: Phase 1 | E97: GRI 416-2 | F97: Environment | G97: Customer Experience | H97: Các sự cố vi phạm liên quan đến tác động sức khỏe và an toàn của sản phẩm/dịch vụ | I97: Incidents of noncompliance concerning the health and safety impacts of products and services | K97: Incidents of non-compliance concerning the health and safety impacts of products and services | M97: Dashboard | N97: Excel | O97: GRI 416-2 - Các sự cố vi phạm liên quan đến tác động sức khỏe và an toàn của sản phẩm dịch vụ | P97: 1 | Q97: 1 | R97: 1 | S97: Yes | T97: GRI 416-2 | U97: Các sự cố vi phạm liên quan đến tác động sức khỏe và an toàn của sản phẩm/dịch vụ / Incidents of non-compliance concerning the health and safety impacts of products and services | V97: ≤ KH | W97: Nhập thủ công | X97: -Năm | Y97: Yes | Z97: hiện tại = 0 có thể thay đổi sau này, tần suất cập nhật dữ liệu 1 năm/lần
A98: =ROW()-2 -> 96 | B98: Tổ dịch vụ | D98: Phase 2 | E98: GRI 417-1 | F98: Social | G98: Customer Experience | K98: Requirements for product and service information and labeling | T98: GRI 417-1
A99: =ROW()-2 -> 97 | B99: Tổ dịch vụ | C99: Nguyễn Thị Hằng | D99: Phase 1 | E99: GRI 417-2 | F99: Environment | G99: Customer Experience | H99: Các sự cố vi phạm về thông tin và nhãn sản phẩm/dịch vụ | I99: Incidents of noncompliance concerning product and service information and labeling | K99: Incidents of non-compliance concerning product and service information and labeling | M99: Dashboard | N99: Excel | O99: GRI 417-2 - Các sự cố vi phạm về thông tin và nhãn sản phẩm/dịch vụ | P99: 1 | Q99: 1 | R99: 1 | S99: Yes | T99: GRI 417-2 | U99: Các sự cố vi phạm về thông tin và nhãn sản phẩm/dịch vụ / Incidents of non-compliance concerning product and service information and labeling | V99: ≤ KH | W99: Nhập thủ công | X99: -Năm | Y99: Yes | Z99: hiện tại = 0 có thể thay đổi sau này, tần suất cập nhật dữ liệu 1 năm/lần
A100: =ROW()-2 -> 98 | B100: Ban TT | D100: Phase 1 | E100: GRI 417-3 | F100: Social | G100: Customer Experience | H100: Các vụ việc không tuân thủ liên quan đến truyền thông marketing | I100: Incidents of non-compliance concerning marketing communications | K100: Incidents of non-compliance concerning marketing communications | M100: Dashboard | N100: Excel | O100: GRI 417-3 - Incidents of non-compliance concerning marketing communications - Các vụ việc không tuân thủ liên quan đến truyền thông marketing | P100: 1 | Q100: 1 | R100: 2 | S100: No | Y100: No
...

Sheet 29 Chỉ tiêu Text
A1: TT | B1: Trụ cột | C1: Mã GRI | D1: Chỉ tiêu (Eng) | E1: Chỉ tiêu (Vie) | F1: Yêu cầu của GRI | G1: Câu hỏi | H1: Hiện trạng | I1: PIC | J1: Nội dung hiển thị cho VNA
A2: 1 | B2: Xã hội | C2: GRI 401-2 | D2: Benefits provided to full-time employees that are not provided to temporary or part-time employees | E2: Phúc lợi cho nhân viên toàn thời gian | F2: 1. Các phúc lợi tiêu chuẩn được cung cấp cho nhân viên làm việc toàn thời gian của tổ chức 2. Danh sách các phúc lợi này bao gồm: (i) Bảo hiểm nhân thọ (Life insurance). (ii) Chăm sóc sức khỏe y tế (Health care). (iii) Bảo hiểm thương tật và mất khả năng lao động (Disability and invalidity coverage). (iv) Chế độ nghỉ phép chăm con/thai sản (Parental leave). (v) Chế độ hưu trí (Retirement provision). (vi) Quyền sở hữu cổ phần (Stock ownership). (vii) Các phúc lợi khác. | G2: Tổng công ty đã có những chính sách đãi ngộ như thế nào đối với người lao động? | H2: Đáp ứng | I2: Ban TCNL | J2: Mọi nhân viên chính thức ký hợp đồng lao động trực tiếp với Vietnam Airlines đều được hưởng chế độ đãi ngộ toàn diện, vượt trội so với mặt bằng chung của thị trường lao động, bao gồm: Bảo hiểm sức khỏe, Bảo hiểm hưu trí tự nguyện nhóm, vé máy bay giảm cước trên các chặng bay của Vietnam Airlines và đối tác liên kết (vé ID/AD, my ID Travel); các chính sách nhân văn, gắn kết như hỗ trợ các gia đình thương binh liệt sỹ, quà sinh nhật người lao động, quà tặng 8/3, 20/10 dành cho lao động nữ, …
A3: 2 | B3: Xã hội | C3: GRI 403-4 | D3: Worker participation, consultation, and communication on occupational health and safety | E3: Các chương trình NLĐ tham gia, đóng góp ý kiến và trao đổi về các chính sách sức khỏe và an toàn nghề nghiệp | F3: 1. Quy trình tổ chức cho người lao động tham gia và tham vấn vào việc xây dựng, triển khai, cũng như đánh giá hệ thống quản lý an toàn và sức khỏe nghề nghiệp. 2. Cách thức tổ chức cung cấp quyền truy cập và truyền đạt các thông tin liên quan về an toàn, sức khỏe nghề nghiệp đến người lao động. 3. Thông tin chi tiết về các Ủy ban an toàn và sức khỏe chung (các ủy ban chính thức kết hợp giữa đại diện ban quản lý và người lao động) - nếu có tồn tại, dựa trên 4 tiêu chí bắt buộc: (i) Trách nhiệm của ủy ban; (ii) Tần suất tổ chức họp; (iii) Thẩm quyền ra quyết định của ủy ban; (iv) Tình trạng đại diện của người lao động (phải xác định rõ có nhóm lao động nào không được đại diện trong các ủy ban này không, và giải thích lý do tại sao). | G3: Tổng công ty có duy trì các kênh đối thoại và cơ chế đại diện cho người lao động trong công tác quản lý an toàn và sức khỏe nghề nghiệp không? | H3: Đáp ứng | I3: Ban TCNL | J3: Vietnam Airlines duy trì cơ chế đối thoại dân chủ trong công tác ATVSLĐ. Hội đồng ATVSLĐ của TCT được thành lập với 6 thành viên, trong đó đại diện người sử dụng lao động làm Chủ tịch; đại diện công đoàn Công đoàn TCT làm Phó Chủ tịch; đại diện Ban Tổ chức và nhân lực làm Ủy viên thường trực-Thư ký và các thành viên thuộc các ban An toàn chất lượng, An ninh Hàng không và Trạm y tế thuộc Đoàn bay 919. Hội đồng có nhiệm vụ tư vấn, phối hợp với người sử dụng lao động xây dựng nội quy, quy trình, kế hoạch và biện pháp ATVSLĐ; tổ chức đối thoại hằng năm giữa người lao động và người sử dụng lao động nhằm chia sẻ thông tin, tăng cường sự hiểu biết và thúc đẩy cải thiện các điều kiện làm việc công bằng, an toàn cho người lao động; nâng cao hiệu quả thực hiện chính sách, pháp luật về ATVSLĐ tại nơi làm việc; kiểm tra tình hình thực hiện tác ATVSLĐ; và yêu cầu người sử dụng lao động xử lý, khắc phục nguy cơ mất ATVSLĐ. Bên cạnh đó, kế hoạch ATVSLĐ hằng năm của các cơ quan, đơn vị trong TCT đều xây dựng nội dung “Thông tin, tuyên truyền, giáo dục về ATVSLĐ
A4: 3 | B4: Xã hội | C4: GRI 403-10 | D4: Work-related ill health | E4: Sự cố phân biệt đối xử và biện pháp xử lý | F4: 1. Số liệu thống kê về bệnh nghề nghiệp, được báo cáo tách biệt cho 2 nhóm: (a) Nhân viên của tổ chức (Employees) và (b) Người lao động không phải nhân viên nhưng công việc hoặc nơi làm việc do tổ chức kiểm soát. Dữ liệu mỗi nhóm phải bao gồm 3 chỉ tiêu: (i) Số ca tử vong do bệnh nghề nghiệp; (ii) Số ca mắc bệnh nghề nghiệp / suy giảm sức khỏe liên quan đến công việc có thể ghi nhận được (recordable cases); (iii) Các loại bệnh nghề nghiệp / suy giảm sức khỏe chính. 2. Thông tin phân tích về các mối nguy hiểm liên quan đến công việc (work-related hazards) có nguy cơ gây bệnh, dựa trên 3 tiêu chí: (i) Cách thức tổ chức xác định các mối nguy hiểm này; (ii) Các mối nguy hiểm cụ thể đã gây ra hoặc góp phần gây ra các ca bệnh trong kỳ báo cáo; (iii) Các hành động đã hoặc đang được thực hiện nhằm loại trừ mối nguy hiểm và giảm thiểu rủi ro. | G4: Tổng công ty đã kiểm soát và ghi nhận số liệu về bệnh nghề nghiệp đối với toàn bộ nhân viên như thế nào? | H4: Đáp ứng | I4: Ban TCNL | J4: Vietnam Airlines đặt sức khỏe thể chất và tinh thần của người lao động là ưu tiên hàng đầu trong quản trị ATVSLĐ. Trong kỳ báo cáo, TCT tiếp tục duy trì thành tích xuất sắc với 0 ca bệnh nghề nghiệp mới phát sinh. Để bảo đảm sức khỏe khai thác cho tổ bay, hãng tuân thủ tuyệt đối quy trình quản trị mệt mỏi phi hành đoàn (FRMS), bảo đảm 100% số giờ nghỉ ngơi tối thiểu giữa các ca bay đạt chuẩn an toàn. Đồng thời, định kỳ hàng năm TCT tổ chức khám sức khỏe cho toàn thể người lao động ít nhất 1 lần/ năm, một số lao động đặc thù được khám 2 lần/ năm hoặc khám bệnh nghề nghiệp chuyên sâu tại các cơ sở y tế đạt chuẩn, chi phí do TCT chi trả.
A5: 4 | B5: Xã hội | C5: GRI 406-1 | D5: Incidents of discrimination and corrective actions taken | E5: Sự cố phân biệt đối xử và biện pháp xử lý (Phần nhân sự) | F5: 1. Tổng số vụ việc phân biệt đối xử đã xảy ra và được ghi nhận trong kỳ báo cáo. 2. Tình trạng của các vụ việc và các hành động khắc phục tương ứng, được phân loại cụ thể theo 4 trạng thái bắt buộc: (i) Vụ việc đã được tổ chức tiếp nhận và đang xem xét/điều tra; (ii) Kế hoạch khắc phục (remediation plans) đang trong quá trình triển khai thực hiện; (iii) Kế hoạch khắc phục đã được triển khai hoàn tất (kèm theo kết quả đã được đánh giá thông qua các quy trình kiểm tra quản lý nội bộ định kỳ); (iv) Vụ việc đã khép lại và không còn thuộc diện phải tiếp tục xử lý hoặc hành động thêm. | G5: Tổng công ty có đảm bảo môi trường làm việc không xảy ra các hành vi kỳ thị hay phân biệt đối xử đối với người lao động không? | H5: Đáp ứng | I5: Ban TCNL | J5: Trong kỳ báo cáo, TCT ghi nhận 0 ý kiến về phân biệt đối xử hay kỳ thị đối với nhân viên nội bộ. TCT duy trì nguyên tắc bình đẳng, không chấp nhận hành vi xúc phạm, đe dọa hoặc phân biệt đối xử trong môi trường làm việc.
A6: 5 | B6: Xã hội | C6: GRI 2-30 | D6: Collective bargaining agreements | E6: Thỏa ước lao động tập thể | F6: 1. Tỷ lệ phần trăm (%) tổng số nhân viên của tổ chức được điều chỉnh/bảo vệ bởi các thỏa ước lao động tập thể. (2) Cung cấp thông tin đối với những nhân viên không được điều chỉnh bởi các thỏa ước lao động tập thể. Cụ thể, tổ chức phải báo cáo rõ liệu các điều kiện làm việc và điều khoản sử dụng lao động của nhóm nhân viên này có được xác định dựa trên: (i) Các thỏa ước lao động tập thể đang được áp dụng cho các nhân viên khác trong cùng tổ chức hay không; hoặc (ii) Các thỏa ước lao động tập thể từ các tổ chức khác hay không. | G6: Các chế độ đãi ngộ dành cho người lao động có được áp dụng dựa trên cơ sở pháp lý và thỏa ước tương đương nào để bảo đảm tối đa quyền lợi? | H6: Đáp ứng | I6: Ban TCNL | J6: Vietnam Airlines tôn trọng, cam kết bảo vệ quyền và lợi ích hợp pháp của người lao động thông qua cơ chế đối thoại, thương lượng và thỏa thuận. 100% người lao động được bảo vệ quyền lợi tại Thỏa ước lao động tập thể. Hằng năm, Ban lãnh đạo TCT phối hợp chặt chẽ với Ban chấp hành Công đoàn TCT tổ chức Hội nghị người lao động và đối thoại định kỳ nhằm lắng nghe tâm tư, nguyện vọng và liên tục cải thiện điều kiện làm việc, quyền và lợi ích hợp pháp của người lao động.
A7: 6 | B7: Xã hội | C7: GRI 404-3 | D7: Percentage of employees receiving regular performance and career development reviews | F7: 1. Tỷ lệ phần trăm (%) tổng số nhân viên được đánh giá hiệu quả công việc và phát triển nghề nghiệp định kỳ trong kỳ báo cáo. 2. Dữ liệu về tỷ lệ phần trăm này phải được báo cáo phân loại chi tiết theo 2 tiêu chí: (i) Giới tính; (ii) Cấp bậc nhân viên. | G7: Tổng công ty đã triển khai quy trình đánh giá kết quả công việc và lộ trình phát triển nghề nghiệp định kỳ cho các nhóm nhân viên chưa? | H7: Đáp ứng | I7: Ban TCNL | J7: Vietnam Airlines cam kết xây dựng một môi trường làm việc công bằng và tạo động lực phát triển liên tục thông qua hệ thống đánh giá kết quả công việc được số hóa trên nền tảng SkyHR. Hàng tháng, công tác đánh giá hiệu quả công việc được thực hiện một cách khách quan, công khai và minh bạch, áp dụng đồng bộ hệ thống Thẻ điểm cân bằng (BSC) kết hợp với các chỉ số đo lường hiệu quả cốt lõi (KPI) và các trục chỉ số đánh giá theo mô hình quản trị hiện đại. Kết quả đánh giá thực hiện công việc này là căn cứ quan trọng để Tổng công ty thực thi các chính sách nhân sự bền vững, bao gồm: quy hoạch, bổ nhiệm, điều động, luân chuyển; xác định nhu cầu đào tạo, bồi dưỡng phát triển năng lực; xét nâng bậc, khen thưởng, kỷ luật và giải quyết các quan hệ lao động phát sinh.
A8: 7 | B8: Xã hội | C8: GRI 201-3 | D8: Defined benefit plan obligations and other retirement plans | E8: Cam kết chi trả lương hưu và phúc lợi | F8: 1. Nếu các nghĩa vụ của chương trình hưu trí được chi trả bằng nguồn tài chính chung của tổ chức, phải báo cáo giá trị ước tính của các khoản nghĩa vụ này. 2. Nếu có một quỹ riêng biệt được thiết lập để chi trả các khoản nghĩa vụ lương hưu của chương trình, cần báo cáo 3 thông tin: (i) Mức độ (tỷ lệ) mà các nghĩa vụ của quỹ được ước tính sẽ được đảm bảo chi trả bởi các tài sản đã được trích lập; (ii) Cơ sở phương pháp luận để đưa ra mức ước tính đó; (iii) Thời điểm thực hiện việc ước tính. | G8: Tổng công ty có thực hiện đầy đủ các khoản bảo hiểm, mức trích đóng cụ thể ra sao? | H8: Đáp ứng | I8: Ban TCNL | J8: Vietnam Airlines thực hiện đóng đầy đủ, đúng hạn các khoản bảo hiểm bắt buộc theo đúng các quy định của Nhà nước. Ngoài ra, để bảo đảm an sinh xã hội dài hạn và bổ sung, hỗ trợ tài chính/ thu nhập sau khi nghỉ hưu cho người lao động, tùy thuộc vào kết quả sản xuất kinh doanh hằng năm, TCT thực hiện đóng vào quỹ hưu trí tự nguyện nhóm. Tổng số tiền đóng tối đa 300 triệu VND/người lao động/hợp đồng, giúp người lao động hoàn toàn yên tâm đồng hành dài hạn cùng sự phát triển của hãng hàng không quốc gia."
A9: 8 | B9: Quản trị | C9: GRI 2-9 | D9: =VLOOKUP(C9,'95 Chỉ tiêu'!$B$4:$K$98,5,0) -> #N/A | E9: Cơ cấu và thành phần quản trị | F9: 1. Sơ đồ cơ cấu quản trị 2. Danh sách các Ủy ban thuộc HĐQT. 3. Bảng thành phần HĐQT và từng Ủy ban theo 8 tiêu chí bắt buộc của GRI: (i) thành viên điều hành / không điều hành; (ii) tính độc lập; (iii) nhiệm kỳ / thời gian đã tại vị; (iv) số vị trí kiêm nhiệm quan trọng khác và tính chất của việc kiêm nhiệm; (v) giới tính; (vi) nhóm xã hội yếu thế/ít được đại diện; (vii) năng lực liên quan đến tác động tới TCT; (viii) đại diện của các bên liên quan. | H9: Đáp ứng | I9: Tổ Thư ký | J9: Cơ cấu quản trị của Vietnam Airlines gồm ĐHĐCĐ, HĐQT, Ban Kiểm soát và TGĐ cùng bộ máy điều hành. HĐQT thành lập 02 tiểu ban: Tiểu ban Chiến lược và đầu tư; Tiểu ban Lao động và Tiền lương Thành phần Hội đồng quản trị: 07 thành viên, gồm 01 thành viên độc lập, thành viên người đại diện phần vốn nhà nước và đại diện ANA. Đối với PTBV, HĐQT giữ vai trò định hướng và giám sát cao nhất. BĐH Chương trình PTBV do TGĐ làm Trưởng ban là cơ quan chịu trách nhiệm ra quyết định và giám sát việc quản lý các tác động kinh tế, môi trường và con người; TTK là cơ quan thường trực điều phối chuyên môn; các Tổ công tác được thành lập theo từng lĩnh vực/chương trình để chủ trì triển khai. (vẽ sơ đồ tương tự báo cáo thường niên)
A10: 9 | B10: Quản trị | C10: GRI 2-10 | D10: =VLOOKUP(C10,'95 Chỉ tiêu'!$B$4:$K$98,5,0) -> #N/A | E10: Quy trình đề cử, lựa chọn cơ quan quản lý cao nhất | F10: 1. Quy trình đề cử, lựa chọn thành viên HĐQT và các tiểu ban 2. Tiêu chí lựa chọn — bắt buộc nêu rõ có xét đến và xét như thế nào đối với: (i) ý kiến của các bên liên quan (bao gồm cổ đông); (ii) tính đa dạng; (iii) tính độc lập; (iv) năng lực liên quan đến tác động PTBV của TCT. | H10: Đáp ứng | I10: Tổ Thư ký | J10: Thành viên HĐQT Vietnam Airlines do ĐHĐCĐ bầu theo phương thức bầu dồn phiếu. Quyền đề cử ứng viên được thực hiện theo tỷ lệ sở hữu cổ phần; Với tư cách doanh nghiệp có vốn nhà nước chi phối, việc giới thiệu người đại diện phần vốn nhà nước tham gia HĐQT được thực hiện theo quy định của Luật số 68/2025/QH15 và chỉ đạo của cơ quan đại diện chủ sở hữu. Trong quá trình đề cử và lựa chọn, TCT xem xét: ý kiến của cổ đông và các bên liên quan thông qua ĐHĐCĐ; tính độc lập của thành viên theo quy định pháp luật về công ty đại chúng; và năng lực, kinh nghiệm phù hợp với đặc thù ngành hàng không.
A11: 10 | B11: Quản trị | C11: GRI 2-11 | D11: =VLOOKUP(C11,'95 Chỉ tiêu'!$B$4:$K$98,5,0) -> #N/A | E11: Chủ tịch HĐQT | F11: Nêu rõ: Chủ tịch HĐQT có đồng thời là cán bộ điều hành cấp cao của TCT hay không. Nếu Chủ tịch kiêm nhiệm điều hành: phải mô tả chức năng điều hành, lý do bố trí và cách ngăn ngừa/giảm thiểu xung đột lợi ích. | H11: Đáp ứng | I11: Tổ Thư ký | J11: CT HĐQT Vietnam Airlines là ông Đặng Ngọc Hòa. CT HĐQT không đồng thời là cán bộ điều hành cấp cao của TCT: chức danh TGĐ - người đại diện theo pháp luật và điều hành hoạt động hằng ngày - do ông Lê Hồng Hà đảm nhiệm.
A12: 11 | B12: Quản trị | C12: GRI 2-12 | D12: =VLOOKUP(C12,'95 Chỉ tiêu'!$B$4:$K$98,5,0) -> #N/A | E12: Vai trò của HĐQT trong giám sát quản lý tác động | F12: 1. Vai trò của HĐQT và của cán bộ điều hành cấp cao trong việc xây dựng, phê duyệt và cập nhật: tầm nhìn/sứ mệnh/giá trị cốt lõi; chiến lược PTBV; các chính sách và mục tiêu PTBV. 2. Vai trò của HĐQT trong giám sát quy trình thẩm định chi tiết và các quy trình khác nhằm nhận diện và quản lý tác động kinh tế – môi trường – con người, gồm: (i) HĐQT có và tương tác với các bên liên quan như thế nào để hỗ trợ các quy trình này; (ii) HĐQT xem xét, sử dụng kết quả đầu ra của các quy trình này ra sao. 3. Vai trò của HĐQT trong rà soát tính hiệu quả của các quy trình nêu trên và tần suất rà soát. | H12: Đáp ứng | I12: Tổ Thư ký | J12: HĐQT là cơ quan quản lý cao nhất của Vietnam Airlines giữ vai trò định hướng và giám sát toàn diện đối với phát triển bền vững. TGĐ và BĐH Chương trình PTBV chịu trách nhiệm xây dựng, đề xuất và cập nhật các nội dung về tầm nhìn, sứ mệnh, giá trị cốt lõi, chiến lược PTBV để trình HĐQT. HĐQT giám sát các quy trình nhận diện, đánh giá và quản lý tác động kinh tế, môi trường và con người thông qua báo cáo của BĐH Chương trình PTBV. Rà soát hiệu quả: TTK họp hàng tháng, BĐH họp hàng quý, rà soát các chỉ tiêu PTBV và có báo cáo lên HĐQT nếu cần
A13: 12 | B13: Quản trị | C13: GRI 2-13 | D13: =VLOOKUP(C13,'95 Chỉ tiêu'!$B$4:$K$98,5,0) -> #N/A | E13: Ủy quyền trách nhiệm quản lý các tác động | F13: 1. Cách HĐQT phân cấp trách nhiệm quản lý tác động, gồm: (i) HĐQT có bổ nhiệm cán bộ điều hành cấp cao chịu trách nhiệm về quản lý tác động hay không; (ii) trách nhiệm có được giao tiếp cho người lao động khác hay không. 2. Quy trình báo cáo ngược lên HĐQT về việc quản lý tác động. | H13: Đáp ứng | I13: Tổ Thư ký | J13: Hội đồng quản trị phân cấp trách nhiệm quản lý các tác động kinh tế, môi trường và con người cho Tổng giám đốc và bộ máy điều hành. BĐH Chương trình PTBV do TGĐ làm Trưởng ban là đầu mối cấp cao nhất chịu trách nhiệm điều hành công tác PTBV của TCT. TTK là cơ quan thường trực, điều phối chuyên môn và tham mưu tổng hợp, chịu sự chỉ đạo trực tiếp của Trưởng BĐH và PTBTT. Các Tổ công tác được thành lập theo từng lĩnh vực để chủ trì triển khai và chịu trách nhiệm về kết quả trong phạm vi được giao. Ở cấp thực thi, trách nhiệm được giao tiếp cho các Ban chức năng và đơn vị theo lĩnh vực chuyên môn: kiểm kê và giảm phát thải, quản lý nhiên liệu, mua sắm, nhân sự, dịch vụ hành khách, an toàn – chất lượng. Cơ chế báo cáo ngược: BĐH Chương trình Phát triển bền vững tổng hợp và báo cáo HĐQT về tiến độ, kết quả và các vấn đề phát sinh trong quản lý tác động PTBV.
A14: 13 | B14: Quản trị | C14: GRI 2-14 | E14: Vai trò của cơ quan quản trị cao nhất trong báo cáo bền vững | F14: Cần chỉ rõ: HĐQT có chịu trách nhiệm rà soát và phê duyệt thông tin công bố trong Báo cáo PTBV, bao gồm danh mục các chủ đề trọng yếu, hay không. Nếu có, hãy mô tả quy trình. Nếu không, hãy đưa lý do. | H14: Đáp ứng | I14: Tổ Thư ký | J14: HĐQT chịu trách nhiệm rà soát và phê duyệt các thông tin công bố trong Báo cáo thường niên, bao gồm nội dung báo cáo PTBV. Quy trình rà soát và phê duyệt: TTK BĐH Chương trình PTBV chủ trì thu thập dữ liệu từ các Tổ công tác, CQĐV, tổng hợp và xây dựng dự thảo báo cáo, gửi báo cáo cho Ban TT. Ban TT tập hợp thông tin báo cáo Ban Giám đốc và HĐQT báo cáo thường niên. HĐQT xem xét và phê duyệt trước khi công bố.
A15: 14 | B15: Quản trị | C15: GRI 2-15 | D15: =VLOOKUP(C15,'95 Chỉ tiêu'!$B$4:$K$98,5,0) -> #N/A | E15: Xung đột lợi ích | F15: Mô tả quy trình HĐQT ngăn ngừa và giảm thiểu xung đột lợi ích. Báo cáo nếu xung đột lợi ích được tiết lộ đến các bên liên quan, ít nhất là bao gồm: i. Kiêm nhiệm chéo trong HĐQT ii. Sở hữu chéo với nhà cung cấp và các bên liên quan iii. Sự tồn tại của cổ đông chi phối iv. Các bên liên quan: mối quan hệ, giao dịch và số dư còn lại. | H15: Đáp ứng | I15: Tổ Thư ký | J15: Điều 55 trong Điều lệ TCT ban hành ngày 28/6/2026 quy định về trách nhiệm trung thực và tránh các xung đột về quyền lợi. Xung đột lợi ích tới các bên liên quan: i. Kiêm nhiệm chéo: • Ông Đặng Ngọc Hòa: Ủy viên BCH Liên đoàn thương mại và công nghiệp Việt Nam (VCCI) • Ông Lê Hồng Hà: thành viên Hội đồng Học viện Hàng không Việt Nam nhiệm kỳ 2025-2030 • Ông Tạ Mạnh Hùng: Chủ tịch HĐTV Công ty TNHH MTV Dịch vụ mặt đất sân bay Việt Nam (VIAGS) • Ông Lê Trường Giang: Chủ tịch HĐQT Công ty cổ phần Dịch vụ hàng hóa Tân Sơn Nhất (TCS) • Ông Đinh Việt Tùng: PTGĐ TCT Đầu tư và Kinh doanh vốn nhà nước (SCIC). Chủ tịch HĐQT TCT Licogi. Chủ tịch HĐQT TCTCP Bảo Minh • Ông Trương Văn Phước: Ủy viên hội đồng khoa học của UB Thường vụ Quốc hội • Ông Hidekazu Isone: PTGĐ phụ trách chiến lược của ANA Holdings ii. Sở hữu chéo với nhà cung cấp: Vietnam Airlines nắm giữ vốn tại một số đơn vị đồng thời là nhà cung cấp dịch vụ cho Tổng công ty. iii. Cổ đông chi phối: Nhà nước là cổ đông chi phối, nắm giữ khoảng 86,42% vốn điều lệ thông qua Bộ Tài chính và Tổng công ty Đầu tư và Kinh doanh vốn nhà nước (SCIC). ANA Holdings là cổ đông chiến lược với tỷ lệ 5,62% iv. Giao dịch với bên liên quan: mối quan hệ, giá trị giao dịch và số dư còn lại với các bên liên quan được trình bày tại Thuyết minh Báo cáo tài chính hợp nhất đã kiểm toán hàng năm.
A16: 15 | B16: Quản trị | C16: GRI 2-16 | E16: Báo cáo các mối quan ngại nghiêm trọng | F16: 1. Mô tả "mối quan ngại nghiêm trọng" và việc các mối quan ngại nghiêm trọng được báo cáo lên HĐQT như thế nào 2. Tổng số và tính chất của các mối quan ngại nghiêm trọng đã được báo cáo lên HĐQT trong kỳ báo cáo. | H16: Đáp ứng | I16: Tổ Thư ký | J16: Vietnam Airlines xác định "mối quan ngại nghiêm trọng" là các vấn đề liên quan đến tác động tiêu cực tiềm ẩn hoặc thực tế đối với các bên liên quan, hoặc liên quan đến hành vi kinh doanh của Tổng công ty, có mức độ ảnh hưởng đủ lớn để cần đến sự xem xét của cơ quan quản trị cao nhất. Các mối quan ngại nghiêm trọng được truyền đạt lên Hội đồng quản trị thông qua hệ thống kiểm toán nội bộ. Ban Kiểm soát thực hiện chức năng giám sát độc lập và báo cáo ĐHĐCĐ. Các vấn đề phát sinh từ kênh tiếp nhận đơn thư khiếu nại, tố cáo, kiến nghị, phản ánh và từ cơ chế tố giác nội bộ được xử lý theo trình tự, thủ tục quy định và được báo cáo lên cấp có thẩm quyền tương ứng với tính chất, mức độ của vụ việc.
A17: 16 | B17: Quản trị | C17: GRI 2-17 | E17: Kiến thức tập thể của cơ quan quản lý cao nhất | F17: Các biện pháp đã thực hiện để nâng cao kiến thức, kỹ năng và kinh nghiệm tập thể của HĐQT về phát triển bền vững. | H17: Đáp ứng | I17: Tổ Thư ký | J17: Vietnam Airlines chú trọng nâng cao năng lực về PTBV cho đội ngũ quản trị và điều hành. Trong năm 2025, BĐH Chương trình PTBV đã hoàn thành chương trình đào tạo về PTBV do chuyên gia tư vấn độc lập bên ngoài thực hiện và dự định triển khai kế hoạch đối với HĐQT trong thời gian tới.
A18: 17 | B18: Quản trị | C18: GRI 2-18 | E18: Đánh giá hiệu quả hoạt động của cơ quan quản trị cao nhất | F18: 1. Mô tả quy trình đánh giá hiệu quả hoạt động của HĐQT trong việc giám sát quản lý tác động kinh tế – môi trường – con người 2. Đánh giá là độc lập hay tự đánh giá; tần suất đánh giá. 3. Các hành động đã thực hiện sau đánh giá, bao gồm thay đổi về thành phần HĐQT và thay đổi về thông lệ quản trị của tổ chức. | H18: Đáp ứng | I18: Tổ Thư ký | J18: Ban KS có đánh giá HĐQT hàng năm
A19: 18 | B19: Quản trị | C19: GRI 2-23 | D19: =VLOOKUP(C19,'95 Chỉ tiêu'!$B$4:$K$98,5,0) -> #N/A | E19: Các cam kết về chính sách | F19: 1. Danh mục các cam kết chính sách về ứng xử kinh doanh có trách nhiệm, bao gồm: i. các văn kiện liên chính phủ có thẩm quyền mà các cam kết đề cập đến; ii. cam kết có yêu cầu thực hiện thẩm định chi tiết hay không; iii. cam kết có áp dụng nguyên tắc phòng ngừa hay không; iv. cam kết có quy định về tôn trọng quyền con người hay không. 2. Cam kết riêng về tôn trọng quyền con người: i. các quyền con người được quốc tế công nhận mà cam kết này bao hàm; ii. các nhóm bên liên quan được đặc biệt quan tâm, gồm nhóm có nguy cơ/dễ bị tổn thương. 3. Đường dẫn công bố công khai của từng chính sách, hoặc lý do không công khai. 4. Cấp phê duyệt của từng chính sách - nêu rõ có phải cấp cao nhất hay không. 5. Phạm vi áp dụng. 6. Cách truyền thông cam kết tới người lao động, đối tác kinh doanh và các bên liên quan khác. | H19: Đáp ứng | I19: Tổ Thư ký | J19: Vietnam Airlines thiết lập hệ thống cam kết chính sách về ứng xử kinh doanh có trách nhiệm, được đăng tải trên các trang nội bộ của Vietnam Airlines, bao gồm: • Chương trình Phòng, chống tham nhũng, tiêu cực, thực hành tiết kiệm, chống lãng phí (ban hành năm 2025); • Bộ định nghĩa hành vi và Hướng dẫn thực hiện văn hóa chính trực • Chính sách An toàn (thuộc Tài liệu Hệ thống Quản lý An toàn – SMSM) • Quy chế quản lý lao động • Quy chế bảo vệ môi trường, sử dụng năng lượng tiết kiệm và hiệu quả • Quy chế đấu thầu và mua sắm • ...
A20: 19 | B20: Quản trị | C20: GRI 2-24 | E20: Lồng ghép các cam kết chính sách | F20: Mô tả cách VNA lồng ghép từng cam kết chính sách vào toàn bộ hoạt động và quan hệ kinh doanh, bao gồm: i. Cách phân bổ trách nhiệm thực thi cam kết theo các cấp trong tổ chức; ii. Cách tích hợp cam kết vào chiến lược, chính sách vận hành, quy trình vận hành; iii. Cách thực thi cam kết thông qua quan hệ kinh doanh; iv. Đào tạo về thực thi cam kết: đối tượng, nội dung, hình thức, tần suất, tỷ lệ hoàn thành. | H20: Đáp ứng | I20: Tổ Thư ký | J20: Vietnam Airlines lồng ghép các cam kết chính sách vào hoạt động, cụ thể: Phân bổ trách nhiệm theo cấp: HĐQT giữ vai trò giám sát cao nhất. TGĐ và BĐH Chương trình PTBV chịu trách nhiệm tổ chức thực hiện. Các Tổ công tác, CQĐV chịu trách nhiệm hằng ngày đối với từng nhóm cam kết theo lĩnh vực chuyên môn. Tích hợp vào chiến lược và quy trình vận hành: các cam kết phát triển bền vững được cụ thể hóa thành chỉ tiêu trong kế hoạch sản xuất kinh doanh hằng năm. Thực thi qua quan hệ kinh doanh: ví dụ qua Bộ Quy tắc Ứng xử dành cho nhà cung cấp; tiêu chí sàng lọc trong quy trình mua sắm và đấu thầu.] Đào tạo: Trong nội bộ VNA đã triển khai nhiều khóa đào tạo về thực thi các chính sách, cam kết như: về an toàn thông tin, giao tiếp và hợp tác trên môi trường số, Nâng cao nhận thức pháp luật về Bảo vệ dữ liệu cá nhân, ...
A21: 20 | B21: Quản trị | C21: GRI 2-25 | E21: Quy trình khắc phục các tác động tiêu cực | F21: 1. Cam kết của VNA về việc thực hiện hoặc hợp tác khắc phục các tác động tiêu cực mà VNA gây ra hoặc góp phần gây ra; 2. Mô tả cách tiếp cận của tổ chức trong việc xác định và giải quyết các khiếu nại, bao gồm cả các cơ chế giải quyết khiếu nại mà tổ chức đã thiết lập hoặc tham gia; 3. Các quy trình khắc phục khác ngoài cơ chế khiếu nại; 4. Mô tả cách thức các bên liên quan - với tư cách là người sử dụng cơ chế khiếu nại - tham gia vào quá trình thiết kế, rà soát, vận hành và cải tiến các cơ chế này; 5. Cách doanh nghiệp theo dõi tính hiệu quả của cơ chế khiếu nại và các quy trình khắc phục; ví dụ minh chứng về hiệu quả, kèm phản hồi của bên liên quan. | H21: Đáp ứng | I21: Tổ Thư ký | J21: Vietnam Airlines cam kết thực hiện hoặc hợp tác khắc phục các tác động tiêu cực mà Tổng công ty gây ra hoặc góp phần gây ra đối với các bên liên quan, trên cơ sở bảo vệ quyền và lợi ích hợp pháp của tổ chức, cá nhân và tuân thủ pháp luật hiện hành.
A22: 21 | B22: Quản trị | C22: GRI 2-26 | D22: =VLOOKUP(C22,'95 Chỉ tiêu'!$B$4:$K$98,5,0) -> #N/A | E22: Cơ chế tham vấn, phản ánh các vấn đề đạo đức | F22: 1. Cơ chế để cá nhân xin tư vấn về việc thực thi các chính sách và thông lệ ứng xử kinh doanh có trách nhiệm. 2. Cơ chế để cá nhân phản ánh quan ngại về hành vi kinh doanh của doanh nghiệp. | H22: Đáp ứng | I22: Tổ Thư ký | J22: Vietnam Airlines duy trì các cơ chế để cá nhân xin tư vấn và phản ánh quan ngại liên quan đến ứng xử kinh doanh có trách nhiệm. Xin tư vấn: người lao động và các bên liên quan có thể liên hệ Ban Pháp chế và các Ban chức năng để được hướng dẫn về việc áp dụng các quy định nội bộ và pháp luật liên quan trong hoạt động hằng ngày. Phản ánh quan ngại: Vietnam Airlines tiếp nhận và xử lý đơn thư khiếu nại, tố cáo, kiến nghị, phản ánh theo quy định của pháp luật Bảo mật và bảo vệ người tố giác: thông tin về người tố cáo được bảo mật theo quy định pháp luật; người tố cáo được bảo vệ và không bị trả đũa vì việc phản ánh trung thực.
A23: 22 | B23: Quản trị | C23: GRI 2-27 | E23: Tuân thủ pháp luật và các quy định | F23: Đây là chỉ tiêu định lượng - bốn tiểu mục đều yêu cầu số liệu, không phải cam kết: 1. TỔNG SỐ trường hợp không tuân thủ đáng kể phát sinh trong kỳ, chia theo: (i) số trường hợp bị phạt tiền; (ii) số trường hợp bị áp dụng chế tài phi tiền tệ. 2. TỔNG SỐ và GIÁ TRỊ TIỀN các khoản phạt ĐÃ NỘP trong kỳ, chia theo: (i) khoản phạt cho vi phạm phát sinh trong kỳ báo cáo; (ii) khoản phạt cho vi phạm phát sinh ở các kỳ trước. 3. Mô tả từng trường hợp không tuân thủ đáng kể (địa bàn, lĩnh vực, bối cảnh). 4. Mô tả cách thức xác định các trường hợp không tuân thủ nghiêm trọng | H23: No | I23: Tổ Thư ký | J23: Vietnam Airlines cam kết duy trì ở mức cao nhất các tiêu chuẩn đạo đức trong hoạt động sản xuất kinh doanh, đề cao tính chuyên nghiệp, trung thực và minh bạch. Bảo đảm tuân thủ các điều ước quốc tế, Hiến pháp và pháp luật luôn là ưu tiên quan trọng của Tổng công ty trong mọi hoạt động. Trong năm 2025, VNA không bị phạt hoặc áp dụng chế tài
A24: 23 | B24: Quản trị | C24: GRI 2-29 | D24: =VLOOKUP(C24,'95 Chỉ tiêu'!$B$4:$K$98,5,0) -> #N/A | E24: Tiếp cận đối thoại các bên liên quan | F24: 1. Danh mục các nhóm bên liên quan mà doanh nghiệp đối thoại và phương pháp nhận diện các nhóm này. 2. Mục đích đối thoại với từng nhóm 3. Cách doanh nghiệp đảm bảo đối thoại thực chất | H24: Đáp ứng | I24: Tổ Thư ký | J24: Vietnam Airlines xác định các nhóm bên liên quan trên cơ sở mức độ ảnh hưởng của hoạt động của TCT tới các nhóm này và mức độ ảnh hưởng của các nhóm này tới hoạt động của TCT. Mục đích đối thoại là nắm bắt kỳ vọng và mối quan tâm của từng nhóm, nhận diện các tác động thực tế và tiềm ẩn, và xác định các biện pháp phòng ngừa, giảm thiểu phù hợp. Các nhóm bên liên quan chính và kênh đối thoại bao gồm: • Cổ đông và nhà đầu tư: ĐHĐCĐ thường niên và bất thường; công bố thông tin định kỳ và bất thường theo quy định; gặp gỡ nhà đầu tư. • Khách hàng: các kênh tiếp nhận phản ánh, khiếu nại; khảo sát mức độ hài lòng; chương trình khách hàng thường xuyên; mạng xã hội. • Người lao động và Công đoàn: Hội nghị người lao động; đối thoại tại nơi làm việc; thương lượng tập thể; các kênh truyền thông nội bộ. • Cơ quan quản lý nhà nước: báo cáo định kỳ; làm việc với cơ quan đại diện chủ sở hữu và cơ quan quản lý chuyên ngành; tham gia góp ý xây dựng chính sách. • Nhà cung cấp và đối tác: đàm phán hợp đồng; đánh giá nhà cung cấp; hội nghị đối tác. • Cộng đồng: các chương trình cộng đồng và hoạt động an sinh xã hội. • Hiệp hội và liên minh ngành: tham gia IATA, AAPA, SkyTeam và Hiệp hội Doanh nghiệp Hàng không Việt Nam. • Cơ quan truyền thông: họp báo, thông cáo báo chí, kênh truyền thông chính thức.
A25: 24 | B25: Quản trị | C25: GRI 3-3 | D25: =VLOOKUP(C25,'95 Chỉ tiêu'!$B$4:$K$98,5,0) -> #N/A | E25: Quản lý các chủ đề trọng yếu | F25: LƯU Ý CẤU TRÚC: GRI 3-3 phải được báo cáo RIÊNG cho TỪNG chủ đề trọng yếu, không báo cáo gộp cho cả trụ cột. Trước 3-3 phải có GRI 3-1 (quy trình xác định chủ đề trọng yếu) và GRI 3-2 (danh mục chủ đề trọng yếu). i. Xác định các chủ đề trọng yếu thuộc trụ cột Governance. ii. Với mỗi chủ đề, công bố đủ 6 nội dung: (a) Mô tả các tác động thực tế và tiềm ẩn, tiêu cực và tích cực đối với kinh tế, môi trường và con người (kể cả quyền con người). (b) VNA có liên quan tới các tác động tiêu cực đó thông qua hoạt động của chính mình hay thông qua quan hệ kinh doanh — và mô tả hoạt động/quan hệ kinh doanh đó. (c) Các chính sách hoặc cam kết đối với chủ đề. (d) Các hành động quản lý chủ đề, gồm: (i) ngăn ngừa/giảm thiểu tác động tiêu cực tiềm ẩn; (ii) xử lý tác động tiêu cực thực tế, gồm thực hiện hoặc hợp tác khắc phục; (iii) quản lý tác động tích cực. (e) Theo dõi hiệu quả của các hành động, gồm: (i) quy trình theo dõi; (ii) mục tiêu, chỉ tiêu và chỉ số đánh giá tiến độ; (iii) mức độ hiệu quả đạt được, gồm tiến độ so với mục tiêu; (iv) bài học rút ra và cách đưa vào chính sách, quy trình vận hành. (f) Việc đối thoại với các bên liên quan đã định hình các hành động tại (d) và việc đánh giá hiệu quả tại (e) như thế nào. | H25: Đáp ứng | I25: Tổ Thư ký | J25: Đề xuất không đưa nội dung này lên website, vì cần báo cáo cụ thể cho 21 chỉ tiêu còn lại nên có thể trùng với các nội dung đã báo cáo
A26: 25 | B26: Quản trị | C26: GRI 201-4 | D26: =VLOOKUP(C26,'95 Chỉ tiêu'!$B$4:$K$98,5,0) -> #N/A | E26: Trợ cấp/tài trợ nhận từ chính phủ | F26: 1. TỔNG GIÁ TRỊ TIỀN TỆ hỗ trợ tài chính nhận được từ BẤT KỲ chính phủ nào trong kỳ, phân theo 08 loại: (i) miễn, giảm thuế và tín dụng thuế; (ii) trợ cấp; (iii) tài trợ đầu tư, tài trợ nghiên cứu và phát triển, các loại tài trợ khác; (iv) giải thưởng; (v) miễn/giảm tiền bản quyền, phí nhượng quyền; (vi) hỗ trợ tài chính từ các Cơ quan Tín dụng Xuất khẩu (ECA); (vii) ưu đãi tài chính; (viii) lợi ích tài chính khác đã nhận hoặc sẽ nhận từ bất kỳ chính phủ nào cho bất kỳ hoạt động nào 2. Số liệu tại mục (1) phân tách theo quốc gia 3. Chính phủ có hiện diện trong cơ cấu sở hữu hay không và mức độ hiện diện 4. Cơ sở xác định giá trị: áp dụng nhất quán các nguyên tắc kế toán được thừa nhận chung | H26: Đáp ứng | I26: Tổ Thư ký | J26: Sự hiện diện của Nhà nước trong cơ cấu sở hữu: Nhà nước là cổ đông chi phối của Vietnam Airlines, nắm giữ khoảng 86,42% vốn điều lệ thông qua Bộ Tài chính và Tổng công ty Đầu tư và Kinh doanh vốn nhà nước (SCIC). Nhà nước thực hiện các quyền và nghĩa vụ của cổ đông theo quy định của pháp luật và Điều lệ TCT. Hỗ trợ tài chính nhận từ Chính phủ: Thực hiện Nghị quyết số 135/2020/QH14 ngày 17/11/2020 của Quốc hội về các giải pháp tháo gỡ khó khăn cho TCTHKVN do ảnh hưởng của đại dịch COVID-19, Vietnam Airlines đã triển khai gói giải pháp thanh khoản quy mô 12.000 tỷ đồng, gồm: • Khoản vay tái cấp vốn 4.000 tỷ đồng thông qua các tổ chức tín dụng được Ngân hàng Nhà nước tái cấp vốn với lãi suất 0%/năm, không tài sản bảo đảm. Khoản vay đã được Quốc hội cho phép gia hạn trả nợ, tối đa đến ngày 31/12/2027. • Phương án phát hành cổ phiếu tăng vốn điều lệ quy mô khoảng 8.000 tỷ đồng, trong đó SCIC thay mặt Chính phủ thực hiện quyền mua cổ phần của cổ đông Nhà nước. Kiểm toán Nhà nước đã thực hiện kiểm toán việc sử dụng nguồn vốn của gói hỗ trợ và kết luận nguồn vốn được quản lý, sử dụng đúng mục đích đề ra.
A27: 26 | B27: Quản trị | C27: GRI 205-2 | D27: =VLOOKUP(C27,'95 Chỉ tiêu'!$B$4:$K$98,5,0) -> #N/A | E27: Truyền thông, đào tạo về chống tham nhũng | F27: Đây là chỉ tiêu định lượng, cụ thể: 1. Số lượng và tỷ lệ thành viên cơ quan quản trị đã được truyền thông về chính sách và quy trình phòng, chống tham nhũng — phân theo khu vực. 2. Số lượng và tỷ lệ người lao động đã được truyền thông — phân theo nhóm lao động và theo khu vực 3. Số lượng và tỷ lệ đối tác kinh doanh đã được truyền thông — phân theo nhóm lao động và theo khu vực; đồng thời mô tả nếu có truyền thông tới tổ chức/cá nhân khác. 4. Số lượng và tỷ lệ thành viên HĐQT đã được đào tạo về phòng, chống tham nhũng — phân theo khu vực. 5. Số lượng và tỷ lệ người lao động đã được đào tạo — phân theo nhóm lao động và khu vực. | H27: Đáp ứng | I27: Tổ Thư ký | J27: Trong năm 2025, Ban lãnh đạo Vietnam Airlines đã ban hành Chương trình Phòng, chống tham nhũng, tiêu cực, thực hành tiết kiệm, chống lãng phí — được xác định là kim chỉ nam trong mọi hoạt động sản xuất kinh doanh cũng như công tác quản trị nội bộ. Chương trình được triển khai theo Luật Phòng, chống tham nhũng 2018 và các quy định liên quan. -> Mục 1 và 2 đã đảm bảo tỷ lệ 100%
A28: 27 | B28: Quản trị | C28: GRI 205-3 | D28: =VLOOKUP(C28,'95 Chỉ tiêu'!$B$4:$K$98,5,0) -> #N/A | E28: Sự cố tham nhũng xác nhận và biện pháp xử lý | F28: 1. TỔNG SỐ và TÍNH CHẤT các sự cố tham nhũng ĐÃ ĐƯỢC XÁC NHẬN trong kỳ báo cáo. 2. (b) Tổng số sự cố đã xác nhận dẫn tới việc NGƯỜI LAO ĐỘNG bị sa thải hoặc bị kỷ luật vì hành vi tham nhũng. 3. (c) Tổng số sự cố đã xác nhận dẫn tới việc CHẤM DỨT hoặc KHÔNG GIA HẠN hợp đồng với đối tác kinh doanh do vi phạm liên quan đến tham nhũng. 4. (d) Các VỤ VIỆC PHÁP LÝ CÔNG KHAI về tham nhũng được khởi kiện đối với Tổng công ty hoặc người lao động của Tổng công ty trong kỳ, và KẾT QUẢ xử lý các vụ việc đó. | H28: No | I28: Tổ Thư ký | J28: Không có sự cố tham nhũng nào tại Vietnam Airlines
A29: 28 | B29: Quản trị | C29: GRI 206-1 | D29: =VLOOKUP(C29,'95 Chỉ tiêu'!$B$4:$K$98,5,0) -> #N/A | E29: Vụ kiện về cạnh tranh không lành mạnh, độc quyền | F29: 1. (a) SỐ VỤ KIỆN đang xử lý hoặc đã hoàn tất trong kỳ báo cáo liên quan đến hành vi hạn chế cạnh tranh và vi phạm pháp luật về chống độc quyền, trong đó doanh nghiệp được xác định là MỘT BÊN THAM GIA. 2. (b) KẾT QUẢ CHÍNH của các vụ kiện đã hoàn tất, bao gồm các quyết định hoặc phán quyết. | H29: No | I29: Tổ Thư ký | J29: Không có vụ kiện về cạnh tranh không lành mạnh, độc quyền nào tại Vietnam Airlines
A30: 29 | B30: Quản trị | C30: GRI 415-1 | D30: =VLOOKUP(C30,'95 Chỉ tiêu'!$B$4:$K$98,5,0) -> #N/A | E30: Đóng góp cho các hoạt động chính trị | F30: 1. (a) TỔNG GIÁ TRỊ TIỀN TỆ các khoản đóng góp chính trị bằng TIỀN và bằng HIỆN VẬT, được thực hiện TRỰC TIẾP và GIÁN TIẾP bởi doanh nghiệp — phân theo QUỐC GIA và theo BÊN NHẬN/THỤ HƯỞNG. 2. (b) Nếu có đóng góp bằng hiện vật: phương pháp ước tính giá trị. | H30: Đáp ứng | I30: Tổ Thư ký | J30: Là Hãng hàng không quốc gia, Vietnam Airlines phối hợp chặt chẽ với Chính phủ và các cơ quan quản lý trong quá trình xây dựng và hoàn thiện chính sách, pháp luật về hàng không dân dụng và phát triển bền vững. Tổng công ty cũng tham gia đóng góp ý kiến chính sách một cách gián tiếp thông qua các hiệp hội và liên minh ngành như IATA, AAPA, SkyTeam và Hiệp hội Doanh nghiệp Hàng không Việt Nam. Trong năm 2026, Vietnam Airlines đã chi 753.708 USD phí hội viên cho các hiệp hội và liên minh trên

Sheet 32 chỉ tiêu BC động
AF1: Thông tin nguồn | AL1: Báo cáo | AN1: Đưa ra landing page
A2: STT | B2: PIC CQĐV | C2: PIC VNA | D2: PIC (AQT) | E2: Mã GRI | F2: Trụ cột | G2: Chủ đề | H2: Tên chỉ tiêu | I2: Mã báo cáo | J2: Chỉ tiêu con/báo cáo (EN) | K2: Chỉ tiêu con/báo cáo (VI) | L2: Người cung cấp | M2: Định nghĩa / Diễn giải | N2: Logic/Công thức tính | O2: Đơn vị tính | P2: Nguồn dữ liệu thực tế | Q2: Tần suất cập nhật dữ liệu | R2: Chiều tổng hợp dữ liệu | S2: So sánh với lũy kế cùng kỳ | T2: So sánh với cùng kỳ | U2: So sánh với tháng trước | V2: So sánh với định mức | W2: So sánh với kế hoạch tháng | X2: So sánh với kế hoạch năm | Y2: So sánh với ngưỡng | Z2: So sánh các tháng trong năm | AA2: So sánh các quý trong năm | AB2: So sánh các năm | AC2: Mức độ ưu tiên (1: Rất cần thiết 2: Cần thiết 3: Bình thường 4: Chưa quan tâm 5: Có thể bị thay thế, loại bỏ) | AD2: Tài liệu/Form | AE2: Ghi chú | AF2: Bảng | AG2: Trường dữ liệu | AH2: Quy tắc lấy dữ liệu | AI2: Ghi chú của thông tin nguồn | AJ2: Tên báo cáo (EN) | AK2: Tên báo cáo (VN) | AL2: Tab | AM2: Loại biểu đồ
A3: 1 | B3: Tổ Khai thác | C3: MS Lê | D3: NhiPLH | E3: GRI 302-1 | F3: =VLOOKUP(E3,'95 Chỉ tiêu'!$B$4:$F$177,2,0) -> #N/A | G3: Energy and Emissions | H3: Năng lượng tiêu thụ trong tổ chức | I3: CT 1.1 | J3: Total Fuel Consumption | K3: Tổng nhiên liệu tiêu thụ | L3: Chị Lê | M3: - Tổng lượng nhiên liệu hàng không được ghi nhận tiêu thụ trong kỳ, được xác định dựa trên lượng nhiên liệu nạp vào tàu bay (fuel uplift) thay vì lượng nhiên liệu thực tế đốt cháy trong quá trình bay. - Toàn bộ nhiên liệu nạp cho chuyến bay sẽ được phân bổ vào ngày khởi hành của chuyến bay đó, bao gồm cả nhiên liệu sử dụng trong giai đoạn taxi out/in, kể cả đối với các chuyến bay kéo dài sang ngày hôm sau. - Nhiên liệu tiêu thụ bao gồm cả nhiên liệu Jet A-1 và nhiên liệu SAF nguyên chất; tuy nhiên không phải tất cả chuyến bay đều sử dụng SAF, do một số chuyến bay chỉ sử dụng 100% nhiên liệu Jet A-1 | N3: - Tổng nhiên liệu tiêu thụ = Tổng lượng nhiên liệu đã nạp trên tất cả chuyến bay theo hóa đơn | O3: - Lít | P3: - FIMS | Q3: - Hàng tháng (ngày cuối cùng trong tháng) | R3: - Năm | S3: N/A | T3: N/A | U3: N/A | V3: N/A | W3: N/A | X3: N/A | Y3: N/A | Z3: N/A | AA3: N/A | AB3: X | AC3: 1 | AD3: FLIGHT_INTERGRATED.xlsx | AF3: stg_fims.receipts | AG3: number_unit | AH3: Tổng hợp lượng tra nạp (uplift) dựa trên hóa đơn, gán theo ngày khởi hành (dep_dt). Đơn vị: Lít. | AJ3: Energy consumption within the organization | AK3: Năng lượng tiêu thụ trong tổ chức | AM3: Card
A4: 2 | B4: Tổ Khai thác | C4: MS Lê | D4: NhiPLH | E4: GRI 302-1 | F4: =VLOOKUP(E4,'95 Chỉ tiêu'!$B$4:$F$177,2,0) -> #N/A | G4: Energy and Emissions | H4: Năng lượng tiêu thụ trong tổ chức | I4: CT 1.2 | J4: Jet A-1 Fuel Consumption | K4: Nhiên liệu tiêu thụ Jet A-1 | L4: Chị Lê | M4: - Là tổng lượng nhiên liệu hàng không hóa thạch Jet A-1 được tra nạp và sử dụng cho hoạt động khai thác bay. | N4: - Nhiên liệu tiêu thụ Jet A-1 = Tổng nhiên liệu tiêu thụ - Lượng SAF nguyên chất. | O4: - Lít | P4: - Tổng nhiên liệu tiêu thụ: FIMS. - Nhiên liệu SAF nguyên chất: ANCM. | Q4: - Hàng tháng (ngày cuối cùng trong tháng) | R4: - Năm | S4: N/A | T4: N/A | U4: N/A | V4: N/A | W4: N/A | X4: N/A | Y4: N/A | Z4: N/A | AA4: N/A | AB4: N/A | AC4: 1 | AD4: https://vtxgroupvn.sharepoint.com/:x:/r/sites/v25gfx02639/_layouts/15/Doc.aspx?sourcedoc=%7B037CC2E8-12C6-41E4-A941-1E3E6132DE37%7D&file=FIMS.xlsx&action=default&mobileredirect=true | AF4: stg_fims.receipts | AG4: number_unit | AH4: - Lấy tổng nhiên liệu từ FIMS trừ đi lượng SAF nguyên chất (Neat SAF). Đơn vị: Lít. - Neat SAF: Lấy từ ANCM | AI4: Chưa có ANCM | AJ4: Energy consumption within the organization | AK4: Năng lượng tiêu thụ trong tổ chức | AM4: Card
A5: 3 | B5: Tổ Khai thác | C5: MS Lê | D5: NhiPLH | E5: GRI 302-1 | F5: =VLOOKUP(E5,'95 Chỉ tiêu'!$B$4:$F$177,2,0) -> #N/A | G5: Energy and Emissions | H5: Năng lượng tiêu thụ trong tổ chức | I5: CT 1.3 | J5: SAF Consumption | K5: Nhiên liệu tiêu thụ SAF | L5: Chị Lê | M5: - Nhiên liệu tiêu thụ SAF là phần SAF nguyên chất (Neat SAF). - Trên thực tế, tàu bay không sử dụng 100% SAF mà sử dụng nhiên liệu pha trộn giữa SAF và Jet A-1 theo tỷ lệ do nhà cung cấp hoặc quy định từng khu vực quy định. | N5: - Nhiên liệu tiêu thụ SAF = Tổng lượng SAF nguyên chất được xác định trong chứng nhận từ nhà cung cấp tại các sân bay. | O5: - Lít | P5: - ANCM | Q5: - Hàng tháng (ngày cuối cùng trong tháng) | R5: - Năm, Tháng | S5: N/A | T5: N/A | U5: N/A | V5: N/A | W5: N/A | X5: N/A | Y5: N/A | Z5: N/A | AA5: N/A | AB5: N/A | AC5: 1 | AF5: Nhập tay (ANCM) | AG5: N/A | AH5: Tổng hợp từ chứng nhận nạp SAF do nhà cung cấp cấp tại các sân bay quốc tế. Đơn vị: Lít. | AI5: Chưa có ANCM | AJ5: Energy consumption within the organization | AK5: Năng lượng tiêu thụ trong tổ chức | AM5: Card
A6: 4 | B6: Tổ Khai thác | C6: MS Lê | D6: NhiPLH | E6: GRI 302-1 | F6: =VLOOKUP(E6,'95 Chỉ tiêu'!$B$4:$F$177,2,0) -> #N/A | G6: Energy and Emissions | H6: Năng lượng tiêu thụ trong tổ chức | I6: CT 1.4 | J6: Fuel Type Distribution | K6: Tỷ lệ các loại nhiên liệu | L6: Chị Lê | M6: - Chỉ tiêu phản ánh tỷ trọng tiêu thụ của từng loại nhiên liệu trong tổng lượng nhiên liệu khai thác bay, bao gồm nhiên liệu Jet A-1 và nhiên liệu SAF. | N6: - Tỷ lệ nhiên liệu SAF = Lượng tiêu thụ nhiên liệu SAF/ Tổng lượng nhiên liệu tiêu thụ. - Tỷ lệ nhiên liệu Jet A-1 = Lượng tiêu thụ nhiên liệu Jet A-1/ Tổng lượng nhiên liệu tiêu thụ. | O6: - Lít | P6: - Tham chiếu nguồn dữ liệu của CT 1.2 và CT 1.3. | Q6: - Theo tháng hoặc theo năm (ngày cuối cùng trong tháng) | R6: - Năm | S6: N/A | T6: N/A | U6: N/A | V6: N/A | W6: N/A | X6: N/A | Y6: N/A | Z6: N/A | AA6: N/A | AB6: N/A | AC6: 2 | AF6: Thừa kế luồng | AG6: N/A | AH6: Tính toán tỷ lệ phần trăm (%) cho từng loại nhiên liệu trên tổng lượng tiêu thụ. | AI6: Chưa có ANCM | AJ6: Energy consumption within the organization | AK6: Năng lượng tiêu thụ trong tổ chức | AM6: Donut
A7: 5 | B7: Tổ Khai thác | C7: MS Lê | D7: NhiPLH | E7: GRI 302-1 | F7: =VLOOKUP(E7,'95 Chỉ tiêu'!$B$4:$F$177,2,0) -> #N/A | G7: Energy and Emissions | H7: Năng lượng tiêu thụ trong tổ chức | I7: CT 1.5 | J7: Neat SAF Consumption by Ratio | K7: Tiêu thụ SAF theo tỷ lệ pha trộn SAF | L7: Chị Lê | M7: - Tổng lượng nhiên liệu pha trộn SAF được phân loại theo các mức tỷ lệ pha trộn SAF khác nhau như 2%, 3%, 5%, 7%.... | N7: - Tỷ lệ pha trộn SAF được xác định dựa trên tỷ lệ giữa lượng SAF nguyên chất (Neat SAF) và tổng lượng nhiên liệu SAF pha trộn (Blended SAF), cụ thể: + Tỷ lệ pha trộn SAF (% Neat SAF) = Lượng SAF nguyên chất (Neat SAF) / Lượng SAF pha trộn (Blended SAF). | O7: - Lít | P7: - Nhiên liệu SAF nguyên chất, SAF pha trộn: ANCM | Q7: - Theo tháng hoặc theo năm (ngày cuối cùng trong tháng) | R7: - Năm | S7: N/A | T7: N/A | U7: N/A | V7: N/A | W7: N/A | X7: N/A | Y7: N/A | Z7: N/A | AA7: N/A | AB7: N/A | AC7: 2 | AD7: 01. DETAIL--POS-170-I-0226-VIETNAM-VN-DPS.pdf | AF7: Nhập tay (ANCM) | AG7: N/A | AH7: Bóc tách từ chứng từ nạp nhiên liệu tại từng sân bay. | AI7: Chưa có ANCM | AJ7: Energy consumption within the organization | AK7: Năng lượng tiêu thụ trong tổ chức | AM7: Donut
A8: 6 | B8: Tổ Khai thác | C8: MS Lê | D8: NhiPLH | E8: GRI 302-1 | F8: =VLOOKUP(E8,'95 Chỉ tiêu'!$B$4:$F$177,2,0) -> #N/A | G8: Energy and Emissions | H8: Năng lượng tiêu thụ trong tổ chức | I8: CT 1.6 | J8: Annual Fuel Consumption vs Target | K8: Tiêu thụ nhiên liệu theo năm so với mục tiêu (Lít) | L8: Chị Lê | M8: - Tổng lượng nhiên liệu tiêu thụ thực tế theo từng năm và so sánh với mức mục tiêu tiêu thụ nhiên liệu đã được kế hoạch hoặc hãng hàng không đặt ra. - Dữ liệu bao gồm tổng lượng nhiên liệu Jet A-1 và nhiên liệu SAF sử dụng cho hoạt động khai thác bay trong năm báo cáo. | N8: - Tổng nhiên liệu tiêu thụ theo năm = Tổng lượng tiêu thụ Jet A-1 + Tổng lượng tiêu thụ SAF (theo năm). - So sánh giữa giá trị thực tế và giá trị mục tiêu theo từng năm báo cáo. | O8: - Lít | P8: - Tham chiếu nguồn dữ liệu của CT 1.2 và CT 1.3. | Q8: - Cuối năm (ngày cuối cùng trong năm) | R8: - Năm | S8: N/A | T8: N/A | U8: N/A | V8: N/A | W8: N/A | X8: X | Y8: N/A | Z8: N/A | AA8: N/A | AB8: X | AC8: 1 | AF8: stg_khnh.fls_ops | AG8: fuel | AH8: So sánh lũy kế thực hiện năm với mục tiêu tiêu thụ nhiên liệu lấy từ PMS | AJ8: Energy consumption within the organization | AK8: Năng lượng tiêu thụ trong tổ chức | AM8: Combo chart
A9: 7 | B9: Tổ Khai thác | C9: MS Lê | D9: NhiPLH | E9: GRI 302-1 | F9: =VLOOKUP(E9,'95 Chỉ tiêu'!$B$4:$F$177,2,0) -> #N/A | G9: Energy and Emissions | H9: Năng lượng tiêu thụ trong tổ chức | I9: CT 1.7 | J9: Monthly Fuel Consumption in the Current Year | K9: Tiêu thụ nhiên liệu theo tháng trong năm hiện tại (Lít) | L9: Chị Lê | M9: - Tổng lượng nhiên liệu tiêu thụ theo từng tháng trong năm hiện tại phục vụ hoạt động khai thác bay. - Dữ liệu bao gồm cả nhiên liệu Jet A-1 và nhiên liệu SAF được sử dụng trong kỳ báo cáo. | N9: - Tổng nhiên liệu tiêu thụ theo tháng = Tổng lượng tiêu thụ Jet A-1 + Tổng lượng tiêu thụ SAF trong tháng tương ứng. - Dữ liệu được tổng hợp và hiển thị theo từng tháng của năm hiện tại. | O9: - Lít | P9: - Tham chiếu nguồn dữ liệu của CT 1.2 và CT 1.3.P12 | Q9: - Hàng tháng (ngày cuối cùng trong tháng). | R9: - Năm, Tháng | S9: N/A | T9: X | U9: N/A | V9: N/A | W9: N/A | X9: N/A | Y9: N/A | Z9: X | AA9: N/A | AB9: N/A | AC9: 2 | AF9: Thừa kế luồng | AG9: N/A | AH9: Tổng hợp dữ liệu hiển thị theo chu kỳ tháng để so sánh biến động cùng kỳ. Đơn vị: Lít. | AI9: Chưa có ANCM | AJ9: Energy consumption within the organization | AK9: Năng lượng tiêu thụ trong tổ chức | AM9: Stacked column
A10: 8 | B10: Tổ Khai thác | C10: MS Lê | D10: NhiPLH | E10: GRI 302-1 | F10: =VLOOKUP(E10,'95 Chỉ tiêu'!$B$4:$F$177,2,0) -> #N/A | G10: Energy and Emissions | H10: Năng lượng tiêu thụ trong tổ chức | I10: CT 1.8 | J10: Annual Jet A-1 Fuel Consumption Trend | K10: Tiêu thụ nhiên liệu Jet A-1 qua các năm | L10: Chị Lê | M10: - Tổng lượng nhiên liệu tiêu thụ Jet A-1 trong 10 năm gần nhất. | N10: - Nhiên liệu tiêu thụ Jet A-1 = Tổng nhiên liệu tiêu thụ - Lượng SAF nguyên chất. | O10: - Lít | P10: - Tham chiếu nguồn dữ liệu của CT 1.2 và CT 1.3.P12 | Q10: - Hàng tháng (ngày cuối cùng trong tháng). | R10: - Năm, Tháng | S10: N/A | T10: N/A | U10: N/A | V10: N/A | W10: N/A | X10: N/A | Y10: N/A | Z10: N/A | AA10: N/A | AB10: N/A | AC10: 2 | AF10: Thừa kế luồng
A11: 9 | B11: Tổ Khai thác | C11: MS Lê | D11: NhiPLH | E11: GRI 302-1 | F11: =VLOOKUP(E11,'95 Chỉ tiêu'!$B$4:$F$177,2,0) -> #N/A | G11: Energy and Emissions | H11: Năng lượng tiêu thụ trong tổ chức | I11: CT 1.9 | J11: Annual Neat SAF Consumption Trend | K11: Tiêu thụ nhiên liệu SAF qua các năm | L11: Chị Lê | M11: - Tổng lượng nhiên liệu tiêu thụ SAF nguyên chất (Neat SAF) trong 10 năm gần nhất. | N11: - Nhiên liệu tiêu thụ SAF = Tổng lượng SAF nguyên chất được xác định trong chứng nhận từ nhà cung cấp tại các sân bay. | O11: - Lít | P11: - ANCM | Q11: - Hàng tháng (ngày cuối cùng trong tháng). | R11: - Năm, Tháng | S11: N/A | T11: N/A | U11: N/A | V11: N/A | W11: N/A | X11: N/A | Y11: N/A | Z11: N/A | AA11: N/A | AB11: N/A | AC11: 2 | AF11: Thừa kế luồng
A12: 10 | B12: Tổ Khai thác | C12: MS Lê | D12: NhiPLH | E12: GRI 302-4 | F12: =VLOOKUP(E12,'95 Chỉ tiêu'!$B$4:$F$177,2,0) -> #N/A | G12: Energy and Emissions | H12: Tiết kiệm năng lượng trong tổ chức | I12: CT 1.10 | J12: Total Energy Saved | K12: Tổng năng lượng tiết kiệm (Lít) | L12: Chị Lê | M12: - Là tổng lượng năng lượng hàng không được tiết kiệm trong kỳ báo cáo thông qua các chương trình tối ưu khai thác, tiết kiệm nhiên liệu và sử dụng nhiên liệu hàng không bền vững (SAF), bao gồm: + Năng lượng tiết kiệm từ nhiên liệu Jet A-1; + Năng lượng tiết kiệm từ việc sử dụng SAF. - Dữ liệu hiện được theo dõi ở mức tổng hợp theo tháng và theo năm, không thực hiện bóc tách chi tiết theo từng chuyến bay. | N12: =- J38 -> 0 | O12: - Lít | P12: - Nhập thủ công. | Q12: - Hàng tháng (ngày cuối cùng trong tháng). | R12: - Năm | S12: N/A | T12: N/A | U12: N/A | V12: N/A | W12: N/A | X12: N/A | Y12: N/A | Z12: N/A | AA12: N/A | AB12: N/A | AC12: 1 | AF12: Thừa kế luồng | AJ12: Reduction of energy consumption | AK12: Giảm tiêu thụ năng lượng | AM12: Card
A13: 11 | B13: Tổ Khai thác | C13: MS Lê | D13: NhiPLH | E13: GRI 302-4 | F13: =VLOOKUP(E13,'95 Chỉ tiêu'!$B$4:$F$177,2,0) -> #N/A | G13: Energy and Emissions | H13: Tiết kiệm năng lượng trong tổ chức | I13: CT 1.11 | J13: Total Fuel Savings | K13: Tổng tiết kiệm nhiên liệu (kg) | L13: Chị Lê | M13: - Là tổng lượng nhiên liệu hàng không được tiết kiệm trong kỳ báo cáo, được quy đổi từ tổng năng lượng tiết kiệm theo đơn vị khối lượng. - Chỉ tiêu được tính toán dựa trên tổng năng lượng tiết kiệm (Lít) từ các chương trình tối ưu khai thác, tiết kiệm nhiên liệu và sử dụng nhiên liệu hàng không bền vững (SAF). | N13: - Không có | O13: - kg | P13: - Nhập thủ công. | Q13: - Hàng tháng (trước ngày 15 tháng kế tiếp). | R13: - Năm | S13: N/A | T13: N/A | U13: N/A | V13: N/A | W13: N/A | X13: N/A | Y13: N/A | Z13: N/A | AA13: N/A | AB13: N/A | AC13: 1 | AF13: Thừa kế luồng | AJ13: Reduction of energy consumption | AK13: Giảm tiêu thụ năng lượng | AM13: Card
A14: 12 | B14: Tổ Khai thác | C14: MS Lê | D14: NhiPLH | E14: GRI 302-4 | F14: =VLOOKUP(E14,'95 Chỉ tiêu'!$B$4:$F$177,2,0) -> #N/A | G14: Energy and Emissions | H14: Tiết kiệm năng lượng trong tổ chức | I14: CT 1.12 | J14: Total GHG Emissions Reduction | K14: Tổng giảm phát thải khí nhà kính (Tấn) | L14: Chị Lê | M14: - Là tổng lượng phát thải khí nhà kính (GHG) được giảm thiểu trong kỳ báo cáo thông qua các hoạt động tối ưu khai thác, tiết kiệm nhiên liệu và sử dụng nhiên liệu hàng không bền vững (SAF). - Chỉ tiêu hiện được kế thừa từ số liệu báo cáo GRI 305-5 về giảm phát thải khí nhà kính trực tiếp (Phạm vi 1), được tính toán dựa trên lượng nhiên liệu hàng không tiêu thụ quy đổi sang lượng phát thải CO₂ tương đương. | N14: - Tổng giảm phát thải khí nhà kính (tấn) = Tổng phát thải giảm nhờ các biện pháp tiết kiệm nhiên liệu nhiên liệu + Tổng giảm phát thải nhờ sử dụng SAF + Tổng phát thải đền bù | O14: - tấn | P14: - Tổng nhiên liệu tiêu thụ: FIMS. | Q14: - Hàng tháng (ngày cuối cùng trong tháng). | R14: - Năm | S14: N/A | T14: N/A | U14: N/A | V14: N/A | W14: N/A | X14: N/A | Y14: N/A | Z14: N/A | AA14: N/A | AB14: N/A | AC14: 1 | AE14: Chỉ tiêu được lấy từ báo cáo GRI 305-5: Phát thải khí nhà kính trực tiếp (Phạm vi 1). | AF14: Thừa kế luồng | AJ14: Reduction of energy consumption | AK14: Giảm tiêu thụ năng lượng | AM14: Card
A15: 13 | B15: Tổ Khai thác | C15: MS Lê | D15: NhiPLH | E15: GRI 302-4 | F15: =VLOOKUP(E15,'95 Chỉ tiêu'!$B$4:$F$177,2,0) -> #N/A | G15: Energy and Emissions | H15: Tiết kiệm năng lượng trong tổ chức | I15: CT 1.13 | J15: Annual Energy Savings vs Target | K15: Năng lượng tiết kiệm theo năm so với mục tiêu (Lít) | L15: Chị Lê | M15: - Là chỉ tiêu thể hiện xu hướng tổng năng lượng tiết kiệm được theo từng năm so với mục tiêu đề ra trong giai đoạn 10 năm gần nhất. Chỉ tiêu bao gồm tổng năng lượng tiết kiệm từ: + Nhiên liệu Jet A-1; + Nhiên liệu hàng không bền vững (SAF). | N15: - Không có. | O15: - Lít | P15: - Nhập thủ công. | Q15: - Theo tháng hoặc theo năm (ngày cuối cùng trong tháng). | R15: - Năm | S15: N/A | T15: N/A | U15: N/A | V15: N/A | W15: N/A | X15: X | Y15: N/A | Z15: N/A | AA15: N/A | AB15: X | AC15: 2 | AF15: Thừa kế luồng | AJ15: Reduction of energy consumption | AK15: Giảm tiêu thụ năng lượng | AM15: Combo chart
A16: 14 | B16: Tổ Khai thác | C16: MS Lê | D16: NhiPLH | E16: GRI 302-4 | F16: =VLOOKUP(E16,'95 Chỉ tiêu'!$B$4:$F$177,2,0) -> #N/A | G16: Energy and Emissions | H16: Tiết kiệm năng lượng trong tổ chức | I16: CT 1.14 | J16: Annual Fuel Savings vs Target | K16: Kết quả tiết kiệm nhiên liệu theo năm so với mục tiêu (kg) | L16: Chị Lê | M16: - Là chỉ tiêu thể hiện xu hướng tổng khối lượng nhiên liệu tiết kiệm được theo từng năm so với mục tiêu đề ra trong giai đoạn 10 năm gần nhất. Chỉ tiêu bao gồm tổng nhiên liệu tiết kiệm từ: + Nhiên liệu Jet A-1; + Nhiên liệu hàng không bền vững (SAF). | N16: - Không có. | O16: - Lít | P16: - Nhập thủ công. | Q16: - Theo tháng hoặc theo năm (ngày cuối cùng trong tháng). | R16: - Năm | S16: N/A | T16: N/A | U16: N/A | V16: N/A | W16: N/A | X16: N/A | Y16: N/A | Z16: X | AA16: N/A | AB16: N/A | AC16: 2 | AE16: - Mong muốn so sánh thực hiện với mục tiêu. | AF16: Thừa kế luồng | AJ16: Reduction of energy consumption | AK16: Giảm tiêu thụ năng lượng | AM16: Combo chart
A17: 15 | B17: Tổ Khai thác | C17: MS Lê | D17: NhiPLH | E17: GRI 302-4 | F17: =VLOOKUP(E17,'95 Chỉ tiêu'!$B$4:$F$177,2,0) -> #N/A | G17: Energy and Emissions | H17: Tiết kiệm năng lượng trong tổ chức | I17: CT 1.15 | J17: Monthly Energy Savings in the Year | K17: Năng lượng tiết kiệm theo tháng trong năm (Lít) | L17: Chị Lê | M17: - Là chỉ tiêu thể hiện tổng năng lượng tiết kiệm được theo từng tháng trong năm hiện tại từ các hoạt động tối ưu khai thác và sử dụng nhiên liệu hiệu quả. Chỉ tiêu bao gồm: + Năng lượng tiết kiệm từ nhiên liệu Jet A-1; + Năng lượng tiết kiệm từ nhiên liệu hàng không bền vững (SAF). | N17: - Không có. | O17: - Lít | P17: - Nhập thủ công. | Q17: - Hàng tháng (ngày cuối cùng trong tháng). | R17: - Năm | S17: N/A | T17: N/A | U17: N/A | V17: N/A | W17: N/A | X17: N/A | Y17: N/A | Z17: N/A | AA17: N/A | AB17: N/A | AC17: 2 | AF17: Thừa kế luồng | AJ17: Reduction of energy consumption | AK17: Giảm tiêu thụ năng lượng | AM17: Column
A18: 16 | B18: Tổ Khai thác | C18: MS Lê | D18: HungND2 | E18: GRI 305-1 | F18: =VLOOKUP(E18,'95 Chỉ tiêu'!$B$4:$F$177,2,0) -> #N/A | G18: Energy and Emissions | H18: Phát thải khí nhà kính trực tiếp (Phạm vi 1) | I18: CT 1.16 | J18: Total Emission | K18: Tổng phát thải khí nhà kính | L18: Chị Lê | M18: - Tổng lượng phát thải khí nhà kính phát sinh trực tiếp từ các nguồn do Vietnam Airlines sở hữu hoặc kiểm soát trong kỳ báo cáo. | N18: - Tổng phát thải khí nhà kính = Phát thải Jet A-1 + Phát thải SAF | O18: - Tấn | P18: - Kế thừa trực tiếp từ dữ liệu tiêu thụ nhiên liệu (GRI 302-1) bao gồm hóa đơn nạp nhiên liệu bay, Techlog | Q18: - Hàng tháng (ngày cuối cùng trong tháng). | R18: - Năm | S18: N/A | T18: N/A | U18: N/A | V18: N/A | W18: N/A | X18: N/A | Y18: N/A | Z18: N/A | AA18: N/A | AB18: X | AC18: 1 | AD18: FLIGHT_INTERGRATED.xlsx | AF18: Thừa kế luồng | AJ18: Direct (Scope 1) GHG emissions | AK18: Phát thải khí nhà kính trực tiếp (Phạm vi 1) | AM18: Card
A19: 17 | B19: Tổ Khai thác | C19: MS Lê | D19: HungND2 | E19: GRI 305-1 | F19: =VLOOKUP(E19,'95 Chỉ tiêu'!$B$4:$F$177,2,0) -> #N/A | G19: Energy and Emissions | H19: Phát thải khí nhà kính trực tiếp (Phạm vi 1) | I19: CT 1.17 | J19: Jet A-1 Emissions | K19: Phát thải Jet A-1 | L19: Chị Lê | M19: - Lượng khí nhà kính phát thải vào khí quyển từ việc tiêu thụ nhiên liệu hàng không gốc hóa thạch (Jet A-1) trong quá trình vận hành các chuyến bay của Vietnam Airlines. - Chỉ tiêu này bóc tách riêng biệt phần phát thải từ nhiên liệu truyền thống ra khỏi tổng phát thải, không bao gồm phát thải từ nhiên liệu bền vững (SAF) | N19: - Phát thải Jet A-1 (Tấn) = Nhiên liệu tiêu thụ Jet A-1 (Lít) * 0.8 / 1000 * Hệ số phát thải CO2 | O19: - Tấn | P19: - Kế thừa trực tiếp từ dữ liệu nhiên liệu tiêu thụ Jet A-1 (GRI 302-1), phần mềm FIMS là nơi quản lý dữ liệu nạp Jet A-1 | Q19: - Hàng tháng (ngày cuối cùng trong tháng). | R19: - Năm | S19: N/A | T19: N/A | U19: N/A | V19: N/A | W19: N/A | X19: N/A | Y19: N/A | Z19: N/A | AA19: N/A | AB19: X | AC19: 1 | AF19: Thừa kế luồng | AJ19: Direct (Scope 1) GHG emissions | AK19: Phát thải khí nhà kính trực tiếp (Phạm vi 1) | AM19: Card
A20: 18 | B20: Tổ Khai thác | C20: MS Lê | D20: HungND2 | E20: GRI 305-1 | F20: =VLOOKUP(E20,'95 Chỉ tiêu'!$B$4:$F$177,2,0) -> #N/A | G20: Energy and Emissions | H20: Phát thải khí nhà kính trực tiếp (Phạm vi 1) | I20: CT 1.18 | J20: SAF Emissions | K20: Phát thải SAF | L20: Chị Lê | M20: - Đây là lượng khí nhà kính phát thải từ quá trình đốt cháy phần Nhiên liệu hàng không bền vững (SAF) được pha trộn vào nhiên liệu cấp cho các chuyến bay của Vietnam Airlines trong kỳ báo cáo. | N20: - Phát thải SAF = Hàm lượng năng lượng (MJ) * Cường độ phát thải CO2 tương đương của vòng đời (gCO2e/MJ) / 1000000 Trong đó: + Hàm lượng năng lượng (Energy content) + Cường độ phát thải CO2 tương đương của vòng đời (CO2e lifecycle emissions intensity) | O20: - Tấn | P20: - Kế thừa trực tiếp từ dữ liệu nhiên liệu tiêu thụ Jet A-1 (GRI 302-1), phần mềm FIMS là nơi quản lý dữ liệu nạp Jet A-1 - Hàm lượng năng lượng, Cường độ phát thải CO2 tương đương của vòng đời: Lấy từ chứng nhận nạp SAF tại mỗi sân bay. | Q20: - Hàng tháng (ngày cuối cùng trong tháng). | R20: - Năm | S20: N/A | T20: N/A | U20: N/A | V20: N/A | W20: N/A | X20: N/A | Y20: N/A | Z20: N/A | AA20: N/A | AB20: X | AC20: 1 | AF20: Thừa kế luồng | AJ20: Direct (Scope 1) GHG emissions | AK20: Phát thải khí nhà kính trực tiếp (Phạm vi 1) | AM20: Card
A21: 19 | B21: Tổ Khai thác | C21: MS Lê | D21: HungND2 | E21: GRI 305-1 | F21: =VLOOKUP(E21,'95 Chỉ tiêu'!$B$4:$F$177,2,0) -> #N/A | G21: Energy and Emissions | H21: Phát thải khí nhà kính trực tiếp (Phạm vi 1) | I21: CT 1.19 | J21: Annual Emissions vs. Target | K21: Phát thải khí nhà kính theo năm vs. Mục tiêu | L21: Chị Lê | M21: - Tổng lượng phát thải thực tế theo từng năm và so sánh với mức mục tiêu phát thải đã được kế hoạch hoặc hãng hàng không đặt ra. - Dữ liệu bao gồm tổng lượng phát thải Jet A-1 và SAF sử dụng cho hoạt động khai thác bay trong năm báo cáo. | N21: - Phát thải nhà kính theo năm = Phát thải Jet A-1 + Phát thải SAF (theo năm) | O21: - Tấn | P21: - Tham chiếu nguồn dữ liệu của CT 1.2 và CT 1.3. | Q21: - Cuối năm (ngày cuối cùng trong năm). | R21: - Năm | AC21: 1 | AF21: Thừa kế luồng | AJ21: Direct (Scope 1) GHG emissions | AK21: Phát thải khí nhà kính trực tiếp (Phạm vi 1) | AM21: Stacked Bar Chart
A22: 20 | B22: Tổ Khai thác | C22: MS Lê | D22: HungND2 | E22: GRI 305-1 | F22: =VLOOKUP(E22,'95 Chỉ tiêu'!$B$4:$F$177,2,0) -> #N/A | G22: Energy and Emissions | H22: Phát thải khí nhà kính trực tiếp (Phạm vi 1) | I22: CT 1.20 | J22: Monthly Emissions in Current Year | K22: Phát thải khí nhà kính theo tháng trong năm hiện tại | L22: Chị Lê | M22: - Tổng phát thải theo từng tháng trong năm hiện tại phục vụ hoạt động khai thác bay. - Dữ liệu bao gồm cả nhiên liệu Jet A-1 và nhiên liệu SAF được sử dụng trong kỳ báo cáo. | N22: - Phát thải nhà kính theo tháng = Phát thải Jet A-1 + Phát thải SAF trong tháng tương ứng. - Dữ liệu được tổng hợp và hiển thị theo từng tháng của năm hiện tại. | O22: - Tấn | P22: - Tham chiếu nguồn dữ liệu của CT 1.2 và CT 1.3. | Q22: - Theo tháng hoặc theo năm (ngày cuối cùng trong tháng). | R22: - Năm | AC22: 1 | AF22: Thừa kế luồng | AJ22: Direct (Scope 1) GHG emissions | AK22: Phát thải khí nhà kính trực tiếp (Phạm vi 1) | AM22: Stacked Bar Chart
A23: 21 | B23: Tổ Khai thác | C23: MS Lê | D23: HungND2 | E23: GRI 305-4 | F23: =VLOOKUP(E23,'95 Chỉ tiêu'!$B$4:$F$177,2,0) -> #N/A | G23: Energy and Emissions | H23: Cường độ phát thải khí nhà kính | I23: CT 1.21 | J23: Total Emissions Intensity | K23: Tổng cường độ phát thải khí nhà kính | L23: Chị Lê | M23: - Cường độ phát thải là tỷ số giữa mức phát thải khí nhà kính chia cho một đơn vị tham chiếu đặc trưng của tổ chức (mẫu số chung). Trong ngành hàng không, để bao hàm cả vận tải hành khách và hàng hóa (đặc thù của VNA), mẫu số chung chuẩn mực nhất thường được sử dụng là RTK (Revenue Tonne-Kilometres - Tấn-Kilomet thực hiện) | N23: - Cường độ phát thải khí nhà kính = Tổng phát thải khí nhà kính / Tổng RTK | O23: - Tấn/100 RTK | P23: - Tổng phát thải khí nhà kính được thừa hưởng kết quả từ báo cáo GRI 305-4 - Số RTK được lấy từ phần mềm RPS | Q23: - Hàng tháng (ngày cuối cùng trong tháng). | R23: - Năm | S23: N/A | T23: N/A | U23: N/A | V23: N/A | W23: N/A | X23: N/A | Y23: N/A | Z23: N/A | AA23: N/A | AB23: X | AC23: 1 | AF23: Thừa kế luồng | AJ23: GHG emissions intensity | AK23: Cường độ phát thải khí nhà kính | AM23: Card
A24: 22 | B24: Tổ Khai thác | C24: MS Lê | D24: HungND2 | E24: GRI 305-4 | F24: =VLOOKUP(E24,'95 Chỉ tiêu'!$B$4:$F$177,2,0) -> #N/A | G24: Energy and Emissions | H24: Cường độ phát thải khí nhà kính | I24: CT 1.22 | J24: Total Emission | K24: Tổng phát thải khí nhà kính | L24: Chị Lê | M24: - Tổng lượng phát thải khí nhà kính phát sinh trực tiếp từ các nguồn do Vietnam Airlines sở hữu hoặc kiểm soát trong kỳ báo cáo. | N24: - Tổng phát thải khí nhà kính = Phát thải Jet A-1 + Phát thải SAF | O24: - Tấn | P24: - Kế thừa trực tiếp từ dữ liệu tiêu thụ nhiên liệu (GRI 302-1) bao gồm hóa đơn nạp nhiên liệu bay, Techlog | Q24: - Hàng tháng (ngày cuối cùng trong tháng). | R24: - Năm | S24: N/A | T24: N/A | U24: N/A | V24: N/A | W24: N/A | X24: N/A | Y24: N/A | Z24: N/A | AA24: N/A | AB24: X | AC24: 1 | AF24: Thừa kế luồng | AJ24: GHG emissions intensity | AK24: Cường độ phát thải khí nhà kính | AM24: Card
A25: 23 | B25: Tổ Khai thác | C25: MS Lê | D25: HungND2 | E25: GRI 305-4 | F25: =VLOOKUP(E25,'95 Chỉ tiêu'!$B$4:$F$177,2,0) -> #N/A | G25: Energy and Emissions | H25: Cường độ phát thải khí nhà kính | I25: CT 1.23 | J25: Total RTK | K25: Tổng RTK | L25: Chị Lê | M25: - RTK là đơn vị chuẩn quốc tế đo lường khối lượng công việc vận chuyển thực tế có sinh lời của một hãng hàng không. | N25: - Tổng RTK là tổng cộng RTK của tất cả các chặng bay | O25: - RTK | P25: - Phần mềm RPS | Q25: - Hàng tháng (ngày cuối cùng trong tháng). | R25: - Năm | S25: N/A | T25: N/A | U25: N/A | V25: N/A | W25: N/A | X25: N/A | Y25: N/A | Z25: N/A | AA25: N/A | AB25: N/A | AC25: 1 | AF25: Thừa kế luồng | AJ25: GHG emissions intensity | AK25: Cường độ phát thải khí nhà kính | AM25: Card
A26: 24 | B26: Tổ Khai thác | C26: MS Lê | D26: HungND2 | E26: GRI 305-4 | F26: =VLOOKUP(E26,'95 Chỉ tiêu'!$B$4:$F$177,2,0) -> #N/A | G26: Energy and Emissions | H26: Cường độ phát thải khí nhà kính | I26: CT 1.24 | J26: Annual Emissions Intensity vs. Target | K26: Cường độ phát thải khí nhà kính theo năm vs. Mục tiêu | L26: Chị Lê | M26: - Cường độ phát thải thực tế theo từng năm và so sánh với mức mục tiêu cường độ phát thải đã được kế hoạch hoặc hãng hàng không đặt ra. | N26: - Cường độ phát thải nhà kính theo năm = Tổng phát thải khí nhà kính / Tổng RTK (theo năm) | O26: - Tấn/100 RTK | P26: - Tham chiếu nguồn dữ liệu của CT 1.2 và CT 1.3. | Q26: - Cuối năm (ngày cuối cùng trong năm). | R26: - Năm | S26: N/A | T26: N/A | U26: N/A | V26: N/A | W26: N/A | X26: N/A | Y26: N/A | Z26: N/A | AA26: N/A | AB26: X | AC26: 1 | AF26: Thừa kế luồng | AJ26: GHG emissions intensity | AK26: Cường độ phát thải khí nhà kính | AM26: Bar Chart
A27: 25 | B27: Tổ Khai thác | C27: MS Lê | D27: HungND2 | E27: GRI 305-4 | F27: =VLOOKUP(E27,'95 Chỉ tiêu'!$B$4:$F$177,2,0) -> #N/A | G27: Energy and Emissions | H27: Cường độ phát thải khí nhà kính | I27: CT 1.25 | J27: Monthly Emissions Intensity in Current Year | K27: Cường độ phát thải nhà kính theo tháng trong năm hiện tại | L27: Chị Lê | M27: - Cường độ phát thải theo từng tháng trong năm hiện tại phục vụ hoạt động khai thác bay. | N27: - Cường độ phát thải nhà kính theo năm = Tổng phát thải khí nhà kính / Tổng RTK trong tháng tương ứng. - Dữ liệu được tổng hợp và hiển thị theo từng tháng của năm hiện tại. | O27: - Tấn/100 RTK | P27: - Tham chiếu nguồn dữ liệu của CT 1.2 và CT 1.3. | Q27: - Theo tháng hoặc theo năm (ngày cuối cùng trong tháng). | R27: - Năm | S27: N/A | T27: N/A | U27: N/A | V27: N/A | W27: N/A | X27: N/A | Y27: N/A | Z27: X | AA27: N/A | AB27: N/A | AC27: 1 | AF27: Thừa kế luồng | AJ27: GHG emissions intensity | AK27: Cường độ phát thải khí nhà kính | AM27: Bar Chart
A28: 26 | B28: Tổ Khai thác | C28: MS Lê | D28: HungND2 | E28: GRI 305-5 | F28: =VLOOKUP(E28,'95 Chỉ tiêu'!$B$4:$F$177,2,0) -> #N/A | G28: Energy and Emissions | H28: Giảm phát thải khí nhà kính | I28: CT 1.26 | J28: Total Reduction of Emissions | K28: Tổng giảm phát thải khí nhà kính | L28: Chị Lê | M28: - Lượng khí nhà kính (CO2) giảm được nhờ áp dụng các biện pháp tiết kiệm nhiên liệu, tối ưu nhiên liệu sử dụng trong khai thác tàu bay và sử dụng nhiên liệu SAF | N28: -Tổng giảm phát thải khí nhà kính (tấn) = Tổng phát thải giảm nhờ các biện pháp tiết kiệm nhiên liệu + Tổng giảm phát thải nhờ sử dụng SAF + Tổng phát thải đền bù | O28: - Tấn | P28: - Tham chiếu nguồn dữ liệu | Q28: - Theo tháng hoặc theo năm (ngày cuối cùng trong tháng). | R28: - Năm | S28: N/A | T28: N/A | U28: N/A | V28: N/A | W28: N/A | X28: N/A | Y28: N/A | Z28: N/A | AA28: N/A | AB28: N/A | AC28: 1 | AF28: Thừa kế luồng | AJ28: Reduction of GHG emissions | AK28: Giảm phát thải khí nhà kính | AM28: Card
A29: 27 | B29: Tổ Khai thác | C29: MS Lê | D29: HungND2 | E29: GRI 305-5 | F29: =VLOOKUP(E29,'95 Chỉ tiêu'!$B$4:$F$177,2,0) -> #N/A | G29: Energy and Emissions | H29: Giảm phát thải khí nhà kính | I29: CT 1.27 | J29: Total Energy Saved | K29: Tổng năng lượng tiết kiệm | L29: Chị Lê | M29: - Là tổng lượng năng lượng hàng không được tiết kiệm trong kỳ báo cáo thông qua các chương trình tối ưu khai thác, tiết kiệm nhiên liệu và sử dụng nhiên liệu hàng không bền vững (SAF), | N29: - Không có | O29: - Tấn | P29: - Tham chiếu nguồn dữ liệu | Q29: - Theo tháng hoặc theo năm (ngày cuối cùng trong tháng). | R29: - Năm | S29: N/A | T29: N/A | U29: N/A | V29: N/A | W29: N/A | X29: N/A | Y29: N/A | Z29: N/A | AA29: N/A | AB29: N/A | AC29: 1 | AF29: Thừa kế luồng | AJ29: Reduction of GHG emissions | AK29: Giảm phát thải khí nhà kính | AM29: Card
A30: 28 | B30: Tổ Khai thác | C30: MS Lê | D30: HungND2 | E30: GRI 305-5 | F30: =VLOOKUP(E30,'95 Chỉ tiêu'!$B$4:$F$177,2,0) -> #N/A | G30: Energy and Emissions | H30: Giảm phát thải khí nhà kính | I30: CT 1.28 | J30: Energy-Saving Emission Reduction | K30: Tổng giảm phát thải nhờ các biện pháp tiết kiệm nhiên liệu | L30: Chị Lê | M30: - Là lượng CO2e được ngăn chặn xả ra môi trường trực tiếp nhờ vào các sáng kiến tối ưu hóa quy trình khai thác bay và bảo dưỡng kỹ thuật, giúp làm giảm lượng nhiên liệu hóa thạch (Jet A-1) tiêu thụ thực tế. | N30: - Tổng phát thải giảm nhờ các biện pháp tiết kiệm nhiên liệu = Tổng nhiên liệu tiết kiệm (Lít) * 0.8 / 1000 * Hệ số phát thải CO2 | O30: - Tấn | P30: - Tham chiếu nguồn dữ liệu | Q30: - Theo tháng hoặc theo năm (ngày cuối cùng trong tháng). | R30: - Năm | S30: N/A | T30: N/A | U30: N/A | V30: N/A | W30: N/A | X30: N/A | Y30: N/A | Z30: N/A | AA30: N/A | AB30: N/A | AC30: 1 | AF30: Thừa kế luồng | AJ30: Reduction of GHG emissions | AK30: Giảm phát thải khí nhà kính | AM30: Card
A31: 29 | B31: Tổ Khai thác | C31: MS Lê | D31: HungND2 | E31: GRI 305-5 | F31: =VLOOKUP(E31,'95 Chỉ tiêu'!$B$4:$F$177,2,0) -> #N/A | G31: Energy and Emissions | H31: Giảm phát thải khí nhà kính | I31: CT 1.29 | J31: SAF-Related Emission Reduction | K31: Tổng giảm phát thải nhờ sử dụng SAF | L31: Chị Lê | M31: - Là lượng phát thải khí nhà kính được cắt giảm nhờ việc Hãng thay thế một phần nhiên liệu hóa thạch truyền thống (Jet A-1) bằng Nhiên liệu hàng không bền vững (SAF) | N31: - Tổng phát thải giảm nhờ sử dụng SAF (Tấn) = Hàm lượng năng lượng (MJ) * (Cường độ phát thải cơ sở của nhiên liệu hóa thạch (gCO2e/MJ) - Cường độ phát thải CO2 tương đương của vòng đời (gCO2e/MJ)) / 1000000 | O31: - Tấn | P31: - Tham chiếu nguồn dữ liệu | Q31: - Theo tháng hoặc theo năm (ngày cuối cùng trong tháng). | R31: - Năm | S31: N/A | T31: N/A | U31: N/A | V31: N/A | W31: N/A | X31: N/A | Y31: N/A | Z31: N/A | AA31: N/A | AB31: N/A | AC31: 1 | AF31: Thừa kế luồng | AJ31: Reduction of GHG emissions | AK31: Giảm phát thải khí nhà kính | AM31: Card
A32: 30 | B32: Tổ Khai thác | C32: MS Lê | D32: HungND2 | E32: GRI 305-5 | F32: =VLOOKUP(E32,'95 Chỉ tiêu'!$B$4:$F$177,2,0) -> #N/A | G32: Energy and Emissions | H32: Giảm phát thải khí nhà kính | I32: CT 1.30 | J32: Total Emission Reduction through Carbon Offsetting | K32: Tổng phát thải đền bù | L32: Chị Lê | M32: - Là tổng lượng phát thải CO₂ cuối cùng mà hãng hàng không có nghĩa vụ phải bù trừ sau khi đã áp dụng các cơ chế giảm trừ theo quy định đối với 03 cơ chế EU ETS, UK ETS và CORSIA | N32: - Tổng phát thải đền bù = Lượng CO₂ cần đền bù (EU ETS) + Lượng CO₂ cần đền bù (UK ETS) + Lượng CO₂ cần đền bù (CORSIA). | O32: - Tấn | P32: - Tham chiếu nguồn dữ liệu | Q32: - Theo tháng hoặc theo năm (ngày cuối cùng trong tháng). | R32: - Năm | S32: N/A | T32: N/A | U32: N/A | V32: N/A | W32: N/A | X32: N/A | Y32: N/A | Z32: N/A | AA32: N/A | AB32: N/A | AC32: 1 | AF32: Thừa kế luồng | AJ32: Reduction of GHG emissions | AK32: Giảm phát thải khí nhà kính | AM32: Card
A33: 31 | B33: Tổ Khai thác | C33: MS Lê | D33: HungND2 | E33: GRI 305-5 | F33: =VLOOKUP(E33,'95 Chỉ tiêu'!$B$4:$F$177,2,0) -> #N/A | G33: Energy and Emissions | H33: Giảm phát thải khí nhà kính | I33: CT 1.31 | J33: Annual Reduction of Emissions vs. Target | K33: Giảm phát thải khí nhà kính theo năm vs. Mục tiêu | L33: Chị Lê | M33: - Giảm phát thải nhà kính theo từng năm và so sánh với mức mục tiêu đã được kế hoạch hoặc hãng hàng không đặt ra | N33: - Không có | O33: - Tấn | P33: - Tham chiếu nguồn dữ liệu | Q33: - Theo tháng hoặc theo năm (ngày cuối cùng trong tháng). | R33: - Năm | S33: N/A | T33: N/A | U33: N/A | V33: N/A | W33: N/A | X33: N/A | Y33: N/A | Z33: N/A | AA33: N/A | AB33: N/A | AC33: 1 | AF33: Thừa kế luồng | AJ33: Reduction of GHG emissions | AK33: Giảm phát thải khí nhà kính | AM33: Stacked Bar Chart
A34: 32 | B34: Tổ Khai thác | C34: MS Lê | D34: HungND2 | E34: GRI 305-5 | F34: =VLOOKUP(E34,'95 Chỉ tiêu'!$B$4:$F$177,2,0) -> #N/A | G34: Energy and Emissions | H34: Giảm phát thải khí nhà kính | I34: CT 1.32 | J34: Monthly Reduction of Emissions in Current Year | K34: Giảm phát thải khí nhà kính theo tháng trong năm hiện tại | L34: Chị Lê | M34: - Giảm phát thải theo từng tháng trong năm hiện tại phục vụ hoạt động khai thác bay | N34: - Không có | O34: - Tấn | P34: - Tham chiếu nguồn dữ liệu | Q34: - Theo tháng hoặc theo năm (ngày cuối cùng trong tháng). | R34: - Năm | S34: N/A | T34: N/A | U34: N/A | V34: N/A | W34: N/A | X34: N/A | Y34: N/A | Z34: N/A | AA34: N/A | AB34: N/A | AC34: 1 | AF34: Thừa kế luồng | AJ34: Reduction of GHG emissions | AK34: Giảm phát thải khí nhà kính | AM34: Stacked Bar Chart
A35: 33 | B35: Tổ Khai thác | C35: MS Lê | D35: HungND2 | E35: GRI 305-7 | F35: =VLOOKUP(E35,'95 Chỉ tiêu'!$B$4:$F$177,2,0) -> #N/A | G35: Energy and Emissions | H35: Nitrogen oxides (NOX), sulfur oxides (SOX), and other significant air emissions | K35: Tổng SOx phát thải | L35: Chị Lê | AE35: Không số hóa giai đoạn này | AJ35: Nitrogen oxides (NOX), sulfur oxides (SOX), and other significant air emissions | AK35: NOx, SOx và khí thải khác | AM35: Card
A36: 34 | B36: Tổ Khai thác | C36: MS Lê | D36: HungND2 | E36: GRI 305-7 | F36: =VLOOKUP(E36,'95 Chỉ tiêu'!$B$4:$F$177,2,0) -> #N/A | G36: Energy and Emissions | H36: Nitrogen oxides (NOX), sulfur oxides (SOX), and other significant air emissions | K36: Tổng NOx phát thải | L36: Chị Lê | AJ36: Nitrogen oxides (NOX), sulfur oxides (SOX), and other significant air emissions | AK36: NOx, SOx và khí thải khác | AM36: Card
A37: 35 | B37: Tổ Khai thác | C37: MS Lê | D37: HungND2 | E37: GRI 305-7 | F37: =VLOOKUP(E37,'95 Chỉ tiêu'!$B$4:$F$177,2,0) -> #N/A | G37: Energy and Emissions | H37: Nitrogen oxides (NOX), sulfur oxides (SOX), and other significant air emissions | K37: Tổng CO2 phát thải | L37: Chị Lê | AJ37: Nitrogen oxides (NOX), sulfur oxides (SOX), and other significant air emissions | AK37: NOx, SOx và khí thải khác | AM37: Card
A38: 36 | B38: Tổ Khai thác | C38: MS Lê | D38: HungND2 | E38: GRI 305-7 | F38: =VLOOKUP(E38,'95 Chỉ tiêu'!$B$4:$F$177,2,0) -> #N/A | G38: Energy and Emissions | H38: Nitrogen oxides (NOX), sulfur oxides (SOX), and other significant air emissions | K38: Phát thải SOx theo năm vs. Mục tiêu | L38: Chị Lê | AJ38: Nitrogen oxides (NOX), sulfur oxides (SOX), and other significant air emissions | AK38: NOx, SOx và khí thải khác | AM38: Bar chart
A39: 37 | B39: Tổ Khai thác | C39: MS Lê | D39: HungND2 | E39: GRI 305-7 | F39: =VLOOKUP(E39,'95 Chỉ tiêu'!$B$4:$F$177,2,0) -> #N/A | G39: Energy and Emissions | H39: Nitrogen oxides (NOX), sulfur oxides (SOX), and other significant air emissions | K39: Phát thải NOx theo năm vs. Mục tiêu | L39: Chị Lê | AJ39: Nitrogen oxides (NOX), sulfur oxides (SOX), and other significant air emissions | AK39: NOx, SOx và khí thải khác | AM39: Bar chart
A40: 38 | B40: Tổ Khai thác | C40: MS Lê | D40: HungND2 | E40: GRI 305-7 | F40: =VLOOKUP(E40,'95 Chỉ tiêu'!$B$4:$F$177,2,0) -> #N/A | G40: Energy and Emissions | H40: Nitrogen oxides (NOX), sulfur oxides (SOX), and other significant air emissions | K40: Phát thải NOx, SOx theo năm vs. Mục tiêu | L40: Chị Lê | AJ40: Nitrogen oxides (NOX), sulfur oxides (SOX), and other significant air emissions | AK40: NOx, SOx và khí thải khác | AM40: Stacked Bar Chart
A41: 39 | B41: Tổ Khai thác | C41: MS Lê | D41: HungND2 | E41: GRI 305-7 | F41: =VLOOKUP(E41,'95 Chỉ tiêu'!$B$4:$F$177,2,0) -> #N/A | G41: Energy and Emissions | H41: Nitrogen oxides (NOX), sulfur oxides (SOX), and other significant air emissions | K41: Phát thải NOx, SOx theo tháng trong năm bất kỳ | L41: Chị Lê | AJ41: Nitrogen oxides (NOX), sulfur oxides (SOX), and other significant air emissions | AK41: NOx, SOx và khí thải khác | AM41: Stacked Bar Chart
A42: 40 | B42: Tổ Kỹ thuật | C42: MS Quỳnh | D42: NhiPLH | E42: Không thuộc GRI | F42: =VLOOKUP(E42,'95 Chỉ tiêu'!$B$4:$F$177,2,0) -> #N/A | G42: Energy and Emissions | H42: Báo cáo sử dụng SAF | I42: CT 2.1 | J42: Total EU Flights | K42: Tổng số chuyến bay thương mại từ châu Âu | L42: Chị Quỳnh | M42: Tổng số chuyến bay thương mại có điểm khởi hành từ các sân bay thuộc Liên minh châu Âu trong kỳ báo cáo, không phân biệt loại hình khai thác chuyến bay. | N42: Chỉ tính các chuyến bay có sân bay khởi hành (DEP) từ các quốc gia theo quy định Liên minh Châu Âu | O42: Chuyến | P42: - EU ETS | Q42: - Hàng tháng (ngày cuối cùng trong tháng) | R42: - Năm | AJ42: SAF Report | AK42: Báo cáo sử dụng SAF | AL42: Tab 1: Overview | AM42: Card
A43: 41 | B43: Tổ Kỹ thuật | C43: MS Quỳnh | D43: NhiPLH | E43: Không thuộc GRI | F43: =VLOOKUP(E43,'95 Chỉ tiêu'!$B$4:$F$177,2,0) -> #N/A | G43: Energy and Emissions | H43: Báo cáo sử dụng SAF | I43: CT 2.2 | J43: Total Flight Hours | K43: Tổng số giờ bay | L43: Chị Quỳnh | M43: Tổng giờ bay thực tế của chuyến bay xuất phát từ Liên minh châu Âu từ khi lúc cất cánh đến khi hạ cánh. | N43: Tổng số giờ bay thực tế của chuyến bay (tính từ thời điểm tàu bay cất cánh (block-off) đến thời điểm hạ cánh (block-on) theo dữ liệu khai thác thực tế). | O43: Giờ | P43: - EU ETS | Q43: - Hàng tháng (ngày cuối cùng trong tháng) | R43: - Năm | AJ43: SAF Report | AK43: Báo cáo sử dụng SAF | AL43: Tab 1: Overview | AM43: Card
A44: 42 | B44: Tổ Kỹ thuật | C44: MS Quỳnh | D44: NhiPLH | E44: Không thuộc GRI | F44: =VLOOKUP(E44,'95 Chỉ tiêu'!$B$4:$F$177,2,0) -> #N/A | G44: Energy and Emissions | H44: Báo cáo sử dụng SAF | I44: CT 2.3 | J44: Planned SAF Volume (Tonnes) | K44: Lượng SAF kế hoạch ban đầu (tấn) | L44: Chị Quỳnh | M44: Là lượng nhiên liệu hàng không bền vững (SAF) được ước tính cần sử dụng trong kỳ theo kế hoạch. | N44: Lượng SAF kế hoạch ban đầu = Tổng nhiên liệu cần tra nạp theo kế hoạch * Tỷ lệ SAF theo quy định của nhà chức trách áp dụng tại thời điểm lập kế hoạch. | O44: Tấn | P44: ANCM | Q44: - Khi có quy định từ nhà chức trách | R44: - Năm | AJ44: SAF Report | AK44: Báo cáo sử dụng SAF | AL44: Tab 1: Overview | AM44: Card
A45: 43 | B45: Tổ Kỹ thuật | C45: MS Quỳnh | D45: NhiPLH | E45: Không thuộc GRI | F45: =VLOOKUP(E45,'95 Chỉ tiêu'!$B$4:$F$177,2,0) -> #N/A | G45: Energy and Emissions | H45: Báo cáo sử dụng SAF | I45: CT 2.4 | J45: Actual SAF Uplifted (Tonnes) | K45: Lượng SAF nạp thực tế (tấn) | L45: Chị Quỳnh | M45: Là tổng khối lượng nhiên liệu hàng không bền vững (SAF) đã được nạp thực tế cho tàu bay trong kỳ báo cáo, được xác định dựa trên hóa đơn hoặc xác nhận cung cấp nhiên liệu từ các nhà cung cấp tại sân bay. | N45: Không có | O45: Tấn | P45: ANCM | Q45: - Khi có chứng nhận nạp dầu từ NCC | R45: - Năm | AJ45: SAF Report | AK45: Báo cáo sử dụng SAF | AL45: Tab 1: Overview | AM45: Card
A46: 44 | B46: Tổ Kỹ thuật | C46: MS Quỳnh | D46: NhiPLH | E46: Không thuộc GRI | F46: =VLOOKUP(E46,'95 Chỉ tiêu'!$B$4:$F$177,2,0) -> #N/A | G46: Energy and Emissions | H46: Báo cáo sử dụng SAF | I46: CT 2.5 | J46: Neat SAF Ratio by Airport | K46: Tỷ lệ neat SAF theo sân bay | L46: Chị Quỳnh | M46: Là tỷ lệ giữa khối lượng nhiên liệu hàng không bền vững nguyên chất (Neat SAF) và tổng khối lượng nhiên liệu SAF pha trộn (Blended SAF) được nạp tại từng sân bay trong kỳ báo cáo. | N46: Tỷ lệ Neat SAF (%) = (Khối lượng SAF nguyên chất / Tổng khối lượng SAF pha trộn) * 100. | O46: % | P46: ANCM | Q46: - Khi có chứng nhận nạp dầu từ NCC | R46: - Năm | AJ46: SAF Report | AK46: Báo cáo sử dụng SAF | AL46: Tab 1: Overview | AM46: Bar Chart
A47: 46 | B47: Tổ Kỹ thuật | C47: MS Quỳnh | D47: NhiPLH | E47: Không thuộc GRI | F47: =VLOOKUP(E47,'95 Chỉ tiêu'!$B$4:$F$177,2,0) -> #N/A | G47: Energy and Emissions | H47: Báo cáo sử dụng SAF | I47: CT 2.6 | J47: Monthly SAF Uplift Volume | K47: Lượng SAF tra nạp theo tháng trong năm | L47: Chị Quỳnh | M47: Là tổng khối lượng nhiên liệu hàng không bền vững (SAF) được ghi nhận theo từng tháng trong kỳ báo cáo. | N47: Trường hợp đã có thư xác nhận: - Lượng SAF cho từng chuyến bay = (Lượng Neat SAF thực tế / Tổng nhiên liệu SAF pha trộn) * Lượng nhiên liệu nạp từng chuyến bay. - Lượng SAF nạp theo tháng = Σ Lượng SAF cho từng chuyến bay. Trường hợp chưa có thư xác nhận sẽ lấy theo số kế hoạch: - Lượng SAF cho từng chuyến bay = % SAF theo kế hoạch * Lượng nhiên liệu nạp từng chuyến bay. - Lượng SAF nạp heo tháng = Σ Lượng SAF cho từng chuyến bay. | O47: Tấn | P47: ANCM | Q47: - Khi có chứng nhận nạp dầu từ NCC | R47: - Năm | AE47: So sánh lượng nạp thực tế - kế hoạch | AJ47: SAF Report | AK47: Báo cáo sử dụng SAF | AL47: Tab 1: Overview | AM47: Combo chart
A48: 45 | B48: Tổ Kỹ thuật | C48: MS Quỳnh | D48: NhiPLH | E48: Không thuộc GRI | F48: =VLOOKUP(E48,'95 Chỉ tiêu'!$B$4:$F$177,2,0) -> #N/A | G48: Energy and Emissions | H48: Báo cáo sử dụng SAF | I48: CT 2.7 | J48: Monthly SAF Surcharge | K48: Phụ phí SAF theo tháng trong năm | L48: Chị Quỳnh | M48: Là tổng khối lượng nhiên liệu hàng không bền vững (SAF) đã được mua và phụ phí mua SAF phát sinh trong kỳ báo cáo, được tổng hợp theo từng năm dựa trên dữ liệu nạp nhiên liệu và dữ liệu tài chính liên quan đến SAF tại các sân bay thuộc phạm vi áp dụng. | N48: Lượng SAF theo tháng = Tổng khối lượng SAF pha trộn thực tế đã mua. Phụ phí SAF theo tháng = Phụ phí mua SAF phát sinh tương ứng với lượng SAF đã nạp. | O48: USD | P48: ANCM | Q48: - Khi có chứng nhận nạp dầu từ NCC | R48: - Năm | AE48: So sánh lượng mua và phụ phí SAF | AJ48: SAF Report | AK48: Báo cáo sử dụng SAF | AL48: Tab 1: Overview | AM48: Combo chart
A49: 47 | B49: Tổ Kỹ thuật | C49: MS Quỳnh | D49: NhiPLH | E49: Không thuộc GRI | F49: =VLOOKUP(E49,'95 Chỉ tiêu'!$B$4:$F$177,2,0) -> #N/A | G49: Energy and Emissions | H49: Báo cáo sử dụng SAF | I49: CT 2.8 | J49: SAF Purchase Volume by Eligible Fuel and Supplier | K49: Lượng mua SAF theo loại SAF & sân bay | L49: Chị Quỳnh | M49: Là tổng khối lượng nhiên liệu hàng không bền vững (SAF) đã được mua trong kỳ báo cáo, được phân loại theo: - Loại SAF (HEFA, FT, ATJ…); - Sân bay nạp nhiên liệu. | N49: Không có. | O49: Tấn | P49: ANCM | Q49: - Khi có chứng nhận nạp dầu từ NCC | R49: - Năm | AJ49: SAF Report | AK49: Báo cáo sử dụng SAF | AL49: Tab 1: Overview | AM49: Stacked Bar Chart
A50: 48 | B50: Tổ Kỹ thuật | C50: MS Quỳnh | D50: NhiPLH | E50: Không thuộc GRI | F50: =VLOOKUP(E50,'95 Chỉ tiêu'!$B$4:$F$177,2,0) -> #N/A | G50: Energy and Emissions | H50: Báo cáo sử dụng SAF | I50: CT 2.9 | J50: SAF Purchase Reporting | K50: Bảng chi tiết việc mua SAF | L50: Chị Quỳnh | M50: Là bảng dữ liệu chi tiết phục vụ theo dõi và báo cáo tình hình mua, nạp và sử dụng nhiên liệu hàng không bền vững (SAF) theo yêu cầu tuân thủ của ReFuelEU Aviation. | N50: Không có | O50: Tấn | P50: ANCM | Q50: - Khi có chứng nhận nạp dầu từ NCC | R50: - Năm | AJ50: SAF Report | AK50: Báo cáo sử dụng SAF | AL50: Tab 2: Fuel & SAF Purchase Reporting (ReFuelEU Aviation Template) | AM50: Table
A51: 49 | B51: Tổ Kỹ thuật | C51: MS Quỳnh | D51: NhiPLH | E51: Không thuộc GRI | F51: =VLOOKUP(E51,'95 Chỉ tiêu'!$B$4:$F$177,2,0) -> #N/A | G51: Energy and Emissions | H51: Báo cáo sử dụng SAF | I51: CT 2.10 | J51: Fuel Reporting | K51: Bảng chi tiết nhiên liệu tra nạp tại các sân bay | L51: Chị Quỳnh | M51: Là bảng dữ liệu chi tiết ghi nhận thông tin nhiên liệu hàng không đã được tra nạp tại các sân bay thuộc phạm vi áp dụng của ReFuelEU Aviation trong kỳ báo cáo | N51: Tổng lượng nhiên liệu lẽ ra cần thiết cho hoạt động bay trong năm = Trip fuel + Taxi fuel Lượng nhiên liệu cõng thêm vì mục đích kinh tế: mặc định bằng 0. Lượng nhiên liệu bổ sung do yêu cầu an toàn bay hoặc yêu cầu khai thác: mặc định bằng 0. | O51: Tấn | P51: - EU ETS | Q51: - Hàng tháng (ngày cuối cùng trong tháng) | R51: - Năm | AJ51: SAF Report | AK51: Báo cáo sử dụng SAF | AL51: Tab 2: Fuel & SAF Purchase Reporting (ReFuelEU Aviation Template) | AM51: Table
A52: 50 | B52: Tổ Kỹ thuật | C52: MS Quỳnh | D52: NhiPLH | E52: Không thuộc GRI | F52: =VLOOKUP(E52,'95 Chỉ tiêu'!$B$4:$F$177,2,0) -> #N/A | G52: Energy and Emissions | H52: Báo cáo sử dụng SAF | I52: CT 2.11 | J52: Total Flights Departing from France | K52: Tổng số chuyến bay tại Pháp | L52: Chị Quỳnh | M52: Là tổng số chuyến bay thương mại có điểm khởi hành từ các sân bay thuộc lãnh thổ Pháp trong kỳ báo cáo, không phân biệt loại hình chuyến bay hoặc điểm đến. | N52: Chỉ tính các chuyến bay có sân bay khởi hành (DEP) thuộc lãnh thổ Pháp. | O52: Chuyến | P52: - EU ETS | Q52: - Hàng tháng (ngày cuối cùng trong tháng) | R52: - Năm | AJ52: SAF Report | AK52: Báo cáo sử dụng SAF | AL52: Tab 3: CARBURE | AM52: Card
A53: 51 | B53: Tổ Kỹ thuật | C53: MS Quỳnh | D53: NhiPLH | E53: Không thuộc GRI | F53: =VLOOKUP(E53,'95 Chỉ tiêu'!$B$4:$F$177,2,0) -> #N/A | G53: Energy and Emissions | H53: Báo cáo sử dụng SAF | I53: CT 2.12 | J53: Total Flight Hours (France) | K53: Tổng số giờ bay (Pháp) | L53: Chị Quỳnh | M53: Là tổng thời gian bay thực tế của toàn bộ các chuyến bay thương mại có điểm khởi hành từ các sân bay thuộc lãnh thổ Pháp trong kỳ báo cáo. | N53: Tổng thời gian bay được tính từ thời điểm tàu bay rời vị trí đỗ để chuẩn bị cất cánh đến thời điểm tàu bay vào vị trí đỗ sau khi hạ cánh. | O53: Giờ | P53: - EU ETS | Q53: - Hàng tháng (ngày cuối cùng trong tháng) | R53: - Năm | AJ53: SAF Report | AK53: Báo cáo sử dụng SAF | AL53: Tab 3: CARBURE | AM53: Card
A54: 52 | B54: Tổ Kỹ thuật | C54: MS Quỳnh | D54: NhiPLH | E54: Không thuộc GRI | F54: =VLOOKUP(E54,'95 Chỉ tiêu'!$B$4:$F$177,2,0) -> #N/A | G54: Energy and Emissions | H54: Báo cáo sử dụng SAF | I54: CT 2.13 | J54: Planned SAF Volume (France) | K54: Lượng SAF kế hoạch ban đầu (Pháp) | L54: Chị Quỳnh | M54: Là tổng khối lượng nhiên liệu hàng không bền vững (SAF) dự kiến cần sử dụng trong kỳ báo cáo, được tính toán dựa trên tổng nhu cầu nhiên liệu khai thác và tỷ lệ SAF bắt buộc theo quy định của nhà chức trách hoặc kế hoạch nội bộ của hãng hàng không. | N54: Lượng SAF kế hoạch ban đầu = Tổng nhiên liệu cần sử dụng theo kế hoạch * Tỷ lệ SAF theo quy định của nhà chức trách áp dụng tại thời điểm lập kế hoạch. | O54: Tấn | P54: ANCM | Q54: - Khi có quy định từ nhà chức trách | R54: - Năm | AJ54: SAF Report | AK54: Báo cáo sử dụng SAF | AL54: Tab 3: CARBURE | AM54: Card
A55: 53 | B55: Tổ Kỹ thuật | C55: MS Quỳnh | D55: NhiPLH | E55: Không thuộc GRI | F55: =VLOOKUP(E55,'95 Chỉ tiêu'!$B$4:$F$177,2,0) -> #N/A | G55: Energy and Emissions | H55: Báo cáo sử dụng SAF | I55: CT 2.14 | J55: Actual SAF Uplifted Volume (Pháp) | K55: Lượng SAF nạp thực tế (Pháp) | L55: Chị Quỳnh | M55: Là tổng khối lượng nhiên liệu hàng không bền vững (SAF) đã được tra nạp thực tế vào tàu bay trong kỳ báo cáo. | N55: Không có. | O55: Tấn | P55: ANCM | Q55: - Khi có chứng nhận nạp dầu từ NCC | R55: - Năm | AJ55: SAF Report | AK55: Báo cáo sử dụng SAF | AL55: Tab 3: CARBURE | AM55: Card
A56: 56 | B56: Tổ Kỹ thuật | C56: MS Quỳnh | D56: NhiPLH | E56: Không thuộc GRI | F56: =VLOOKUP(E56,'95 Chỉ tiêu'!$B$4:$F$177,2,0) -> #N/A | G56: Energy and Emissions | H56: Báo cáo sử dụng SAF | I56: CT 2.15 | J56: Neat SAF Ratio by Airport (France) | K56: Tỷ lệ neat SAF theo sân bay (Pháp) | L56: Chị Quỳnh | M56: Là tỷ lệ giữa khối lượng nhiên liệu hàng không bền vững nguyên chất (Neat SAF) và tổng khối lượng nhiên liệu SAF pha trộn (Blended SAF) được nạp tại từng sân bay trong kỳ báo cáo. | N56: Tỷ lệ Neat SAF (%) = (Khối lượng SAF nguyên chất / Tổng khối lượng SAF pha trộn) * 100. | O56: % | P56: ANCM | Q56: - Khi có chứng nhận nạp dầu từ NCC | R56: - Năm | AJ56: SAF Report | AK56: Báo cáo sử dụng SAF | AL56: Tab 3: CARBURE | AM56: Bar Chart
A57: 54 | B57: Tổ Kỹ thuật | C57: MS Quỳnh | D57: NhiPLH | E57: Không thuộc GRI | F57: =VLOOKUP(E57,'95 Chỉ tiêu'!$B$4:$F$177,2,0) -> #N/A | G57: Energy and Emissions | H57: Báo cáo sử dụng SAF | I57: CT 2.16 | J57: Monthly SAF Uplift Volume (Tonnes) (France) | K57: Lượng SAF tra nạp theo tháng trong năm (Pháp) | L57: Chị Quỳnh | M57: Là tổng khối lượng nhiên liệu hàng không bền vững (SAF) được ghi nhận theo từng tháng trong kỳ báo cáo. | N57: Trường hợp đã có thư xác nhận: - Lượng SAF cho từng chuyến bay = (Lượng Neat SAF thực tế / Tổng nhiên liệu SAF pha trộn) * Lượng nhiên liệu nạp từng chuyến bay. - Lượng SAF nạp theo tháng = Σ Lượng SAF cho từng chuyến bay. Trường hợp chưa có thư xác nhận sẽ lấy theo số kế hoạch: - Lượng SAF cho từng chuyến bay = % SAF theo kế hoạch * Lượng nhiên liệu nạp từng chuyến bay. - Lượng SAF nạp heo tháng = Σ Lượng SAF cho từng chuyến bay. | O57: Tấn | P57: ANCM | Q57: - Khi có chứng nhận nạp dầu từ NCC | R57: - Năm | AE57: So sánh lượng nạp thực tế - kế hoạch | AJ57: SAF Report | AK57: Báo cáo sử dụng SAF | AL57: Tab 3: CARBURE | AM57: Combo chart
A58: 55 | B58: Tổ Kỹ thuật | C58: MS Quỳnh | D58: NhiPLH | E58: Không thuộc GRI | F58: =VLOOKUP(E58,'95 Chỉ tiêu'!$B$4:$F$177,2,0) -> #N/A | G58: Energy and Emissions | H58: Báo cáo sử dụng SAF | I58: CT 2.17 | J58: SAF Surcharge by Month in the Year (France) | K58: Phụ phí SAF theo tháng trong năm (Pháp) | L58: Chị Quỳnh | M58: Là tổng khối lượng nhiên liệu hàng không bền vững (SAF) đã được mua và phụ phí mua SAF phát sinh trong kỳ báo cáo, được tổng hợp theo từng năm dựa trên dữ liệu nạp nhiên liệu và dữ liệu tài chính liên quan đến SAF tại các sân bay thuộc phạm vi áp dụng. | N58: Lượng SAF theo tháng = Tổng khối lượng SAF pha trộn thực tế đã mua. Phụ phí SAF theo tháng = Phụ phí mua SAF phát sinh tương ứng với lượng SAF đã nạp. | O58: USD | P58: ANCM | Q58: - Khi có chứng nhận nạp dầu từ NCC | R58: - Năm | AE58: So sánh lượng mua và phụ phí SAF | AJ58: SAF Report | AK58: Báo cáo sử dụng SAF | AL58: Tab 3: CARBURE | AM58: Combo chart
A59: 57 | B59: Tổ Kỹ thuật | C59: MS Quỳnh | D59: NhiPLH | E59: Không thuộc GRI | F59: =VLOOKUP(E59,'95 Chỉ tiêu'!$B$4:$F$177,2,0) -> #N/A | G59: Energy and Emissions | H59: Báo cáo sử dụng SAF | I59: CT 2.18 | J59: SAF Purchased Volume by SAF Type and Supplier (France) | K59: Lượng mua SAF theo loại SAF & sân bay (Pháp) | L59: Chị Quỳnh | M59: Là tổng khối lượng nhiên liệu hàng không bền vững (SAF) đã được mua trong kỳ báo cáo, được phân loại theo: Loại SAF (HEFA, FT, ATJ…); Sân bay nạp nhiên liệu. | N59: Không có | O59: Tấn | P59: ANCM | Q59: - Khi có chứng nhận nạp dầu từ NCC | R59: - Năm | AJ59: SAF Report | AK59: Báo cáo sử dụng SAF | AL59: Tab 3: CARBURE | AM59: Stacked Bar Chart
A60: 58 | B60: Tổ Khai thác | C60: MS Lê | D60: NhiPLH | E60: Không thuộc GRI | F60: =VLOOKUP(E60,'95 Chỉ tiêu'!$B$4:$F$177,2,0) -> #N/A | G60: Energy and Emissions | H60: Báo cáo tuân thủ phát thải Carbon | I60: CT 2.19 | J60: EU ETS Full Scope Flights | K60: Tổng số chuyến bay đi/đến châu Âu | L60: Chị Lê | M60: - Tất cả các chuyến bay đi/đến các quốc gia thành viên EEA, bao gồm: các chuyến bay đi/đến các vùng lãnh thổ của quốc gia thành viên EEA; và các chuyến bay đi/đến các vùng ngoài cùng (OMR) của EEA. | N60: Không có | O60: Chuyến | P60: - EU ETS | Q60: - Hàng tháng (ngày cuối cùng trong tháng) | R60: - Năm | AJ60: Carbon Emissions Compliance Report | AK60: Báo cáo tuân thủ phát thải Carbon | AL60: Tab 1: EU-ETS | AM60: Card
A61: 59 | B61: Tổ Khai thác | C61: MS Lê | D61: NhiPLH | E61: Không thuộc GRI | F61: =VLOOKUP(E61,'95 Chỉ tiêu'!$B$4:$F$177,2,0) -> #N/A | G61: Energy and Emissions | H61: Báo cáo tuân thủ phát thải Carbon | I61: CT 2.20 | J61: EU ETS Reduced Scope Flights | K61: Số chuyến bay áp dụng EU ETS | L61: Chị Lê | M61: - Tổng số các chuyến bay thuộc diện thu hẹp (Reduced scope) theo chỉ thị EU ETS | N61: Không có | O61: Chuyến | P61: - EU ETS | Q61: - Hàng tháng (ngày cuối cùng trong tháng) | R61: - Năm | AJ61: Carbon Emissions Compliance Report | AK61: Báo cáo tuân thủ phát thải Carbon | AL61: Tab 1: EU-ETS | AM61: Card
A62: 60 | B62: Tổ Khai thác | C62: MS Lê | D62: NhiPLH | E62: Không thuộc GRI | F62: =VLOOKUP(E62,'95 Chỉ tiêu'!$B$4:$F$177,2,0) -> #N/A | G62: Energy and Emissions | H62: Báo cáo tuân thủ phát thải Carbon | I62: CT 2.21 | J62: CO₂ Offsetting Requirement (tonnes) (EU ETS) | K62: Lượng CO₂ cần đền bù (tấn) | L62: Chị Lê | M62: - Là tổng lượng phát thải CO₂ cuối cùng mà hãng hàng không có nghĩa vụ phải bù trừ sau khi đã áp dụng các cơ chế giảm trừ theo quy định, bao gồm miễn trừ phạm vi áp dụng, giảm phát thải từ nhiên liệu SAF hoặc các khoản phân bổ/hạn ngạch liên quan (chỉ tính trong phạm vi "Reduced scope"). | N62: Lượng CO2 cần đền bù = Lượng phát thải CO2 thực tế – Lượng CO2 được giảm trừ (nhờ sử dụng nhiên liệu SAF) – Hạn ngạch miễn phí (Allowance). | O62: Tấn | P62: - EU ETS | Q62: - Hàng năm | R62: - Năm | AJ62: Carbon Emissions Compliance Report | AK62: Báo cáo tuân thủ phát thải Carbon | AL62: Tab 1: EU-ETS | AM62: Card
A63: 61 | B63: Tổ Khai thác | C63: MS Lê | D63: NhiPLH | E63: Không thuộc GRI | F63: =VLOOKUP(E63,'95 Chỉ tiêu'!$B$4:$F$177,2,0) -> #N/A | G63: Energy and Emissions | H63: Báo cáo tuân thủ phát thải Carbon | I63: CT 2.22 | J63: CO₂ Emissions vs ETS Allowance | K63: Phát thải CO₂ so với hạn ngạch ETS theo từng năm | L63: Chị Lê | M63: So sánh phát thải thực tế với hạn ngạch được cấp theo năm. | N63: Lượng phát thải CO2 thực tế = Lượng phát thải CO2 do Jet A-1 + Lượng phát thải CO2 do SAF nguyên chất. | O63: Tấn | P63: - EU ETS | Q63: - Hàng năm | R63: - Năm | AJ63: Carbon Emissions Compliance Report | AK63: Báo cáo tuân thủ phát thải Carbon | AL63: Tab 1: EU-ETS | AM63: Combo chart
A64: 62 | B64: Tổ Khai thác | C64: MS Lê | D64: NhiPLH | E64: Không thuộc GRI | F64: =VLOOKUP(E64,'95 Chỉ tiêu'!$B$4:$F$177,2,0) -> #N/A | G64: Energy and Emissions | H64: Báo cáo tuân thủ phát thải Carbon | I64: CT 2.23 | J64: Annual EUA Compensation Cost (USD) | K64: Tổng chi phí bù trừ EUA (USD) theo năm | L64: Chị Lê | M64: Thống kê tổng chi phí mua tín chỉ EUA để bù trừ lượng phát thải CO₂ vượt hạn ngạch theo từng năm. | N64: Tổng chi phí bù trừ EUA = Tổng số lượng tín chỉ EUA cần mua mỗi loại * Đơn giá mỗi loại. | O64: USD | P64: Nhập thủ công | Q64: - Hàng năm | R64: - Năm | AJ64: Carbon Emissions Compliance Report | AK64: Báo cáo tuân thủ phát thải Carbon | AL64: Tab 1: EU-ETS | AM64: Column
A65: 63 | B65: Tổ Khai thác | C65: MS Lê | D65: NhiPLH | E65: Không thuộc GRI | F65: =VLOOKUP(E65,'95 Chỉ tiêu'!$B$4:$F$177,2,0) -> #N/A | G65: Energy and Emissions | H65: Báo cáo tuân thủ phát thải Carbon | I65: CT 2.24 | J65: CO₂ Emissions by Route (EU ETS) | K65: Phát thải CO₂ theo chặng bay | L65: Chị Lê | M65: Tổng CO₂ phát sinh, phân theo từng đường bay EU ETS | N65: Lượng phát thải CO2 thực tế = Lượng phát thải CO2 do Jet A-1 + Lượng phát thải CO2 do SAF nguyên chất. | O65: Tấn | P65: - EU ETS | Q65: - Hàng năm | R65: - Năm | AJ65: Carbon Emissions Compliance Report | AK65: Báo cáo tuân thủ phát thải Carbon | AL65: Tab 1: EU-ETS | AM65: Bar chart
A66: 64 | B66: Tổ Khai thác | C66: MS Lê | D66: NhiPLH | E66: Không thuộc GRI | F66: =VLOOKUP(E66,'95 Chỉ tiêu'!$B$4:$F$177,2,0) -> #N/A | G66: Energy and Emissions | H66: Báo cáo tuân thủ phát thải Carbon | I66: CT 2.25 | J66: CO₂ Emissions by Scope (EU ETS) | K66: Phát thải CO₂ theo phạm vi | L66: Chị Lê | M66: Phân loại phát thải theo loại chuyến bay Full scope và Reduce scope. | N66: Lượng phát thải CO2 thực tế = Lượng phát thải CO2 do Jet A-1 + Lượng phát thải CO2 do SAF nguyên chất. | O66: Tấn | P66: - EU ETS | Q66: - Hàng năm | R66: - Năm | AJ66: Carbon Emissions Compliance Report | AK66: Báo cáo tuân thủ phát thải Carbon | AL66: Tab 1: EU-ETS | AM66: Donut
A67: 65 | B67: Tổ Khai thác | C67: MS Lê | D67: NhiPLH | E67: Không thuộc GRI | F67: =VLOOKUP(E67,'95 Chỉ tiêu'!$B$4:$F$177,2,0) -> #N/A | G67: Energy and Emissions | H67: Báo cáo tuân thủ phát thải Carbon | I67: CT 2.26 | J67: UK ETS Full Scope Flights | K67: Tổng số chuyến bay đi/đến UK | L67: Chị Lê | M67: Tất cả các chuyến bay thuộc phạm vi mở rộng (Full scope) theo quy định của UK ETS. | N67: Không có | O67: Chuyến | P67: FIMS | Q67: - Hàng tháng (ngày cuối cùng trong tháng) | R67: - Năm | AJ67: Carbon Emissions Compliance Report | AK67: Báo cáo tuân thủ phát thải Carbon | AL67: Tab 2: UK-ETS | AM67: Card
A68: 66 | B68: Tổ Khai thác | C68: MS Lê | D68: NhiPLH | E68: Không thuộc GRI | F68: =VLOOKUP(E68,'95 Chỉ tiêu'!$B$4:$F$177,2,0) -> #N/A | G68: Energy and Emissions | H68: Báo cáo tuân thủ phát thải Carbon | I68: CT 2.27 | J68: UK ETS Reduced Scope Flights | K68: Số chuyến bay áp dụng UK ETS | L68: Chị Lê | M68: Tất cả các chuyến bay thuộc phạm vi thu hẹp (Reduced scope) theo quy định của UK ETS. | N68: Không có | O68: Chuyến | P68: FIMS | Q68: - Hàng tháng (ngày cuối cùng trong tháng) | R68: - Năm | AJ68: Carbon Emissions Compliance Report | AK68: Báo cáo tuân thủ phát thải Carbon | AL68: Tab 2: UK-ETS | AM68: Card
A69: 67 | B69: Tổ Khai thác | C69: MS Lê | D69: NhiPLH | E69: Không thuộc GRI | F69: =VLOOKUP(E69,'95 Chỉ tiêu'!$B$4:$F$177,2,0) -> #N/A | G69: Energy and Emissions | H69: Báo cáo tuân thủ phát thải Carbon | I69: CT 2.28 | J69: CO₂ Offsetting Requirement (tonnes) (UK ETS) | K69: Lượng CO₂ cần đền bù (tấn) | L69: Chị Lê | M69: Là tổng lượng phát thải CO₂ cuối cùng mà hãng hàng không có nghĩa vụ phải bù trừ sau khi đã áp dụng các cơ chế giảm trừ theo quy định, bao gồm miễn trừ phạm vi áp dụng, giảm phát thải từ nhiên liệu SAF hoặc các khoản phân bổ/hạn ngạch liên quan (chỉ tính trong phạm vi "Reduced scope"). | N69: Lượng CO2 cần đền bù = Lượng phát thải CO2 thực tế – Lượng CO2 được giảm trừ (nhờ sử dụng nhiên liệu SAF) – Hạn ngạch miễn phí (Allowance). | O69: Tấn | P69: FIMS | Q69: - Hàng năm | R69: - Năm | AJ69: Carbon Emissions Compliance Report | AK69: Báo cáo tuân thủ phát thải Carbon | AL69: Tab 2: UK-ETS | AM69: Card
A70: 68 | B70: Tổ Khai thác | C70: MS Lê | D70: NhiPLH | E70: Không thuộc GRI | F70: =VLOOKUP(E70,'95 Chỉ tiêu'!$B$4:$F$177,2,0) -> #N/A | G70: Energy and Emissions | H70: Báo cáo tuân thủ phát thải Carbon | I70: CT 2.29 | J70: CO₂ Emissions vs ETS Allowance | K70: Phát thải CO₂ so với hạn ngạch UK | L70: Chị Lê | M70: So sánh phát thải thực tế với hạn ngạch được cấp theo năm. | N70: Lượng phát thải CO2 thực tế = Lượng phát thải CO2 do Jet A-1 + Lượng phát thải CO2 do SAF nguyên chất. | O70: Tấn | P70: FIMS | Q70: - Hàng năm | R70: - Năm | AJ70: Carbon Emissions Compliance Report | AK70: Báo cáo tuân thủ phát thải Carbon | AL70: Tab 2: UK-ETS | AM70: Combo chart
... A81: 79 | B81: Tổ Khai thác | C81: MS Lê | D81: NhiPLH | E81: Không thuộc GRI | F81: =VLOOKUP(E81,'95 Chỉ tiêu'!$B$4:$F$177,2,0) -> #N/A | G81: Energy and Emissions | H81: Báo cáo tuân thủ phát thải Carbon | I81: CT 2.40 | J81: CO₂ Emissions by Scope | K81: Phát thải CO₂ theo phạm vi chuyến bay | L81: Chị Lê | M81: Là chỉ tiêu phân loại lượng phát thải khí CO₂ theo từng phạm vi chuyến bay thuộc cơ chế CORSIA trong kỳ báo cáo, được phân loại theo Full Scope và Reduced Scope | N81: Lượng phát thải CO2 thực tế = Lượng phát thải CO2 do Jet A-1 + Lượng phát thải CO2 do SAF nguyên chất. | O81: Tấn | P81: FIMS | Q81: - Hàng tháng (ngày cuối cùng trong tháng) | R81: - Năm | AJ81: Carbon Emissions Compliance Report | AK81: Báo cáo tuân thủ phát thải Carbon | AL81: Tab 3: CORSIA | AM81: Donut
A82: 80 | B82: Ban TCNL | C82: Mr Trường, Mr Quang Mr | D82: HieuCM | E82: Airline D-1 | F82: =VLOOKUP(E82,'95 Chỉ tiêu'!$B$4:$F$177,2,0) -> #N/A | G82: Labor Conditions | H82: Working days lost to strikes/Ngày công mất do đình công | I82: CT 4.1 | J82: Number of strikes | K82: Số vụ đình công | L82: Anh Trường, Anh Quang Anh | M82: - Số vụ đình công xảy ra trong năm báo cáo. | N82: - N/A | O82: - Vụ | P82: - Nhập thủ công | Q82: - Khi có phát sinh thực tế | R82: - Năm | S82: N/A | T82: N/A | U82: N/A | V82: N/A | W82: N/A | X82: N/A | Y82: N/A | Z82: N/A | AA82: N/A | AB82: N/A | AC82: 1 | AD82: - N/A | AJ82: Working days lost to strikes | AK82: Ngày công mất do đình công | AM82: Card
A83: 81 | B83: Ban TCNL | C83: Mr Trường, Mr Quang Mr | D83: HieuCM | E83: Airline F-2 | F83: =VLOOKUP(E83,'95 Chỉ tiêu'!$B$4:$F$177,2,0) -> #N/A | G83: People and Development | H83: Employee satisfaction/ Mức độ hài lòng của nhân viên | I83: CT 4.2 | J83: Overall satisfaction | K83: Mức độ hài lòng chung | L83: Anh Trường, Anh Quang Anh | M83: - Mức độ hài lòng tổng thể (My Organization/Overall satisfaction) | N83: - Lấy theo giá trị tương ứng với "Tổng Công ty" | O83: - % | P83: - Nhập thủ công | Q83: - Tháng 11 hàng năm | R83: - Năm | S83: N/A | T83: N/A | U83: N/A | V83: N/A | W83: N/A | X83: N/A | Y83: N/A | Z83: N/A | AA83: N/A | AB83: N/A | AC83: 1 | AD83: - N/A | AJ83: Employee satisfaction | AK83: Mức độ hài lòng của nhân viên | AM83: Card
A84: 82 | B84: Ban TCNL | C84: Mr Trường, Mr Quang Mr | D84: HieuCM | E84: Airline F-2 | F84: =VLOOKUP(E84,'95 Chỉ tiêu'!$B$4:$F$177,2,0) -> #N/A | G84: People and Development | H84: Employee satisfaction/ Mức độ hài lòng của nhân viên | I84: CT 4.3 | J84: Satisfaction level by division | K84: Mức độ hài lòng theo khối | L84: Anh Trường, Anh Quang Anh | M84: Bao gồm: - 1. Mức độ hài lòng tổng thể (My Organization/Overall satisfaction) - 2. Đặc điểm công việc (My job) - 3. Điều kiện làm việc (My work) - 4. Đào tạo và thăng tiến (Training and Career development) - 5. Lãnh đạo (cấp trên trực tiếp) (My Supervisor/Direct Manager) - 6. Mối quan hệ nơi công sở (My Team) - 7. Thu nhập (My Income) - 8. Phúc lợi cho người lao động (My Welfare) Chia theo 6 khối: (1): Khối Thương mại (2): Khối Dịch vụ (3): Khối Khai thác bay (4): Khối Kỹ thuật (5): Tham mưu tổng hợp (bao gồm lĩnh vực an toàn) (6): Trực thuộc khác Và (7): Tổng Công ty | N84: - N/A | O84: - % | P84: - Nhập thủ công | Q84: - Tháng 11 hàng năm | R84: - Năm | S84: N/A | T84: N/A | U84: N/A | V84: N/A | W84: N/A | X84: N/A | Y84: N/A | Z84: N/A | AA84: N/A | AB84: N/A | AC84: 1 | AD84: - N/A | AJ84: Employee satisfaction | AK84: Mức độ hài lòng của nhân viên | AM84: Column chart
A85: 83 | B85: Ban TCNL | C85: Mr Trường, Mr Quang Mr | D85: HieuCM | E85: Airline F-2 | F85: =VLOOKUP(E85,'95 Chỉ tiêu'!$B$4:$F$177,2,0) -> #N/A | G85: People and Development | H85: Employee satisfaction/ Mức độ hài lòng của nhân viên | I85: CT 4.4 | J85: Satisfaction level by employment type | K85: Mức độ hài lòng theo đối tượng lao động | L85: Anh Trường, Anh Quang Anh | M85: Bao gồm: - 1. Mức độ hài lòng tổng thể (My Organization/Overall satisfaction) - 2. Đặc điểm công việc (My job) - 3. Điều kiện làm việc (My work) - 4. Đào tạo và thăng tiến (Training and Career development) - 5. Lãnh đạo (cấp trên trực tiếp) (My Supervisor/Direct Manager) - 6. Mối quan hệ nơi công sở (My Team) - 7. Thu nhập (My Income) - 8. Phúc lợi cho người lao động (My Welfare) Chia theo 8 loại đối tượng lao động: (1) Lao động mặt đất (2) Phi công Việt Nam (3) Phi công ALS (4) Tiếp viên Việt Nam (5) Tiếp viên ALS (6) Nhân viên chi nhánh nước ngoài (7) Phi công nước ngoài (8) Tiếp viên nước ngoài Và (9) Tổng Công ty | N85: - N/A | O85: - % | P85: - Nhập thủ công | Q85: - Tháng 11 hàng năm | R85: - Năm | S85: N/A | T85: N/A | U85: N/A | V85: N/A | W85: N/A | X85: N/A | Y85: N/A | Z85: N/A | AA85: N/A | AB85: N/A | AC85: 1 | AD85: - N/A | AJ85: Employee satisfaction | AK85: Mức độ hài lòng của nhân viên | AM85: Column chart
A86: 84 | B86: Ban TCNL | C86: Mr Trường, Mr Quang Mr | D86: HieuCM | E86: Airline F-2 | F86: =VLOOKUP(E86,'95 Chỉ tiêu'!$B$4:$F$177,2,0) -> #N/A | G86: People and Development | H86: Employee satisfaction/ Mức độ hài lòng của nhân viên | I86: CT 4.5 | J86: Overall satisfaction across years | K86: Mức độ hài lòng tổng thể qua các năm | L86: Anh Trường, Anh Quang Anh | M86: - Mức độ hài lòng tổng thể (My Organization/Overall satisfaction) qua các năm. | N86: - Lấy theo giá trị tương ứng với "Tổng Công ty" | O86: - % | P86: - Nhập thủ công | Q86: - Tháng 11 hàng năm | R86: - 5 năm gần nhất | S86: N/A | T86: N/A | U86: N/A | V86: N/A | W86: N/A | X86: N/A | Y86: N/A | Z86: N/A | AA86: N/A | AB86: N/A | AC86: 1 | AD86: - N/A | AJ86: Employee satisfaction | AK86: Mức độ hài lòng của nhân viên | AM86: Line chart
A87: 85 | B87: Ban TCNL | C87: Mr Trường, Mr Quang Mr | D87: HieuCM | E87: GRI 202-1 | F87: =VLOOKUP(E87,'95 Chỉ tiêu'!$B$4:$F$177,2,0) -> #N/A | G87: Labor Conditions | H87: Ratios of standard entry-level wage by gender compared to local minimum wage / Tỷ lệ lương khởi điểm so với lương tối thiểu vùng 1 | I87: CT 4.6 | J87: Starting salary of Vietnamese pilots | K87: Lương khởi điểm phi công Việt Nam | L87: Anh Trường, Anh Quang Anh | M87: - Mức lương khởi điểm của phi công Việt Nam. Chỉ lấy theo lương chức danh. | N87: - N/A | O87: - VNĐ (Việt Nam đồng). | P87: - Nhập thủ công | Q87: - Hàng năm. | R87: - Năm | S87: N/A | T87: N/A | U87: N/A | V87: N/A | W87: N/A | X87: N/A | Y87: N/A | Z87: N/A | AA87: N/A | AB87: N/A | AC87: 1 | AD87: - N/A | AJ87: Ratios of standard entry-level wage by gender compared to local minimum wage | AK87: Tỷ lệ lương khởi điểm so với lương tối thiểu vùng 1 | AM87: Card
A88: 86 | B88: Ban TCNL | C88: Mr Trường, Mr Quang Mr | D88: HieuCM | E88: GRI 202-1 | F88: =VLOOKUP(E88,'95 Chỉ tiêu'!$B$4:$F$177,2,0) -> #N/A | G88: Labor Conditions | H88: Ratios of standard entry-level wage by gender compared to local minimum wage / Tỷ lệ lương khởi điểm so với lương tối thiểu vùng 1 | I88: CT 4.7 | J88: Starting salary of permanent flight attendants | K88: Lương khởi điểm tiếp viên cơ hữu | L88: Anh Trường, Anh Quang Anh | M88: - Mức lương khởi điểm của tiếp viên cơ hữu. Chỉ lấy theo lương chức danh. | N88: - N/A | O88: - VNĐ (Việt Nam đồng). | P88: - Nhập thủ công | Q88: - Hàng năm. | R88: - Năm | S88: N/A | T88: N/A | U88: N/A | V88: N/A | W88: N/A | X88: N/A | Y88: N/A | Z88: N/A | AA88: N/A | AB88: N/A | AC88: 1 | AD88: - N/A | AJ88: Ratios of standard entry-level wage by gender compared to local minimum wage | AK88: Tỷ lệ lương khởi điểm so với lương tối thiểu vùng 1 | AM88: Card
A89: 87 | B89: Ban TCNL | C89: Mr Trường, Mr Quang Mr | D89: HieuCM | E89: GRI 202-1 | F89: =VLOOKUP(E89,'95 Chỉ tiêu'!$B$4:$F$177,2,0) -> #N/A | G89: Labor Conditions | H89: Ratios of standard entry-level wage by gender compared to local minimum wage / Tỷ lệ lương khởi điểm so với lương tối thiểu vùng 1 | I89: CT 4.8 | J89: Starting salary of ground staff | K89: Lương khởi điểm lao động mặt đất | L89: Anh Trường, Anh Quang Anh | M89: - Mức lương khởi điểm của lao động mặt đất. Lấy theo lương chức danh + lương năng suất mức 1. | N89: - N/A | O89: - VNĐ (Việt Nam đồng). | P89: - Nhập thủ công | Q89: - Hàng năm. | R89: - Năm | S89: N/A | T89: N/A | U89: N/A | V89: N/A | W89: N/A | X89: N/A | Y89: N/A | Z89: N/A | AA89: N/A | AB89: N/A | AC89: 1 | AD89: - N/A | AJ89: Ratios of standard entry-level wage by gender compared to local minimum wage | AK89: Tỷ lệ lương khởi điểm so với lương tối thiểu vùng 1 | AM89: Card
A90: 88 | B90: Ban TCNL | C90: Mr Trường, Mr Quang Mr | D90: HieuCM | E90: GRI 202-1 | F90: =VLOOKUP(E90,'95 Chỉ tiêu'!$B$4:$F$177,2,0) -> #N/A | G90: Labor Conditions | H90: Ratios of standard entry-level wage by gender compared to local minimum wage / Tỷ lệ lương khởi điểm so với lương tối thiểu vùng 1 | I90: CT 4.9 | J90: Region 1 minimum wage | K90: Mức lương tối thiểu vùng 1 | L90: Anh Trường, Anh Quang Anh | M90: - Mức lương tối thiểu vùng 1 theo quy định của Nhà nước. | N90: - N/A | O90: - VNĐ (Việt Nam đồng). | P90: - Nhập thủ công | Q90: - Hàng năm. | R90: - Năm | S90: N/A | T90: N/A | U90: N/A | V90: N/A | W90: N/A | X90: N/A | Y90: N/A | Z90: N/A | AA90: N/A | AB90: N/A | AC90: 1 | AD90: - N/A | AJ90: Ratios of standard entry-level wage by gender compared to local minimum wage | AK90: Tỷ lệ lương khởi điểm so với lương tối thiểu vùng 1 | AM90: Card
A91: 89 | B91: Ban TCNL | C91: Mr Trường, Mr Quang Mr | D91: HieuCM | E91: GRI 202-1 | F91: =VLOOKUP(E91,'95 Chỉ tiêu'!$B$4:$F$177,2,0) -> #N/A | G91: Labor Conditions | H91: Ratios of standard entry-level wage by gender compared to local minimum wage / Tỷ lệ lương khởi điểm so với lương tối thiểu vùng 1 | I91: CT 4.10 | J91: Starting salary and Region 1 minimum wage over the years | K91: Mức lương khởi điểm và lương tối thiểu vùng 1 qua các năm | L91: Anh Trường, Anh Quang Anh | M91: - Mức lương khởi điểm của phi công Việt Nam, tiếp viên cơ hữu, lao động mặt đất và mức lương tối thiểu vùng 1, theo 5 năm gần nhất tính từ năm hiện tại. | N91: - N/A | O91: - VNĐ (Việt Nam đồng). | P91: - Nhập thủ công | Q91: - Hàng năm. | R91: - 5 năm gần nhất, tính từ năm hiện tại | S91: N/A | T91: N/A | U91: N/A | V91: N/A | W91: N/A | X91: N/A | Y91: N/A | Z91: N/A | AA91: N/A | AB91: N/A | AC91: 1 | AD91: - N/A | AJ91: Ratios of standard entry-level wage by gender compared to local minimum wage | AK91: Tỷ lệ lương khởi điểm so với lương tối thiểu vùng 1 | AM91: Line chart
A92: 90 | B92: Ban TCNL | C92: Mr Trường, Mr Quang Mr | D92: HungND2 | E92: GRI 401-1 | F92: =VLOOKUP(E92,'95 Chỉ tiêu'!$B$4:$F$177,2,0) -> #N/A | G92: Labor Conditions | H92: New employee hires and employee turnover | I92: CT 4.11 | J92: Total New Hires | K92: Tổng số tuyển mới | L92: Anh Trường, Anh Quang Anh | M92: - Là tổng số lượng nhân sự đã gia nhập và chính thức ký hợp đồng lao động với Vietnam Airlines trong kỳ báo cáo | N92: - N/A | O92: - Người | P92: - SkyHR | Q92: - Hàng ngày | R92: - Ngày đến ngày | S92: N/A | T92: N/A | U92: N/A | V92: N/A | W92: N/A | X92: N/A | Y92: N/A | Z92: N/A | AA92: N/A | AB92: N/A | AC92: 1 | AD92: - N/A | AF92: stg.hrms.hrms_employees | AJ92: New employee hires and employee turnover | AK92: Tuyển dụng và nghỉ việc | AL92: Tab 1: Tuyển mới | AM92: Card
A93: 91 | B93: Ban TCNL | C93: Mr Trường, Mr Quang Mr | D93: HungND2 | E93: GRI 401-1 | F93: =VLOOKUP(E93,'95 Chỉ tiêu'!$B$4:$F$177,2,0) -> #N/A | G93: Labor Conditions | H93: New employee hires and employee turnover | I93: CT 4.12 | J93: New Hires by Month | K93: Số tuyển mới theo tháng | L93: Anh Trường, Anh Quang Anh | M93: - Là số lượng lao động tuyển mới gia nhập tổ chức được ghi nhận chi tiết theo từng tháng phát sinh trong kỳ báo cáo | N93: - N/A | O93: - Người | P93: - SkyHR | Q93: - Hàng ngày | R93: - Ngày đến ngày | S93: N/A | T93: N/A | U93: N/A | V93: N/A | W93: N/A | X93: N/A | Y93: N/A | Z93: N/A | AA93: N/A | AB93: N/A | AC93: 1 | AD93: - N/A | AF93: stg.hrms.hrms_employees | AJ93: New employee hires and employee turnover | AK93: Tuyển dụng và nghỉ việc | AL93: Tab 1: Tuyển mới | AM93: Bar chart
A94: 92 | B94: Ban TCNL | C94: Mr Trường, Mr Quang Mr | D94: HungND2 | E94: GRI 401-1 | F94: =VLOOKUP(E94,'95 Chỉ tiêu'!$B$4:$F$177,2,0) -> #N/A | G94: Labor Conditions | H94: New employee hires and employee turnover | I94: CT 4.13 | J94: New Hires by Age Group | K94: Số tuyển mới theo nhóm tuổi | L94: Anh Trường, Anh Quang Anh | M94: - Là chỉ tiêu bóc tách chi tiết tổng số lượng lao động được tuyển mới gia nhập tổ chức trong năm báo cáo dựa trên phân khúc độ tuổi | N94: - N/A | O94: - Người | P94: - SkyHR | Q94: - Hàng ngày | R94: - Ngày đến ngày | S94: N/A | T94: N/A | U94: N/A | V94: N/A | W94: N/A | X94: N/A | Y94: N/A | Z94: N/A | AA94: N/A | AB94: N/A | AC94: 1 | AD94: - N/A | AF94: stg.hrms.hrms_employees | AJ94: New employee hires and employee turnover | AK94: Tuyển dụng và nghỉ việc | AL94: Tab 1: Tuyển mới | AM94: Bar chart
A95: 93 | B95: Ban TCNL | C95: Mr Trường, Mr Quang Mr | D95: HungND2 | E95: GRI 401-1 | F95: =VLOOKUP(E95,'95 Chỉ tiêu'!$B$4:$F$177,2,0) -> #N/A | G95: Labor Conditions | H95: New employee hires and employee turnover | I95: CT 4.14 | J95: New Hires by Gender | K95: Số tuyển mới theo giới tính | L95: Anh Trường, Anh Quang Anh | M95: - Là chỉ tiêu bóc tách tổng số lượng lao động được tuyển mới và gia nhập tổ chức trong kỳ báo cáo dựa trên chiều phân tích về giới tính (Nam và Nữ) | N95: - N/A | O95: - Người | P95: - SkyHR | Q95: - Hàng ngày | R95: - Ngày đến ngày | S95: N/A | T95: N/A | U95: N/A | V95: N/A | W95: N/A | X95: N/A | Y95: N/A | Z95: N/A | AA95: N/A | AB95: N/A | AC95: 1 | AD95: - N/A | AF95: stg.hrms.hrms_employees | AJ95: New employee hires and employee turnover | AK95: Tuyển dụng và nghỉ việc | AL95: Tab 1: Tuyển mới | AM95: Bar chart
A96: 94 | B96: Ban TCNL | C96: Mr Trường, Mr Quang Mr | D96: HungND2 | E96: GRI 401-1 | F96: =VLOOKUP(E96,'95 Chỉ tiêu'!$B$4:$F$177,2,0) -> #N/A | G96: Labor Conditions | H96: New employee hires and employee turnover | I96: CT 4.15 | J96: New Hires by Division | K96: Số tuyển mới theo các khối | L96: Anh Trường, Anh Quang Anh | M96: - Là chỉ tiêu bóc tách tổng số lượng lao động được tuyển mới và chính thức gia nhập Vietnam Airlines trong kỳ báo cáo, được phân loại chi tiết theo các khối của Hãng | N96: - N/A | O96: - Người | P96: - SkyHR | Q96: - Hàng ngày | R96: - Ngày đến ngày | S96: N/A | T96: N/A | U96: N/A | V96: N/A | W96: N/A | X96: N/A | Y96: N/A | Z96: N/A | AA96: N/A | AB96: N/A | AC96: 1 | AD96: - N/A | AF96: stg.hrms.hrms_employees | AJ96: New employee hires and employee turnover | AK96: Tuyển dụng và nghỉ việc | AL96: Tab 1: Tuyển mới | AM96: Bar chart
A97: 95 | B97: Ban TCNL | C97: Mr Trường, Mr Quang Mr | D97: HungND2 | E97: GRI 401-1 | F97: =VLOOKUP(E97,'95 Chỉ tiêu'!$B$4:$F$177,2,0) -> #N/A | G97: Labor Conditions | H97: New employee hires and employee turnover | I97: CT 4.16 | J97: New Hires by Recruitment Region | K97: Số tuyển mới theo khu vực tuyển dụng | L97: Anh Trường, Anh Quang Anh | M97: - Là chỉ tiêu bóc tách tổng số lượng lao động được tuyển mới và chính thức gia nhập Vietnam Airlines trong kỳ báo cáo, phân loại dựa trên khu vực địa lý nơi nhân sự được tuyển dụng và làm việc | N97: - N/A | O97: - Người | P97: - SkyHR | Q97: - Hàng ngày | R97: - Ngày đến ngày | S97: N/A | T97: N/A | U97: N/A | V97: N/A | W97: N/A | X97: N/A | Y97: N/A | Z97: N/A | AA97: N/A | AB97: N/A | AC97: 1 | AD97: - N/A | AF97: stg.hrms.hrms_employees | AJ97: New employee hires and employee turnover | AK97: Tuyển dụng và nghỉ việc | AL97: Tab 1: Tuyển mới | AM97: Bar chart
A98: 96 | B98: Ban TCNL | C98: Mr Trường, Mr Quang Mr | D98: HungND2 | E98: GRI 401-1 | F98: =VLOOKUP(E98,'95 Chỉ tiêu'!$B$4:$F$177,2,0) -> #N/A | G98: Labor Conditions | H98: New employee hires and employee turnover | I98: CT 4.17 | J98: New Hires by Employee Level | K98: Số tuyển mới theo cấp độ nhân viên | L98: Anh Trường, Anh Quang Anh | M98: - Là chỉ tiêu bóc tách chi tiết tổng số lượng lao động được tuyển mới và gia nhập Vietnam Airlines trong kỳ báo cáo, phân loại dựa trên cấp bậc chức danh và đặc thù nghề nghiệp | N98: - N/A | O98: - Người | P98: - SkyHR | Q98: - Hàng ngày | R98: - Ngày đến ngày | S98: N/A | T98: N/A | U98: N/A | V98: N/A | W98: N/A | X98: N/A | Y98: N/A | Z98: N/A | AA98: N/A | AB98: N/A | AC98: 1 | AD98: - N/A | AF98: stg.hrms.hrms_employees | AJ98: New employee hires and employee turnover | AK98: Tuyển dụng và nghỉ việc | AL98: Tab 1: Tuyển mới | AM98: Bar chart
A99: 97 | B99: Ban TCNL | C99: Mr Trường, Mr Quang Mr | D99: HungND2 | E99: GRI 401-1 | F99: =VLOOKUP(E99,'95 Chỉ tiêu'!$B$4:$F$177,2,0) -> #N/A | G99: Labor Conditions | H99: New employee hires and employee turnover | I99: CT 4.18 | J99: Total Employee Turnover | K99: Tổng số nghỉ việc | L99: Anh Trường, Anh Quang Anh | M99: - Là tổng số lượng người lao động chính thức rời khỏi tổ chức hoặc chấm dứt hợp đồng lao động với Vietnam Airlines trong kỳ báo cáo | N99: - N/A | O99: - Người | P99: - SkyHR | Q99: - Hàng ngày | R99: - Ngày đến ngày | S99: N/A | T99: N/A | U99: N/A | V99: N/A | W99: N/A | X99: N/A | Y99: N/A | Z99: N/A | AA99: N/A | AB99: N/A | AC99: 1 | AD99: - N/A | AF99: stg.hrms.hrms_employees | AJ99: New employee hires and employee turnover | AK99: Tuyển dụng và nghỉ việc | AL99: Tab 2: Nghỉ việc | AM99: Card
A100: 98 | B100: Ban TCNL | C100: Mr Trường, Mr Quang Mr | D100: HungND2 | E100: GRI 401-1 | F100: =VLOOKUP(E100,'95 Chỉ tiêu'!$B$4:$F$177,2,0) -> #N/A | G100: Labor Conditions | H100: New employee hires and employee turnover | I100: CT 4.19 | J100: Total Employee Voluntary Turnover | K100: Tổng số nghỉ việc tự nguyện | L100: Anh Trường, Anh Quang Anh | M100: - Là tổng số lượng người lao động nghỉ việc với lý do “Xin thôi việc” và chính thức rời khỏi Vietnam Airlines trong kỳ báo cáo | N100: - N/A | O100: - Người | P100: - SkyHR | Q100: - Hàng ngày | R100: - Ngày đến ngày | S100: N/A | T100: N/A | U100: N/A | V100: N/A | W100: N/A | X100: N/A | Y100: N/A | Z100: N/A | AA100: N/A | AB100: N/A | AC100: 1 | AD100: - N/A | AF100: stg.hrms.hrms_employees | AJ100: New employee hires and employee turnover | AK100: Tuyển dụng và nghỉ việc | AL100: Tab 2: Nghỉ việc | AM100: Card
A101: 99 | B101: Ban TCNL | C101: Mr Trường, Mr Quang Mr | D101: HungND2 | E101: GRI 401-1 | F101: =VLOOKUP(E101,'95 Chỉ tiêu'!$B$4:$F$177,2,0) -> #N/A | G101: Labor Conditions | H101: New employee hires and employee turnover | I101: CT 4.20 | J101: Voluntary Turnover Rate | K101: Tỷ lệ nghỉ việc tự nguyện | L101: Anh Trường, Anh Quang Anh | M101: - Là tỷ số phần trăm giữa số lượng người lao động nghỉ việc tự nguyện trên tổng số lao động bình quân của tổ chức trong kỳ báo cáo | N101: - N/A | O101: - Người | P101: - SkyHR | Q101: - Hàng ngày | R101: - Ngày đến ngày | S101: N/A | T101: N/A | U101: N/A | V101: N/A | W101: N/A | X101: N/A | Y101: N/A | Z101: N/A | AA101: N/A | AB101: N/A | AC101: 1 | AD101: - N/A | AF101: stg.hrms.hrms_employees | AJ101: New employee hires and employee turnover | AK101: Tuyển dụng và nghỉ việc | AL101: Tab 2: Nghỉ việc | AM101: Card
A102: 100 | B102: Ban TCNL | C102: Mr Trường, Mr Quang Mr | D102: HungND2 | E102: GRI 401-1 | F102: =VLOOKUP(E102,'95 Chỉ tiêu'!$B$4:$F$177,2,0) -> #N/A | G102: Labor Conditions | H102: New employee hires and employee turnover | I102: CT 4.21 | J102: Employee turnover by Month | K102: Số nghỉ việc theo tháng | L102: Anh Trường, Anh Quang Anh | M102: - Là chỉ tiêu thống kê tổng số lượng người lao động chính thức chấm dứt hợp đồng và rời khỏi tổ chức (Vietnam Airlines) được ghi nhận chi tiết và bóc tách theo từng tháng phát sinh trong kỳ báo cáo | N102: - N/A | O102: - Người | P102: - SkyHR | Q102: - Hàng ngày | R102: - Ngày đến ngày | S102: N/A | T102: N/A | U102: N/A | V102: N/A | W102: N/A | X102: N/A | Y102: N/A | Z102: N/A | AA102: N/A | AB102: N/A | AC102: 1 | AD102: - N/A | AF102: stg.hrms.hrms_employees | AJ102: New employee hires and employee turnover | AK102: Tuyển dụng và nghỉ việc | AL102: Tab 2: Nghỉ việc | AM102: Bar chart
A103: 101 | B103: Ban TCNL | C103: Mr Trường, Mr Quang Mr | D103: HungND2 | E103: GRI 401-1 | F103: =VLOOKUP(E103,'95 Chỉ tiêu'!$B$4:$F$177,2,0) -> #N/A | G103: Labor Conditions | H103: New employee hires and employee turnover | I103: CT 4.22 | J103: Employee turnover by Age Group | K103: Số nghỉ việc theo nhóm tuổi | L103: Anh Trường, Anh Quang Anh | M103: - Là chỉ tiêu bóc tách chi tiết tổng số lượng người lao động đã chính thức chấm dứt hợp đồng lao động và rời khỏi tổ chức trong kỳ báo cáo dựa trên độ tuổi của họ | N103: - N/A | O103: - Người | P103: - SkyHR | Q103: - Hàng ngày | R103: - Ngày đến ngày | S103: N/A | T103: N/A | U103: N/A | V103: N/A | W103: N/A | X103: N/A | Y103: N/A | Z103: N/A | AA103: N/A | AB103: N/A | AC103: 1 | AD103: - N/A | AF103: stg.hrms.hrms_employees | AJ103: New employee hires and employee turnover | AK103: Tuyển dụng và nghỉ việc | AL103: Tab 2: Nghỉ việc | AM103: Bar chart
... A109: 107 | B109: Ban TCNL | C109: Mr Trường, Mr Quang Mr | D109: HungND2 | E109: GRI 401-1 | F109: =VLOOKUP(E109,'95 Chỉ tiêu'!$B$4:$F$177,2,0) -> #N/A | G109: Labor Conditions | H109: New employee hires and employee turnover | I109: CT 4.28 | J109: Employee turnover by reason for leaving | K109: Số nghỉ việc theo lý do nghỉ việc | L109: Anh Trường, Anh Quang Anh | M109: - Là chỉ tiêu bóc tách chi tiết tổng số lượng người lao động đã chính thức chấm dứt hợp đồng lao động và rời khỏi Vietnam Airlines trong kỳ báo cáo, được phân loại cụ thể dựa trên nguyên nhân cốt lõi dẫn đến nghỉ việc | N109: - N/A | O109: - Người | P109: - SkyHR | Q109: - Hàng ngày | R109: - Ngày đến ngày | S109: N/A | T109: N/A | U109: N/A | V109: N/A | W109: N/A | X109: N/A | Y109: N/A | Z109: N/A | AA109: N/A | AB109: N/A | AC109: 1 | AD109: - N/A | AF109: stg.hrms.hrms_employees | AJ109: New employee hires and employee turnover | AK109: Tuyển dụng và nghỉ việc | AL109: Tab 2: Nghỉ việc | AM109: Bar chart
A110: 108 | B110: Ban TCNL | C110: Text only (báo cáo tĩnh) | D110: NamNC | E110: GRI 401-2 | F110: =VLOOKUP(E110,'95 Chỉ tiêu'!$B$4:$F$177,2,0) -> #N/A | G110: People and Development | H110: Programs for upgrading employee skills | K110: Danh sách phúc lợi toàn thời gian vs. bán thời gian | AJ110: Benefits provided to full-time employees
A111: 109 | B111: Ban TCNL | C111: Text only (báo cáo tĩnh) | D111: NamNC | E111: GRI 403-4 | F111: Xã hội | K111: Tỷ lệ nhân viên tham gia ủy ban ATVSLĐ | AJ111: Worker participation, consultation, and communication on OHS
A112: 110 | B112: Ban TCNL | C112: Mr Trường, Mr Quang Mr | D112: DongNG | E112: GRI 403-9 | F112: =VLOOKUP(E112,'95 Chỉ tiêu'!$B$4:$F$177,2,0) -> #N/A | G112: Labor Conditions | H112: Work-related injuries | I112: CT 4.29 | J112: Total accidents | K112: Tổng số vụ tai nạn | L112: Anh Trường, Anh Quang Anh | M112: Là tổng số vụ tai nạn lao động xảy ra đối với người lao động trong kỳ báo cáo, bao gồm cả tai nạn nhẹ, nặng và nghiêm trọng theo quy định. | N112: N/A | O112: vụ | P112: Nhập liệu thủ công | Q112: 6 tháng/lần | R112: Thời gian: Năm | S112: N/A | T112: N/A | U112: N/A | V112: N/A | W112: N/A | X112: N/A | Y112: N/A | Z112: N/A | AA112: N/A | AB112: N/A | AC112: 1 | AJ112: Work-related injuries | AK112: Thương tật lao động | AM112: Card
A113: 111 | B113: Ban TCNL | C113: Mr Trường, Mr Quang Mr | D113: DongNG | E113: GRI 403-9 | F113: =VLOOKUP(E113,'95 Chỉ tiêu'!$B$4:$F$177,2,0) -> #N/A | G113: Labor Conditions | H113: Work-related injuries | I113: CT 4.31 | J113: Number of injured people | K113: Số người bị thương | L113: Anh Trường, Anh Quang Anh | M113: Tổng số người lao động bị thương do tai nạn lao động trong kỳ báo cáo. | N113: N/A | O113: vụ | P113: Nhập liệu thủ công | Q113: 6 tháng/lần | R113: Thời gian: Năm | S113: N/A | T113: N/A | U113: N/A | V113: N/A | W113: N/A | X113: N/A | Y113: N/A | Z113: N/A | AA113: N/A | AB113: N/A | AC113: 1 | AJ113: Work-related injuries | AK113: Thương tật lao động | AM113: Card
A114: 112 | B114: Ban TCNL | C114: Mr Trường, Mr Quang Mr | D114: DongNG | E114: GRI 403-9 | F114: =VLOOKUP(E114,'95 Chỉ tiêu'!$B$4:$F$177,2,0) -> #N/A | G114: Labor Conditions | H114: Work-related injuries | I114: CT 4.32 | J114: Number of fatal accidents | K114: Số vụ có người chết | L114: Anh Trường, Anh Quang Anh | M114: Số sự kiện tai nạn mà hậu quả có ít nhất một người tử vong. | N114: N/A | O114: vụ | P114: Nhập liệu thủ công | Q114: 6 tháng/lần | R114: Thời gian: Năm | S114: N/A | T114: N/A | U114: N/A | V114: N/A | W114: N/A | X114: N/A | Y114: N/A | Z114: N/A | AA114: N/A | AB114: N/A | AC114: 1 | AJ114: Work-related injuries | AK114: Thương tật lao động | AM114: Card
A115: 113 | B115: Ban TCNL | C115: Mr Trường, Mr Quang Mr | D115: DongNG | E115: GRI 403-9 | F115: =VLOOKUP(E115,'95 Chỉ tiêu'!$B$4:$F$177,2,0) -> #N/A | G115: Labor Conditions | H115: Work-related injuries | I115: CT 4.33 | J115: Number of deaths | K115: Số người chết | L115: Anh Trường, Anh Quang Anh | M115: Tổng số nạn nhân tử vong từ tất cả các vụ tai nạn trong kỳ báo cáo. | N115: N/A | O115: vụ | P115: Nhập liệu thủ công | Q115: 6 tháng/lần | R115: Thời gian: Năm | S115: N/A | T115: N/A | U115: N/A | V115: N/A | W115: N/A | X115: N/A | Y115: N/A | Z115: N/A | AA115: N/A | AB115: N/A | AC115: 1 | AJ115: Work-related injuries | AK115: Thương tật lao động | AM115: Card
...

Sheet Chỉ tiêu G
A1: DANH SÁCH CHỈ TIÊU TRỤ CỘT GOVERNANCE
A3: STT | B3: Mã GRI | C3: Chỉ tiêu (Eng) | D3: Chỉ tiêu (Vie) | E3: Hiện trạng (Yes/No) | F3: Yêu cầu của GRI (theo hướng dẫn của GRI) | G3: Nội dung hiển thị cho VNA | H3: Báo cáo của SQ (Vie) | I3: Chỉ tiêu bổ sung
A4: =ROW()-3 -> 1 | B4: GRI 2-9 | C4: Governance structure and composition | D4: Cơ cấu và thành phần quản trị | E4: Yes | F4: 1. Sơ đồ cơ cấu quản trị 2. Danh sách các Ủy ban thuộc HĐQT. 3. Bảng thành phần HĐQT và từng Ủy ban theo 8 tiêu chí bắt buộc của GRI: (i) thành viên điều hành / không điều hành; (ii) tính độc lập; (iii) nhiệm kỳ / thời gian đã tại vị; (iv) số vị trí kiêm nhiệm quan trọng khác và tính chất của việc kiêm nhiệm; (v) giới tính; (vi) nhóm xã hội yếu thế/ít được đại diện; (vii) năng lực liên quan đến tác động tới TCT; (viii) đại diện của các bên liên quan. | G4: Cơ cấu quản trị của Vietnam Airlines gồm ĐHĐCĐ, HĐQT, Ban Kiểm soát và TGĐ cùng bộ máy điều hành. HĐQT thành lập 02 tiểu ban: Tiểu ban Chiến lược và đầu tư; Tiểu ban Lao động và Tiền lương Thành phần Hội đồng quản trị: 07 thành viên, gồm 01 thành viên độc lập, thành viên người đại diện phần vốn nhà nước và đại diện ANA. Đối với PTBV, HĐQT giữ vai trò định hướng và giám sát cao nhất. BĐH Chương trình PTBV do TGĐ làm Trưởng ban là cơ quan chịu trách nhiệm ra quyết định và giám sát việc quản lý các tác động kinh tế, môi trường và con người; TTK là cơ quan thường trực điều phối chuyên môn; các Tổ công tác được thành lập theo từng lĩnh vực/chương trình để chủ trì triển khai. (vẽ sơ đồ tương tự báo cáo thường niên) | H4: SIA công bố cơ cấu quản trị phát triển bền vững nhiều tầng: Hội đồng quản trị (Board) giám sát cao nhất, được hỗ trợ bởi các Ủy ban trực thuộc Board (gồm Ủy ban An toàn & Rủi ro) và Ủy ban Điều hành (MC), phân cấp xuống Ủy ban Quản lý Rủi ro & Tuân thủ Tập đoàn, Văn phòng PTBV và đại diện các khối/đơn vị kinh doanh. Thành phần và chức năng của từng tầng được nêu rõ, dẫn chiếu thêm Báo cáo Quản trị Công ty trong Báo cáo thường niên.
A5: =ROW()-3 -> 2 | B5: GRI 2-10 | C5: Nomination and selection of the highest governance body | D5: Quy trình đề cử, lựa chọn cơ quan quản lý cao nhất | E5: Yes | F5: 1. Quy trình đề cử, lựa chọn thành viên HĐQT và các tiểu ban 2. Tiêu chí lựa chọn — bắt buộc nêu rõ có xét đến và xét như thế nào đối với: (i) ý kiến của các bên liên quan (bao gồm cổ đông); (ii) tính đa dạng; (iii) tính độc lập; (iv) năng lực liên quan đến tác động PTBV của TCT. | G5: Thành viên HĐQT Vietnam Airlines do ĐHĐCĐ bầu theo phương thức bầu dồn phiếu. Quyền đề cử ứng viên được thực hiện theo tỷ lệ sở hữu cổ phần; Với tư cách doanh nghiệp có vốn nhà nước chi phối, việc giới thiệu người đại diện phần vốn nhà nước tham gia HĐQT được thực hiện theo quy định của Luật số 68/2025/QH15 và chỉ đạo của cơ quan đại diện chủ sở hữu. Trong quá trình đề cử và lựa chọn, TCT xem xét: ý kiến của cổ đông và các bên liên quan thông qua ĐHĐCĐ; tính độc lập của thành viên theo quy định pháp luật về công ty đại chúng; và năng lực, kinh nghiệm phù hợp với đặc thù ngành hàng không. | H5: SIA không trình bày quy trình đề cử và lựa chọn thành viên cơ quan quản trị cao nhất trong Báo cáo PTBV; chỉ tiêu này được dẫn chiếu toàn bộ sang chương Báo cáo Quản trị Công ty trong Báo cáo thường niên FY2024/25 của SIA.
A6: =ROW()-3 -> 3 | B6: GRI 2-11 | C6: Chair of the highest governance body | D6: Chủ tịch HĐQT | E6: Yes | F6: Nêu rõ: Chủ tịch HĐQT có đồng thời là cán bộ điều hành cấp cao của TCT hay không. Nếu Chủ tịch kiêm nhiệm điều hành: phải mô tả chức năng điều hành, lý do bố trí và cách ngăn ngừa/giảm thiểu xung đột lợi ích. | G6: CT HĐQT Vietnam Airlines là ông Đặng Ngọc Hòa. CT HĐQT không đồng thời là cán bộ điều hành cấp cao của TCT: chức danh TGĐ - người đại diện theo pháp luật và điều hành hoạt động hằng ngày - do ông Lê Hồng Hà đảm nhiệm. | H6: Công bố rõ Chủ tịch HĐQT ông Peter Seah Lim Huat (non-independent), tách biệt vai trò CEO (Goh Choon Phong); có Lead Independent Director riêng (Ms Goh Swee Chen).
A7: =ROW()-3 -> 4 | B7: GRI 2-12 | C7: Legal actions for anti-competitive behavior, anti-trust, and monopoly practices | D7: Vai trò của HĐQT trong giám sát quản lý tác động | E7: Yes | F7: 1. Vai trò của HĐQT và của cán bộ điều hành cấp cao trong việc xây dựng, phê duyệt và cập nhật: tầm nhìn/sứ mệnh/giá trị cốt lõi; chiến lược PTBV; các chính sách và mục tiêu PTBV. 2. Vai trò của HĐQT trong giám sát quy trình thẩm định chi tiết và các quy trình khác nhằm nhận diện và quản lý tác động kinh tế – môi trường – con người, gồm: (i) HĐQT có và tương tác với các bên liên quan như thế nào để hỗ trợ các quy trình này; (ii) HĐQT xem xét, sử dụng kết quả đầu ra của các quy trình này ra sao. 3. Vai trò của HĐQT trong rà soát tính hiệu quả của các quy trình nêu trên và tần suất rà soát. | G7: HĐQT là cơ quan quản lý cao nhất của Vietnam Airlines giữ vai trò định hướng và giám sát toàn diện đối với phát triển bền vững. TGĐ và BĐH Chương trình PTBV chịu trách nhiệm xây dựng, đề xuất và cập nhật các nội dung về tầm nhìn, sứ mệnh, giá trị cốt lõi, chiến lược PTBV để trình HĐQT. HĐQT giám sát các quy trình nhận diện, đánh giá và quản lý tác động kinh tế, môi trường và con người thông qua báo cáo của BĐH Chương trình PTBV. Rà soát hiệu quả: TTK họp hàng tháng, BĐH họp hàng quý, rà soát các chỉ tiêu PTBV và có báo cáo lên HĐQT nếu cần | H7: Board cùng Ban lãnh đạo cấp cao giám sát việc quản lý các tác động kinh tế, môi trường và xã hội của Tập đoàn, lồng ghép yếu tố ESG vào tạo giá trị dài hạn. Các rủi ro chiến lược về PTBV và khí hậu được rà soát qua quy trình đánh giá rủi ro toàn Tập đoàn (ARMRE) và báo cáo lên Board cùng lãnh đạo cấp cao.
A8: =ROW()-3 -> 5 | B8: GRI 2-13 | C8: Delegation of responsibility for managing impacts | D8: Ủy quyền trách nhiệm quản lý các tác động | E8: Yes | F8: 1. Cách HĐQT phân cấp trách nhiệm quản lý tác động, gồm: (i) HĐQT có bổ nhiệm cán bộ điều hành cấp cao chịu trách nhiệm về quản lý tác động hay không; (ii) trách nhiệm có được giao tiếp cho người lao động khác hay không. 2. Quy trình báo cáo ngược lên HĐQT về việc quản lý tác động. | G8: Hội đồng quản trị phân cấp trách nhiệm quản lý các tác động kinh tế, môi trường và con người cho Tổng giám đốc và bộ máy điều hành. BĐH Chương trình PTBV do TGĐ làm Trưởng ban là đầu mối cấp cao nhất chịu trách nhiệm điều hành công tác PTBV của TCT. TTK là cơ quan thường trực, điều phối chuyên môn và tham mưu tổng hợp, chịu sự chỉ đạo trực tiếp của Trưởng BĐH và PTBTT. Các Tổ công tác được thành lập theo từng lĩnh vực để chủ trì triển khai và chịu trách nhiệm về kết quả trong phạm vi được giao. Ở cấp thực thi, trách nhiệm được giao tiếp cho các Ban chức năng và đơn vị theo lĩnh vực chuyên môn: kiểm kê và giảm phát thải, quản lý nhiên liệu, mua sắm, nhân sự, dịch vụ hành khách, an toàn – chất lượng. Cơ chế báo cáo ngược: BĐH Chương trình Phát triển bền vững tổng hợp và báo cáo HĐQT về tiến độ, kết quả và các vấn đề phát sinh trong quản lý tác động PTBV. | H8: Trách nhiệm quản lý các tác động được phân cấp từ Tổng Giám đốc và Ủy ban Điều hành xuống Văn phòng PTBV (do Giám đốc PTBV phụ trách) và đại diện các khối/đơn vị kinh doanh — đóng vai trò ban thư ký vận hành. Báo cáo nêu rõ tuyến báo cáo và luồng phân bổ trách nhiệm giữa các cấp.
A9: =ROW()-3 -> 6 | B9: GRI 2-14 | C9: Role of the highest governance body in sustainability reporting | D9: Vai trò của cơ quan quản trị cao nhất trong báo cáo bền vững | E9: Yes | F9: Cần chỉ rõ: HĐQT có chịu trách nhiệm rà soát và phê duyệt thông tin công bố trong Báo cáo PTBV, bao gồm danh mục các chủ đề trọng yếu, hay không. Nếu có, hãy mô tả quy trình. Nếu không, hãy đưa lý do. | G9: HĐQT chịu trách nhiệm rà soát và phê duyệt các thông tin công bố trong Báo cáo thường niên, bao gồm nội dung báo cáo PTBV. Quy trình rà soát và phê duyệt: TTK BĐH Chương trình PTBV chủ trì thu thập dữ liệu từ các Tổ công tác, CQĐV, tổng hợp và xây dựng dự thảo báo cáo, gửi báo cáo cho Ban TT. Ban TT tập hợp thông tin báo cáo Ban Giám đốc và HĐQT báo cáo thường niên. HĐQT xem xét và phê duyệt trước khi công bố. | H9: Board Statement khẳng định vai trò giám sát trực tiếp của Board đối với báo cáo PTBV, được phê duyệt trước công bố. | I9: x (trong báo cáo của SQ, nhưng không thuộc Governance)
A10: =ROW()-3 -> 7 | B10: GRI 2-15 | C10: Conflicts of interest | D10: Xung đột lợi ích | E10: Yes | F10: Mô tả quy trình HĐQT ngăn ngừa và giảm thiểu xung đột lợi ích. Báo cáo nếu xung đột lợi ích được tiết lộ đến các bên liên quan, ít nhất là bao gồm: i. Kiêm nhiệm chéo trong HĐQT ii. Sở hữu chéo với nhà cung cấp và các bên liên quan iii. Sự tồn tại của cổ đông chi phối iv. Các bên liên quan: mối quan hệ, giao dịch và số dư còn lại. | G10: Điều 55 trong Điều lệ TCT ban hành ngày 28/6/2026 quy định về trách nhiệm trung thực và tránh các xung đột về quyền lợi. Xung đột lợi ích tới các bên liên quan: i. Kiêm nhiệm chéo: • Ông Đặng Ngọc Hòa: Ủy viên BCH Liên đoàn thương mại và công nghiệp Việt Nam (VCCI) • Ông Lê Hồng Hà: thành viên Hội đồng Học viện Hàng không Việt Nam nhiệm kỳ 2025-2030 • Ông Tạ Mạnh Hùng: Chủ tịch HĐTV Công ty TNHH MTV Dịch vụ mặt đất sân bay Việt Nam (VIAGS) • Ông Lê Trường Giang: Chủ tịch HĐQT Công ty cổ phần Dịch vụ hàng hóa Tân Sơn Nhất (TCS) • Ông Đinh Việt Tùng: PTGĐ TCT Đầu tư và Kinh doanh vốn nhà nước (SCIC). Chủ tịch HĐQT TCT Licogi. Chủ tịch HĐQT TCTCP Bảo Minh • Ông Trương Văn Phước: Ủy viên hội đồng khoa học của UB Thường vụ Quốc hội • Ông Hidekazu Isone: PTGĐ phụ trách chiến lược của ANA Holdings ii. Sở hữu chéo với nhà cung cấp: Vietnam Airlines nắm giữ vốn tại một số đơn vị đồng thời là nhà cung cấp dịch vụ cho Tổng công ty. iii. Cổ đông chi phối: Nhà nước là cổ đông chi phối, nắm giữ khoảng 86,42% vốn điều lệ thông qua Bộ Tài chính và Tổng công ty Đầu tư và Kinh doanh vốn nhà nước (SCIC). ANA Holdings là cổ đông chiến lược với tỷ lệ 5,62% iv. Giao dịch với bên liên quan: mối quan hệ, giá trị giao dịch và số dư còn lại với các bên liên quan được trình bày tại Thuyết minh Báo cáo tài chính hợp nhất đã kiểm toán hàng năm. | H10: SIA yêu cầu báo cáo ngay các tình huống xung đột lợi ích thực tế hoặc tiềm ẩn; Chính sách Xung đột lợi ích buộc mọi nhân viên kê khai hằng năm với Khối Nhân sự. Chính sách Luân chuyển các vị trí nhạy cảm là biện pháp kiểm soát rủi ro gian lận bổ sung, đánh giá định kỳ 2 năm/lần với các vị trí đến cấp Phó Chủ tịch Khối.
A11: =ROW()-3 -> 8 | B11: GRI 2-16 | C11: Communication of critical concerns | D11: Báo cáo các mối quan ngại nghiêm trọng | E11: Yes | F11: 1. Mô tả "mối quan ngại nghiêm trọng" và việc các mối quan ngại nghiêm trọng được báo cáo lên HĐQT như thế nào 2. Tổng số và tính chất của các mối quan ngại nghiêm trọng đã được báo cáo lên HĐQT trong kỳ báo cáo. | G11: Vietnam Airlines xác định "mối quan ngại nghiêm trọng" là các vấn đề liên quan đến tác động tiêu cực tiềm ẩn hoặc thực tế đối với các bên liên quan, hoặc liên quan đến hành vi kinh doanh của Tổng công ty, có mức độ ảnh hưởng đủ lớn để cần đến sự xem xét của cơ quan quản trị cao nhất. Các mối quan ngại nghiêm trọng được truyền đạt lên Hội đồng quản trị thông qua hệ thống kiểm toán nội bộ. Ban Kiểm soát thực hiện chức năng giám sát độc lập và báo cáo ĐHĐCĐ. Các vấn đề phát sinh từ kênh tiếp nhận đơn thư khiếu nại, tố cáo, kiến nghị, phản ánh và từ cơ chế tố giác nội bộ được xử lý theo trình tự, thủ tục quy định và được báo cáo lên cấp có thẩm quyền tương ứng với tính chất, mức độ của vụ việc. | H11: Các mối quan ngại nghiêm trọng được truyền đạt qua Chính sách Tố giác (Whistleblowing) và Cơ chế Khiếu nại: kênh bảo mật, ẩn danh do bên thứ ba quản lý, báo cáo được chuyển đến Kiểm toán Nội bộ và Ủy ban Kiểm toán rà soát hằng quý. SIA lược bỏ nội dung số lượng và tính chất các quan ngại báo cáo lên Board — vì lý do bảo mật. | I11: x
A12: =ROW()-3 -> 9 | B12: GRI 2-17 | C12: Collective knowledge of the highest governance body | D12: Kiến thức tập thể của cơ quan quản lý cao nhất | E12: Yes | F12: Các biện pháp đã thực hiện để nâng cao kiến thức, kỹ năng và kinh nghiệm tập thể của HĐQT về phát triển bền vững. | G12: Vietnam Airlines chú trọng nâng cao năng lực về PTBV cho đội ngũ quản trị và điều hành. Trong năm 2025, BĐH Chương trình PTBV đã hoàn thành chương trình đào tạo về PTBV do chuyên gia tư vấn độc lập bên ngoài thực hiện và dự định triển khai kế hoạch đối với HĐQT trong thời gian tới. | H12: Công bố thành viên HĐQT hoàn thành đào tạo về PTBV/khí hậu theo yêu cầu SGX-ST, dẫn chứng kinh nghiệm ESG cụ thể của từng thành viên (VD bà Goh Swee Chen từng là Giám đốc UN Global Compact Network Singapore). | I12: x
A13: =ROW()-3 -> 10 | B13: GRI 2-18 | C13: Evaluation of performance of the highest governance body | D13: Đánh giá hiệu quả hoạt động của cơ quan quản trị cao nhất | E13: Yes | F13: 1. Mô tả quy trình đánh giá hiệu quả hoạt động của HĐQT trong việc giám sát quản lý tác động kinh tế – môi trường – con người 2. Đánh giá là độc lập hay tự đánh giá; tần suất đánh giá. 3. Các hành động đã thực hiện sau đánh giá, bao gồm thay đổi về thành phần HĐQT và thay đổi về thông lệ quản trị của tổ chức. | G13: Ban KS có đánh giá HĐQT hàng năm | H13: Trong năm tài chính 2024/25, Ủy ban Đề cử đã thuê tư vấn độc lập bên ngoài đánh giá chính thức Board và các ủy ban trực thuộc, thông qua bảng câu hỏi (kèm phỏng vấn trực tiếp tùy chọn), bao gồm việc giám sát tác động của tổ chức tới kinh tế, môi trường và con người. Tư vấn kết luận Board hoạt động hiệu quả; Ủy ban Đề cử rà soát kết quả và các hành động tiếp theo phù hợp. | I13: x
A14: =ROW()-3 -> 11 | B14: GRI 2-23 | C14: Policy commitments | D14: Các cam kết về chính sách | E14: Yes | F14: 1. Danh mục các cam kết chính sách về ứng xử kinh doanh có trách nhiệm, bao gồm: i. các văn kiện liên chính phủ có thẩm quyền mà các cam kết đề cập đến; ii. cam kết có yêu cầu thực hiện thẩm định chi tiết hay không; iii. cam kết có áp dụng nguyên tắc phòng ngừa hay không; iv. cam kết có quy định về tôn trọng quyền con người hay không. 2. Cam kết riêng về tôn trọng quyền con người: i. các quyền con người được quốc tế công nhận mà cam kết này bao hàm; ii. các nhóm bên liên quan được đặc biệt quan tâm, gồm nhóm có nguy cơ/dễ bị tổn thương. 3. Đường dẫn công bố công khai của từng chính sách, hoặc lý do không công khai. 4. Cấp phê duyệt của từng chính sách - nêu rõ có phải cấp cao nhất hay không. 5. Phạm vi áp dụng. 6. Cách truyền thông cam kết tới người lao động, đối tác kinh doanh và các bên liên quan khác. | G14: Vietnam Airlines thiết lập hệ thống cam kết chính sách về ứng xử kinh doanh có trách nhiệm, được đăng tải trên các trang nội bộ của Vietnam Airlines, bao gồm: • Chương trình Phòng, chống tham nhũng, tiêu cực, thực hành tiết kiệm, chống lãng phí (ban hành năm 2025); • Bộ định nghĩa hành vi và Hướng dẫn thực hiện văn hóa chính trực • Chính sách An toàn (thuộc Tài liệu Hệ thống Quản lý An toàn – SMSM) • Quy chế quản lý lao động • Quy chế bảo vệ môi trường, sử dụng năng lượng tiết kiệm và hiệu quả • Quy chế đấu thầu và mua sắm • ... | H14: Các cam kết chính sách được neo vào Giá trị cốt lõi của SIA và bộ chính sách doanh nghiệp — gồm Chính sách Chống hối lộ/tham nhũng, Chính sách Tố giác, Bộ Quy tắc Ứng xử, Tuyên bố Chống nô lệ hiện đại, Bộ Quy tắc Nhà cung cấp và Khung Quản lý Rủi ro — áp dụng nguyên tắc phòng ngừa, bao trùm quyền con người và ứng xử kinh doanh có trách nhiệm trên toàn chuỗi giá trị.
A15: =ROW()-3 -> 12 | B15: GRI 2-24 | C15: Embedding policy commitments | D15: Lồng ghép các cam kết chính sách | E15: Yes | F15: Mô tả cách VNA lồng ghép từng cam kết chính sách vào toàn bộ hoạt động và quan hệ kinh doanh, bao gồm: i. Cách phân bổ trách nhiệm thực thi cam kết theo các cấp trong tổ chức; ii. Cách tích hợp cam kết vào chiến lược, chính sách vận hành, quy trình vận hành; iii. Cách thực thi cam kết thông qua quan hệ kinh doanh; iv. Đào tạo về thực thi cam kết: đối tượng, nội dung, hình thức, tần suất, tỷ lệ hoàn thành. | G15: Vietnam Airlines lồng ghép các cam kết chính sách vào hoạt động, cụ thể: Phân bổ trách nhiệm theo cấp: HĐQT giữ vai trò giám sát cao nhất. TGĐ và BĐH Chương trình PTBV chịu trách nhiệm tổ chức thực hiện. Các Tổ công tác, CQĐV chịu trách nhiệm hằng ngày đối với từng nhóm cam kết theo lĩnh vực chuyên môn. Tích hợp vào chiến lược và quy trình vận hành: các cam kết phát triển bền vững được cụ thể hóa thành chỉ tiêu trong kế hoạch sản xuất kinh doanh hằng năm. Thực thi qua quan hệ kinh doanh: ví dụ qua Bộ Quy tắc Ứng xử dành cho nhà cung cấp; tiêu chí sàng lọc trong quy trình mua sắm và đấu thầu.] Đào tạo: Trong nội bộ VNA đã triển khai nhiều khóa đào tạo về thực thi các chính sách, cam kết như: về an toàn thông tin, giao tiếp và hợp tác trên môi trường số, Nâng cao nhận thức pháp luật về Bảo vệ dữ liệu cá nhân, ... | H15: Các cam kết chính sách được thể chế hóa vào vận hành: các đơn vị kinh doanh chịu trách nhiệm triển khai cam kết kinh doanh có trách nhiệm trong công việc hằng ngày, được rà soát qua đợt Tự đánh giá Kiểm soát (CSA) hằng năm; Bộ Quy tắc Nhà cung cấp mở rộng yêu cầu tới nhà cung cấp, cùng đào tạo tuân thủ bắt buộc để củng cố việc thực thi. | I15: x
A16: =ROW()-3 -> 13 | B16: GRI 2-25 | C16: Processes to remediate negative impacts | D16: Quy trình khắc phục các tác động tiêu cực | E16: Yes | F16: 1. Cam kết của VNA về việc thực hiện hoặc hợp tác khắc phục các tác động tiêu cực mà VNA gây ra hoặc góp phần gây ra; 2. Mô tả cách tiếp cận của tổ chức trong việc xác định và giải quyết các khiếu nại, bao gồm cả các cơ chế giải quyết khiếu nại mà tổ chức đã thiết lập hoặc tham gia; 3. Các quy trình khắc phục khác ngoài cơ chế khiếu nại; 4. Mô tả cách thức các bên liên quan - với tư cách là người sử dụng cơ chế khiếu nại - tham gia vào quá trình thiết kế, rà soát, vận hành và cải tiến các cơ chế này; 5. Cách doanh nghiệp theo dõi tính hiệu quả của cơ chế khiếu nại và các quy trình khắc phục; ví dụ minh chứng về hiệu quả, kèm phản hồi của bên liên quan. | G16: Vietnam Airlines cam kết thực hiện hoặc hợp tác khắc phục các tác động tiêu cực mà Tổng công ty gây ra hoặc góp phần gây ra đối với các bên liên quan, trên cơ sở bảo vệ quyền và lợi ích hợp pháp của tổ chức, cá nhân và tuân thủ pháp luật hiện hành. | H16: Mô tả kênh khiếu nại nội bộ/ngoài, quy trình xử lý qua Internal Audit độc lập, Audit Committee theo dõi tiến độ khắc phục. | I16: x
A17: =ROW()-3 -> 14 | B17: GRI 2-26 | C17: Mechanisms for seeking advice and raising concerns about ethics | D17: Cơ chế tham vấn, phản ánh các vấn đề đạo đức | E17: Yes | F17: 1. Cơ chế để cá nhân xin tư vấn về việc thực thi các chính sách và thông lệ ứng xử kinh doanh có trách nhiệm. 2. Cơ chế để cá nhân phản ánh quan ngại về hành vi kinh doanh của doanh nghiệp. | G17: Vietnam Airlines duy trì các cơ chế để cá nhân xin tư vấn và phản ánh quan ngại liên quan đến ứng xử kinh doanh có trách nhiệm. Xin tư vấn: người lao động và các bên liên quan có thể liên hệ Ban Pháp chế và các Ban chức năng để được hướng dẫn về việc áp dụng các quy định nội bộ và pháp luật liên quan trong hoạt động hằng ngày. Phản ánh quan ngại: Vietnam Airlines tiếp nhận và xử lý đơn thư khiếu nại, tố cáo, kiến nghị, phản ánh theo quy định của pháp luật Bảo mật và bảo vệ người tố giác: thông tin về người tố cáo được bảo mật theo quy định pháp luật; người tố cáo được bảo vệ và không bị trả đũa vì việc phản ánh trung thực. | H17: Liệt kê đầy đủ kênh (Code of Conduct, Grievance Mechanisms, Whistleblowing Policy, kênh tiếp nhận nội bộ/ngoài), số liệu cụ thể theo dõi.
A18: =ROW()-3 -> 15 | B18: GRI 2-27 | C18: Compliance with Laws and Regulations | D18: Tuân thủ pháp luật và các quy định | E18: No | F18: Đây là chỉ tiêu định lượng - bốn tiểu mục đều yêu cầu số liệu, không phải cam kết: 1. TỔNG SỐ trường hợp không tuân thủ đáng kể phát sinh trong kỳ, chia theo: (i) số trường hợp bị phạt tiền; (ii) số trường hợp bị áp dụng chế tài phi tiền tệ. 2. TỔNG SỐ và GIÁ TRỊ TIỀN các khoản phạt ĐÃ NỘP trong kỳ, chia theo: (i) khoản phạt cho vi phạm phát sinh trong kỳ báo cáo; (ii) khoản phạt cho vi phạm phát sinh ở các kỳ trước. 3. Mô tả từng trường hợp không tuân thủ đáng kể (địa bàn, lĩnh vực, bối cảnh). 4. Mô tả cách thức xác định các trường hợp không tuân thủ nghiêm trọng | G18: Vietnam Airlines cam kết duy trì ở mức cao nhất các tiêu chuẩn đạo đức trong hoạt động sản xuất kinh doanh, đề cao tính chuyên nghiệp, trung thực và minh bạch. Bảo đảm tuân thủ các điều ước quốc tế, Hiến pháp và pháp luật luôn là ưu tiên quan trọng của Tổng công ty trong mọi hoạt động. Trong năm 2025, VNA không bị phạt hoặc áp dụng chế tài | H18: SIA và Scoot cam kết liêm chính, minh bạch, tuân thủ mọi luật xã hội và môi trường hiện hành tại từng quốc gia hoạt động. Trong năm tài chính 2024/25, không có khoản phạt đáng kể (trên 10.000 USD) hay chế tài phi tiền tệ nào do không tuân thủ luật về môi trường, sức khỏe và an toàn. | I18: x
A19: =ROW()-3 -> 16 | B19: GRI 2-29 | C19: Approach to stakeholder engagement | D19: Tiếp cận đối thoại các bên liên quan | E19: Yes | F19: 1. Danh mục các nhóm bên liên quan mà doanh nghiệp đối thoại và phương pháp nhận diện các nhóm này. 2. Mục đích đối thoại với từng nhóm 3. Cách doanh nghiệp đảm bảo đối thoại thực chất | G19: Vietnam Airlines xác định các nhóm bên liên quan trên cơ sở mức độ ảnh hưởng của hoạt động của TCT tới các nhóm này và mức độ ảnh hưởng của các nhóm này tới hoạt động của TCT. Mục đích đối thoại là nắm bắt kỳ vọng và mối quan tâm của từng nhóm, nhận diện các tác động thực tế và tiềm ẩn, và xác định các biện pháp phòng ngừa, giảm thiểu phù hợp. Các nhóm bên liên quan chính và kênh đối thoại bao gồm: • Cổ đông và nhà đầu tư: ĐHĐCĐ thường niên và bất thường; công bố thông tin định kỳ và bất thường theo quy định; gặp gỡ nhà đầu tư. • Khách hàng: các kênh tiếp nhận phản ánh, khiếu nại; khảo sát mức độ hài lòng; chương trình khách hàng thường xuyên; mạng xã hội. • Người lao động và Công đoàn: Hội nghị người lao động; đối thoại tại nơi làm việc; thương lượng tập thể; các kênh truyền thông nội bộ. • Cơ quan quản lý nhà nước: báo cáo định kỳ; làm việc với cơ quan đại diện chủ sở hữu và cơ quan quản lý chuyên ngành; tham gia góp ý xây dựng chính sách. • Nhà cung cấp và đối tác: đàm phán hợp đồng; đánh giá nhà cung cấp; hội nghị đối tác. • Cộng đồng: các chương trình cộng đồng và hoạt động an sinh xã hội. • Hiệp hội và liên minh ngành: tham gia IATA, AAPA, SkyTeam và Hiệp hội Doanh nghiệp Hàng không Việt Nam. • Cơ quan truyền thông: họp báo, thông cáo báo chí, kênh truyền thông chính thức. | H19: Có mục riêng "Stakeholder Engagement" với bảng chi tiết từng nhóm bên liên quan (nhà đầu tư, khách hàng, nhân viên, cơ quan quản lý...), kênh đối thoại, tần suất.
A20: =ROW()-3 -> 17 | B20: GRI 3-3 | C20: Management of material topics | D20: Quản lý các chủ đề trọng yếu | E20: Yes | F20: LƯU Ý CẤU TRÚC: GRI 3-3 phải được báo cáo RIÊNG cho TỪNG chủ đề trọng yếu, không báo cáo gộp cho cả trụ cột. Trước 3-3 phải có GRI 3-1 (quy trình xác định chủ đề trọng yếu) và GRI 3-2 (danh mục chủ đề trọng yếu). i. Xác định các chủ đề trọng yếu thuộc trụ cột Governance. ii. Với mỗi chủ đề, công bố đủ 6 nội dung: (a) Mô tả các tác động thực tế và tiềm ẩn, tiêu cực và tích cực đối với kinh tế, môi trường và con người (kể cả quyền con người). (b) VNA có liên quan tới các tác động tiêu cực đó thông qua hoạt động của chính mình hay thông qua quan hệ kinh doanh — và mô tả hoạt động/quan hệ kinh doanh đó. (c) Các chính sách hoặc cam kết đối với chủ đề. (d) Các hành động quản lý chủ đề, gồm: (i) ngăn ngừa/giảm thiểu tác động tiêu cực tiềm ẩn; (ii) xử lý tác động tiêu cực thực tế, gồm thực hiện hoặc hợp tác khắc phục; (iii) quản lý tác động tích cực. (e) Theo dõi hiệu quả của các hành động, gồm: (i) quy trình theo dõi; (ii) mục tiêu, chỉ tiêu và chỉ số đánh giá tiến độ; (iii) mức độ hiệu quả đạt được, gồm tiến độ so với mục tiêu; (iv) bài học rút ra và cách đưa vào chính sách, quy trình vận hành. (f) Việc đối thoại với các bên liên quan đã định hình các hành động tại (d) và việc đánh giá hiệu quả tại (e) như thế nào. | G20: Đề xuất không đưa nội dung này lên website, vì cần báo cáo cụ thể cho 21 chỉ tiêu còn lại nên có thể trùng với các nội dung đã báo cáo | H20: Thực hiện Double Materiality Assessment (DMA) theo chuẩn GRI 2021/SGX/IFRS, xác định 10 material topics qua khảo sát nội bộ/ngoài, có ma trận trọng yếu (Materiality Matrix) trực quan, review hàng năm bởi MC và CETSC.
A21: =ROW()-3 -> 18 | B21: GRI 201-4 | C21: Financial assistance received from government | D21: Trợ cấp/tài trợ nhận từ chính phủ | E21: Yes | F21: 1. TỔNG GIÁ TRỊ TIỀN TỆ hỗ trợ tài chính nhận được từ BẤT KỲ chính phủ nào trong kỳ, phân theo 08 loại: (i) miễn, giảm thuế và tín dụng thuế; (ii) trợ cấp; (iii) tài trợ đầu tư, tài trợ nghiên cứu và phát triển, các loại tài trợ khác; (iv) giải thưởng; (v) miễn/giảm tiền bản quyền, phí nhượng quyền; (vi) hỗ trợ tài chính từ các Cơ quan Tín dụng Xuất khẩu (ECA); (vii) ưu đãi tài chính; (viii) lợi ích tài chính khác đã nhận hoặc sẽ nhận từ bất kỳ chính phủ nào cho bất kỳ hoạt động nào 2. Số liệu tại mục (1) phân tách theo quốc gia 3. Chính phủ có hiện diện trong cơ cấu sở hữu hay không và mức độ hiện diện 4. Cơ sở xác định giá trị: áp dụng nhất quán các nguyên tắc kế toán được thừa nhận chung. | G21: Sự hiện diện của Nhà nước trong cơ cấu sở hữu: Nhà nước là cổ đông chi phối của Vietnam Airlines, nắm giữ khoảng 86,42% vốn điều lệ thông qua Bộ Tài chính và Tổng công ty Đầu tư và Kinh doanh vốn nhà nước (SCIC). Nhà nước thực hiện các quyền và nghĩa vụ của cổ đông theo quy định của pháp luật và Điều lệ TCT. Hỗ trợ tài chính nhận từ Chính phủ: Thực hiện Nghị quyết số 135/2020/QH14 ngày 17/11/2020 của Quốc hội về các giải pháp tháo gỡ khó khăn cho TCTHKVN do ảnh hưởng của đại dịch COVID-19, Vietnam Airlines đã triển khai gói giải pháp thanh khoản quy mô 12.000 tỷ đồng, gồm: • Khoản vay tái cấp vốn 4.000 tỷ đồng thông qua các tổ chức tín dụng được Ngân hàng Nhà nước tái cấp vốn với lãi suất 0%/năm, không tài sản bảo đảm. Khoản vay đã được Quốc hội cho phép gia hạn trả nợ, tối đa đến ngày 31/12/2027. • Phương án phát hành cổ phiếu tăng vốn điều lệ quy mô khoảng 8.000 tỷ đồng, trong đó SCIC thay mặt Chính phủ thực hiện quyền mua cổ phần của cổ đông Nhà nước. Kiểm toán Nhà nước đã thực hiện kiểm toán việc sử dụng nguồn vốn của gói hỗ trợ và kết luận nguồn vốn được quản lý, sử dụng đúng mục đích đề ra. | H21: SIA KHÔNG báo cáo chỉ tiêu GRI 201-4 (trợ cấp/hỗ trợ tài chính nhận từ chính phủ) trong Báo cáo PTBV FY2024/25 — chỉ tiêu này không có trong GRI Content Index. Phần hiệu quả kinh tế chỉ công bố GRI 201-1 (giá trị kinh tế trực tiếp tạo ra và phân phối); không có công bố riêng về hỗ trợ tài chính từ chính phủ.
A22: =ROW()-3 -> 19 | B22: GRI 205-2 | C22: Communication and training about anti-corruption policies and procedures | D22: Truyền thông, đào tạo về chống tham nhũng | E22: Yes | F22: Đây là chỉ tiêu định lượng, cụ thể: 1. Số lượng và tỷ lệ thành viên cơ quan quản trị đã được truyền thông về chính sách và quy trình phòng, chống tham nhũng — phân theo khu vực. 2. Số lượng và tỷ lệ người lao động đã được truyền thông — phân theo nhóm lao động và theo khu vực 3. Số lượng và tỷ lệ đối tác kinh doanh đã được truyền thông — phân theo nhóm lao động và theo khu vực; đồng thời mô tả nếu có truyền thông tới tổ chức/cá nhân khác. 4. Số lượng và tỷ lệ thành viên HĐQT đã được đào tạo về phòng, chống tham nhũng — phân theo khu vực. 5. Số lượng và tỷ lệ người lao động đã được đào tạo — phân theo nhóm lao động và khu vực. | G22: Trong năm 2025, Ban lãnh đạo Vietnam Airlines đã ban hành Chương trình Phòng, chống tham nhũng, tiêu cực, thực hành tiết kiệm, chống lãng phí — được xác định là kim chỉ nam trong mọi hoạt động sản xuất kinh doanh cũng như công tác quản trị nội bộ. Chương trình được triển khai theo Luật Phòng, chống tham nhũng 2018 và các quy định liên quan. -> Mục 1 và 2 đã đảm bảo tỷ lệ 100% | H22: Số liệu cụ thể 98.3% nhân viên hoàn thành đào tạo chống tham nhũng, 100% thành viên Ban điều hành hoàn thành đào tạo, đào tạo bắt buộc hàng năm qua nền tảng e-learning.
A23: =ROW()-3 -> 20 | B23: GRI 205-3 | C23: Confirmed incidents of corruption and actions taken | D23: Sự cố tham nhũng xác nhận và biện pháp xử lý | E23: No | F23: 1. TỔNG SỐ và TÍNH CHẤT các sự cố tham nhũng ĐÃ ĐƯỢC XÁC NHẬN trong kỳ báo cáo. 2. (b) Tổng số sự cố đã xác nhận dẫn tới việc NGƯỜI LAO ĐỘNG bị sa thải hoặc bị kỷ luật vì hành vi tham nhũng. 3. (c) Tổng số sự cố đã xác nhận dẫn tới việc CHẤM DỨT hoặc KHÔNG GIA HẠN hợp đồng với đối tác kinh doanh do vi phạm liên quan đến tham nhũng. 4. (d) Các VỤ VIỆC PHÁP LÝ CÔNG KHAI về tham nhũng được khởi kiện đối với Tổng công ty hoặc người lao động của Tổng công ty trong kỳ, và KẾT QUẢ xử lý các vụ việc đó. | G23: Không có sự cố tham nhũng nào tại Vietnam Airlines | H23: Trong năm tài chính 2024/25, không có sự cố tham nhũng nào được xác nhận liên quan đến nhân viên SIA, Scoot hay đối tác kinh doanh. Trên toàn Tập đoàn, 33 đơn vị kinh doanh được đánh giá rủi ro hối lộ/tham nhũng qua Bảng câu hỏi CSA, không phát hiện rủi ro đáng kể.
A24: =ROW()-3 -> 21 | B24: GRI 206-1 | C24: Legal actions for anti-competitive behavior, anti-trust, and monopoly practices | D24: Vụ kiện về cạnh tranh không lành mạnh, độc quyền | E24: No | F24: 1. (a) SỐ VỤ KIỆN đang xử lý hoặc đã hoàn tất trong kỳ báo cáo liên quan đến hành vi hạn chế cạnh tranh và vi phạm pháp luật về chống độc quyền, trong đó doanh nghiệp được xác định là MỘT BÊN THAM GIA. 2. (b) KẾT QUẢ CHÍNH của các vụ kiện đã hoàn tất, bao gồm các quyết định hoặc phán quyết. | G24: Không có vụ kiện về cạnh tranh không lành mạnh, độc quyền nào tại Vietnam Airlines | H24: SIA KHÔNG báo cáo chỉ tiêu GRI 206-1 (vụ kiện về hành vi phản cạnh tranh, chống độc quyền) trong Báo cáo PTBV FY2024/25 — không có trong GRI Content Index. Chủ yếu đề cập chung thông qua phần Compliance with Laws and Regulations tổng quát, không có sự cố pháp lý phát sinh.
A25: =ROW()-3 -> 22 | B25: GRI 415-1 | C25: Political contributions | D25: Đóng góp cho các hoạt động chính trị | E25: Yes | F25: 1. (a) TỔNG GIÁ TRỊ TIỀN TỆ các khoản đóng góp chính trị bằng TIỀN và bằng HIỆN VẬT, được thực hiện TRỰC TIẾP và GIÁN TIẾP bởi doanh nghiệp — phân theo QUỐC GIA và theo BÊN NHẬN/THỤ HƯỞNG. 2. (b) Nếu có đóng góp bằng hiện vật: phương pháp ước tính giá trị. | G25: Là Hãng hàng không quốc gia, Vietnam Airlines phối hợp chặt chẽ với Chính phủ và các cơ quan quản lý trong quá trình xây dựng và hoàn thiện chính sách, pháp luật về hàng không dân dụng và phát triển bền vững. Tổng công ty cũng tham gia đóng góp ý kiến chính sách một cách gián tiếp thông qua các hiệp hội và liên minh ngành như IATA, AAPA, SkyTeam và Hiệp hội Doanh nghiệp Hàng không Việt Nam. Trong năm 2026, Vietnam Airlines đã chi 753.708 USD phí hội viên cho các hiệp hội và liên minh trên | H25: Là hãng hàng không quốc gia của Singapore, SIA phối hợp với chính phủ, cơ quan quản lý và vận động gián tiếp qua các hiệp hội ngành (AAPA, IATA, Star Alliance). SIA không đóng góp cho chiến dịch, tổ chức chính trị hay vận động hành lang; năm 2024/25 SIA và Scoot không có khoản đóng góp chính trị nào, song đã chi 805.238 USD phí thành viên cho các hiệp hội thương mại như IATA và AAPA.

Sheet 31 Báo cáo động_ẩn
A1: STT | B1: Tổ/CQĐV phụ trách | C1: PIC VNA | D1: Mã chỉ tiêu | E1: Trụ cột | F1: Chủ đề | G1: Tên chỉ tiêu | H1: Chỉ tiêu con/Dashboard | I1: Có KPI (Yes/No) | J1: KPI đạt khi | K1: Đơn vị tính | L1: Logic tính chỉ tiêu / Công thức tính | M1: Chiều tổng hợp dữ liệu (filter) | N1: Nguồn dữ liệu | O1: Tần suất cập nhật dữ liệu
A2: 1 | B2: Tổ Khai thác | C2: MS Lê | D2: GRI 302-1 | E2: =VLOOKUP(D2,'95 Chỉ tiêu'!$B$4:$F$177,2,0) -> #N/A | F2: Energy and Emissions | G2: Năng lượng tiêu thụ trong tổ chức | H2: Tổng nhiên liệu tiêu thụ | J2: < số KH | K2: Lít | M2: - Theo thời gian: Tháng/Năm | N2: DWH/FIMS | O2: Hàng ngày
A3: 1.1 | H3: Nhiên liệu tiêu thụ Jet A-1 | K3: Lít | L3: Nhiên liệu tiêu thụ Jet A-1 = Tổng nhiên liệu tiêu thụ - Lượng SAF nguyên chất | N3: ANCM | O3: Hàng ngày
A4: 1.2 | H4: Nhiên liệu tiêu thụ SAF | K4: Lít | L4: Nhiên liệu tiêu thụ SAF = Tổng lượng SAF nguyên chất được xác định trong chứng nhận từ nhà cung cấp tại các sân bay | N4: ANCM | O4: Hàng ngày
A5: 1.3 | H5: Tiêu thụ SAF theo tỷ lệ pha trộn SAF | K5: % | L5: Tỷ lệ pha trộn SAF (% Neat SAF) = Lượng SAF nguyên chất (Neat SAF) / Lượng SAF pha trộn (Blended SAF) | N5: ANCM | O5: Hàng ngày
A6: 1.4 | H6: Tỷ lệ các loại nhiên liệu | K6: % | L6: - Tỷ lệ nhiên liệu SAF = Lượng tiêu thụ nhiên liệu SAF/ Tổng lượng nhiên liệu tiêu thụ. - Tỷ lệ nhiên liệu Jet A-1 = Lượng tiêu thụ nhiên liệu Jet A-1/ Tổng lượng nhiên liệu tiêu thụ. | N6: ANCM | O6: Hàng ngày
A7: 1.5 | H7: Tiêu thụ nhiên liệu theo năm so với kế hoạch (Lít) | K7: Lít | N7: DWH/FIMS+ PMS | O7: Hàng ngày
A8: 1.6 | H8: Tiêu thụ nhiên liệu theo tháng trong năm hiện tại (Lít) | K8: Lít | N8: DWH/FIMS+ PMS | O8: Hàng ngày
A9: 1.7 | H9: Tiêu thụ nhiên liệu Jet A-1 qua các năm | K9: Lít | N9: DWH/FIMS + ANCM
A10: 1.8 | H10: Tiêu thụ nhiên liệu SAF qua các năm | K10: Lít | N10: ANCM
A11: 2 | B11: Tổ Khai thác | C11: MS Lê | D11: GRI 302-4 | E11: =VLOOKUP(D11,'95 Chỉ tiêu'!$B$4:$F$177,2,0) -> #N/A | F11: Energy and Emissions | G11: Tiết kiệm năng lượng trong tổ chức | H11: Tổng năng lượng tiết kiệm (Lít) | K11: Lít | L11: Tổng năng lượng tiết kiệm (L) = Tổng tiết kiệm nhiên liệu (kg) / 0.8. | M11: - Theo thời gian: Tháng/Năm | N11: Excel/ Nhập thủ công
A12: 2.1 | H12: Tổng tiết kiệm nhiên liệu (kg) | K12: Kg | N12: Excel/ Nhập thủ công
A13: 2.2 | H13: Tổng giảm phát thải khí nhà kính (Tấn) | K13: tCO2 | L13: Tổng giảm phát thải khí nhà kính (tấn) = Tổng phát thải giảm nhờ các biện pháp tiết kiệm nhiên liệu nhiên liệu + Tổng giảm phát thải nhờ sử dụng SAF + Tổng phát thải đền bù | N13: Excel/ Nhập thủ công
A14: 2.3 | H14: Năng lượng tiết kiệm theo năm so với mục tiêu (Lít) | K14: Lít | N14: Excel/ Nhập thủ công
A15: 2.4 | H15: Kết quả tiết kiệm nhiên liệu theo năm so với mục tiêu (kg) | K15: Kg | N15: Excel/ Nhập thủ công
A16: 2.5 | H16: Năng lượng tiết kiệm theo tháng trong năm (Lít) | K16: Lít | N16: Excel/ Nhập thủ công
A17: 3 | B17: Tổ Khai thác | C17: MS Lê | D17: GRI 305-1 | E17: =VLOOKUP(D17,'95 Chỉ tiêu'!$B$4:$F$177,2,0) -> #N/A | F17: Energy and Emissions | G17: Phát thải khí nhà kính trực tiếp (Phạm vi 1) | H17: Tổng phát thải khí nhà kính | K17: Tấn | L17: Tổng phát thải khí nhà kính = Phát thải Jet A-1 + Phát thải SAF | M17: - Theo thời gian: Tháng/ Năm | N17: DWH/FIMS
A18: 3.1 | H18: Phát thải Jet A-1 | K18: tCO2 | L18: Phát thải Jet A-1 = Nhiên liệu tiêu thụ Jet A-1 * 0.8 / 1000 * Hệ số phát thải CO2 | N18: DWH/FIMS + ANCM
A19: 3.2 | H19: Phát thải SAF | K19: tCO2 | L19: Phát thải SAF = Hàm lượng năng lượng (MJ) * Cường độ phát thải CO2 tương đương của vòng đời (gCO2e/MJ) / 1000000 | N19: DWH/FIMS + ANCM
A20: 3.3 | H20: Phát thải khí nhà kính theo năm vs. Mục tiêu | K20: % | N20: DWH/FIMS + PMS | O20: Hàng ngày
A21: 3.4 | H21: Phát thải khí nhà kính theo tháng trong năm hiện tại | N21: DWH/FIMS | O21: Hàng ngày
A22: 4 | B22: Tổ Khai thác | C22: MS Lê | D22: GRI 305-4 | E22: =VLOOKUP(D22,'95 Chỉ tiêu'!$B$4:$F$177,2,0) -> #N/A | F22: Energy and Emissions | G22: Cường độ phát thải khí nhà kính | H22: Tổng cường độ phát thải khí nhà kính | K22: tCO2/ RTK | L22: Tổng cường độ phát thải = Tổng phát thải khí nhà kính / (Tổng RTK / 100) | M22: - Theo thời gian: Tháng/ Năm | N22: DWH/FIMS+RPS | O22: Hàng ngày
A23: 4.1 | H23: Tổng phát thải khí nhà kính | L23: Tổng phát thải khí nhà kính được lấy ở báo cáo GRI 305-1: Phát thải khí nhà kính trực tiếp (Phạm vi 1) | N23: DWH/FIMS | O23: Hàng ngày
A24: 4.2 | H24: Tổng RTK | N24: RPS | O24: Hàng ngày
A25: 4.3 | H25: Cường độ phát thải khí nhà kính theo năm vs. Mục tiêu | N25: DWH/FIMS + EU_ETS + RPS | O25: Hàng ngày
A26: 4.4 | H26: Cường độ phát thải nhà kính theo tháng trong năm hiện tại | N26: DWH/FIMS+ RPS | O26: Hàng ngày
A27: 5 | B27: Tổ Khai thác | C27: MS Lê | D27: GRI 305-5 | E27: =VLOOKUP(D27,'95 Chỉ tiêu'!$B$4:$F$177,2,0) -> #N/A | F27: Energy and Emissions | G27: Giảm phát thải khí nhà kính | H27: Tổng giảm phát thải khí nhà kính | K27: tCO2 | L27: Tổng giảm phát thải khí nhà kính (tấn) = Tổng phát thải giảm nhờ các biện pháp tiết kiệm nhiên liệu + Tổng giảm phát thải nhờ sử dụng SAF + Tổng phát thải đền bù | M27: - Theo thời gian: Tháng/ Năm | N27: Excel/ Nhập thủ công
A28: 5.1 | H28: Tổng giảm phát thải nhờ các biện pháp tiết kiệm nhiên liệu | L28: Tổng phát thải giảm nhờ các biện pháp tiết kiệm nhiên liệu = Tổng nhiên liệu tiết kiệm (Lít) * 0.8 / 1000 * 3.16 | N28: Excel/ Nhập thủ công
A29: 5.2 | H29: Tổng giảm phát thải nhờ sử dụng SAF | L29: Tổng phát thải giảm nhờ sử dụng SAF (Tấn) = Hàm lượng năng lượng (MJ) * (Cường độ phát thải cơ sở của nhiên liệu hóa thạch (gCO2e/MJ) - Cường độ phát thải CO2 tương đương của vòng đời (gCO2e/MJ)) / 1000000 | N29: Excel/ Nhập thủ công
A30: 5.3 | H30: Tổng phát thải đền bù | L30: Tổng phát thải đền bù = Lượng CO₂ cần đền bù (EU ETS) + Lượng CO₂ cần đền bù (UK ETS) + Lượng CO₂ cần đền bù (CORSIA). | N30: Excel/ Nhập thủ công
A31: 5.4 | H31: Giảm phát thải khí nhà kính theo năm vs. Mục tiêu | N31: Excel/ Nhập thủ công
A32: 5.5 | H32: Giảm phát thải khí nhà kính theo tháng trong năm hiện tại | N32: Excel/ Nhập thủ công
A33: 6 | B33: Tổ Khai thác | C33: MS Lê | D33: GRI 305-7 | E33: =VLOOKUP(D33,'95 Chỉ tiêu'!$B$4:$F$177,2,0) -> #N/A | F33: Energy and Emissions | G33: Nitrogen oxides (NOX), sulfur oxides (SOX), and other significant air emissions | H33: Tổng SOx phát thải | L33: Chưa có cách tính | M33: - Theo thời gian: Tháng/ Năm
A34: 6.1 | G34: Chuyển Phase 2 khi có công thức tính | H34: Tổng NOx phát thải | L34: Chưa có cách tính
A35: 6.2 | H35: Tổng CO2 phát thải | K35: tCO2 | L35: Phát thải khí CO2 được lấy ở báo cáo GRI 305-1: Phát thải khí nhà kính trực tiếp (Phạm vi 1)
A36: 6.3 | H36: Phát thải SOx theo năm vs. Mục tiêu | L36: Chưa có cách tính
A37: 6.4 | H37: Phát thải NOx theo năm vs. Mục tiêu | L37: Chưa có cách tính
A38: 6.5 | H38: Phát thải NOx, SOx theo năm vs. Mục tiêu | L38: Chưa có cách tính
A39: 6.6 | H39: Phát thải NOx, SOx theo tháng trong năm bất kỳ | L39: Chưa có cách tính
A40: 7 | B40: Tổ Kỹ thuật | C40: MS Quỳnh | D40: Không thuộc GRI | G40: Báo cáo sử dụng SAF | H40: Tổng số chuyến bay thương mại từ châu Âu | K40: chuyến | L40: Chỉ tính các chuyến bay có sân bay khởi hành (DEP) từ các quốc gia theo quy định Liên minh Châu Âu. | M40: - Theo thời gian: Tháng/ Năm - Theo quốc gia: EU - Theo sân bay - Theo loại SAF - Theo phạm vi RefuelEU Aviation | N40: DWH/FIMS | O40: Hàng ngày
A41: 7.1 | H41: Tổng số giờ bay | K41: hours | L41: Tổng số giờ bay thực tế (hours) = Block on - Block off | N41: DWH/FIMS | O41: Hàng ngày
A42: 7.1 | H42: Tổng số chuyến bay tại Pháp | K42: hours | L42: Chỉ tính các chuyến bay có sân bay khởi hành (DEP) thuộc lãnh thổ Pháp. | N42: DWH/FIMS
A43: 7.11 | H43: Tổng số giờ bay (Pháp) | K43: hours | L43: Tổng số giờ bay thực tế (hours) = Block on - Block off | N43: ANCM
A44: 7.12 | H44: Lượng SAF kế hoạch ban đầu (Pháp) | K44: Tấn | N44: ANCM
A45: 7.13 | H45: Lượng SAF nạp thực tế (Pháp) | K45: Tấn | N45: ANCM
A46: 7.14 | H46: Lượng SAF tra nạp theo tháng trong năm (Pháp) | K46: Tấn | L46: 1. Trường hợp đã có thư xác nhận: - Lượng SAF cho từng chuyến bay = (Lượng Neat SAF thực tế / Tổng nhiên liệu SAF pha trộn) * Lượng nhiên liệu nạp từng chuyến bay. - Lượng SAF nạp theo tháng = Σ Lượng SAF cho từng chuyến bay. 2. Trường hợp chưa có thư xác nhận sẽ lấy theo số kế hoạch: - Lượng SAF cho từng chuyến bay = % SAF theo kế hoạch * Lượng nhiên liệu nạp từng chuyến bay. - Lượng SAF nạp heo tháng = Σ Lượng SAF cho từng chuyến bay. | N46: ANCM
A47: 7.15 | H47: Phụ phí SAF theo tháng trong năm (Pháp) | N47: ANCM
A48: 7.16 | H48: Tỷ lệ neat SAF theo sân bay (Pháp) | K48: % | L48: Tỷ lệ Neat SAF (%) = (Khối lượng SAF nguyên chất / Tổng khối lượng SAF pha trộn) * 100 | N48: ANCM
A49: 7.17 | H49: Lượng mua SAF theo loại SAF & sân bay (Pháp) | N49: ANCM
A50: 7.2 | H50: Lượng SAF kế hoạch ban đầu (tấn) | K50: Tấn | N50: ANCM
A51: 7.3 | H51: Lượng SAF nạp thực tế (tấn) | K51: Tấn | N51: ANCM
A52: 7.4 | H52: Tỷ lệ neat SAF theo sân bay | K52: % | L52: Tỷ lệ Neat SAF (%) = (Khối lượng SAF nguyên chất / Tổng khối lượng SAF pha trộn) * 100 | N52: ANCM
A53: 7.5 | H53: Phụ phí SAF theo tháng trong năm | N53: ANCM
A54: 7.6 | H54: Lượng SAF tra nạp theo tháng trong năm | K54: Tấn | L54: 1. Trường hợp đã có thư xác nhận: - Lượng SAF cho từng chuyến bay = (Lượng Neat SAF thực tế / Tổng nhiên liệu SAF pha trộn) * Lượng nhiên liệu nạp từng chuyến bay. - Lượng SAF nạp theo tháng = Σ Lượng SAF cho từng chuyến bay. 2. Trường hợp chưa có thư xác nhận sẽ lấy theo số kế hoạch: - Lượng SAF cho từng chuyến bay = % SAF theo kế hoạch * Lượng nhiên liệu nạp từng chuyến bay. - Lượng SAF nạp heo tháng = Σ Lượng SAF cho từng chuyến bay. | N54: ANCM
A55: 7.7 | H55: Lượng mua SAF theo loại SAF & sân bay | K55: Tấn | N55: ANCM
A56: 7.8 | H56: Bảng chi tiết việc mua SAF | N56: ANCM
A57: 7.9 | H57: Bảng chi tiết nhiên liệu tra nạp tại các sân bay | L57: - Aviation Fuel Required = Trip fuel + Taxi fuel - Yearly non-tanked quantity = 0 - Yearly tanked quantity for fuel safety rules = 0 | N57: ANCM
A58: 8 | B58: Tổ Kỹ thuật | C58: MS Lê | D58: Không thuộc GRI | G58: Báo cáo CO2 phát thải vượt mức | H58: Tổng số chuyến bay đi/đến châu Âu | K58: Chuyến | L58: Chỉ tính các chuyến bay có điểm đi (DEP), điểm đến (ARR), hoặc cả DEP và ARR thuộc các sân bay tại EU. | M58: - Theo thời gian: Tháng/ Năm - Theo cơ chế: EU-ETS, UK-ETS, CORSIA - Theo phạm vi: Reduced scope, full scope - Theo chặng bay | N58: DWH/FIMS | O58: Hàng ngày
A59: 8.1 | H59: Số chuyến bay áp dụng EU ETS | K59: Chuyến | L59: Chỉ tính các chuyến bay có điểm đi (DEP) và điểm đến (ARR) dều thuộc các sân bay tại EU. | N59: DWH/FIMS | O59: Hàng ngày
A60: 8.2 | H60: Phát thải CO₂ so với hạn ngạch UK | N60: DWH/FIMS + Excel/ Nhập thủ công
A61: 8.3 | H61: Tổng chi phí bù trừ UKA (USD) theo năm | K61: USD | L61: Tổng chi phí bù trừ UKA = Tổng số lượng tín chỉ UKA cần mua mỗi loại * Đơn giá mỗi loại.
A62: 8.4 | H62: Phát thải CO₂ theo chặng bay | K62: tCO2 | N62: DWH/FIMS | O62: Hàng ngày
A63: 8.5 | H63: Phát thải CO₂ theo phạm vi | K63: tCO2 | N63: DWH/FIMS | O63: Hàng ngày
A64: 8.6 | H64: Tổng số CB quốc tế phạm vi CORSIA | K64: Chuyến | L64: Tổng số chuyến bay quốc tế được thực hiện trong kỳ báo cáo thuộc phạm vi áp dụng của chương trình CORSIA theo quy định của ICAO | N64: DWH/FIMS | O64: Hàng ngày
A65: 8.7 | H65: Tổng số CB CORSIA thuộc phạm vi cần đền bù | K65: Chuyến | L65: Tổng số chuyến bay thuộc phạm vi cần đền bù = Tổng số chuyến bay quốc tế thuộc phạm vi CORSIA đáp ứng điều kiện phát sinh nghĩa vụ đền bù theo quy định hiện hành. | N65: DWH/FIMS | O65: Hàng ngày
A66: 8.8 | H66: Tổng phát thải CORSIA | K66: tCO2 | L66: - Lượng phát thải CO2 thực tế = Lượng phát thải CO2 do Jet A-1 + Lượng phát thải CO2 do SAF nguyên chất. - Lượng nhiên liệu tiêu thụ = Lượng nhiên liệu nạp theo hóa đơn | N66: DWH/FIMS | O66: Hàng ngày
A67: 8.9 | H67: Tổng phát thải CORSIA cần đền bù | K67: tCO2 | L67: Lượng CO2 cần đền bù = Lượng phát thải CO2 thực tế – Lượng CO2 được giảm trừ (nhờ sử dụng nhiên liệu SAF) – Baseline.
A68: 9 | B68: Ban TCNL | C68: Mr Trường, Mr Quang Mr | D68: Airline D-1 | E68: =VLOOKUP(D68,'95 Chỉ tiêu'!$B$4:$F$177,2,0) -> #N/A | F68: Labor Conditions | G68: Working days lost to strikes/Ngày công mất do đình công | H68: Số vụ đình công | K68: Ngày | N68: Excel/ Nhập thủ công | O68: Hàng năm
A69: 10 | C69: Mr Trường, Mr Quang Mr | D69: Airline F-2 | E69: =VLOOKUP(D69,'95 Chỉ tiêu'!$B$4:$F$177,2,0) -> #N/A | F69: People and Development | G69: Employee satisfaction/ Mức độ hài lòng của nhân viên | H69: Mức độ hài lòng chung | N69: Excel/ Nhập thủ công | O69: Hàng năm
A70: 10.1 | H70: Mức độ hài lòng theo khối | N70: Excel/ Nhập thủ công | O70: Hàng năm
A71: 10.2 | H71: Mức độ hài lòng theo đối tượng lao động | N71: Excel/ Nhập thủ công | O71: Hàng năm
A72: 10.3 | H72: Mức độ hài lòng tổng thể qua các năm | N72: Excel/ Nhập thủ công | O72: Hàng năm
A73: 11 | B73: Ban TCNL | C73: Mr Trường, Mr Quang Mr | D73: GRI 202-1 | E73: =VLOOKUP(D73,'95 Chỉ tiêu'!$B$4:$F$177,2,0) -> #N/A | F73: Labor Conditions | G73: Ratios of standard entry-level wage by gender compared to local minimum wage / Tỷ lệ lương khởi điểm so với lương tối thiểu vùng 1 | H73: Lương khởi điểm phi công Việt Nam | N73: Excel/ Nhập thủ công | O73: Hàng năm
A74: 11.1 | H74: Lương khởi điểm tiếp viên cơ hữu | N74: Excel/ Nhập thủ công | O74: Hàng năm
A75: 11.2 | H75: Lương khởi điểm lao động mặt đất | N75: Excel/ Nhập thủ công | O75: Hàng năm
A76: 11.3 | H76: Mức lương tối thiểu vùng 1 | N76: Excel/ Nhập thủ công | O76: Hàng năm
A77: 11.4 | H77: Mức lương khởi điểm và lương tối thiểu vùng 1 qua các năm | N77: Excel/ Nhập thủ công | O77: Hàng năm
A78: 12 | B78: Ban TCNL | C78: Mr Trường, Mr Quang Mr | D78: GRI 401-1 | E78: =VLOOKUP(D78,'95 Chỉ tiêu'!$B$4:$F$177,2,0) -> #N/A | F78: Labor Conditions | G78: New employee hires and employee turnover | H78: Tổng số tuyển mới | K78: Người | L78: Tổng số lượng nhân sự đã gia nhập và chính thức ký hợp đồng lao động với Vietnam Airlines trong kỳ báo cáo. | M78: - Theo thời gian: Tháng/Năm | N78: DWH/SkyHr | O78: Hàng ngày
A79: 12.1 | H79: Số tuyển mới theo tháng | K79: Người | N79: DWH/SkyHr | O79: Hàng ngày
A80: 12.1 | H80: Số nghỉ việc theo tháng | K80: Người | N80: DWH/SkyHr | O80: Hàng ngày
A81: 12.11 | H81: Số nghỉ việc theo nhóm tuổi | K81: Người | N81: DWH/SkyHr | O81: Hàng ngày
A82: 12.12 | H82: Số nghỉ việc theo thâm niên | K82: Người | N82: DWH/SkyHr | O82: Hàng ngày
A83: 12.13 | H83: Số nghỉ việc theo giới tính | K83: Người | N83: DWH/SkyHr | O83: Hàng ngày
A84: 12.14 | H84: Số nghỉ việc theo khối | K84: Người | N84: DWH/SkyHr | O84: Hàng ngày
A85: 12.15 | H85: Số nghỉ việc theo khu vực tuyển dụng | K85: Người | N85: DWH/SkyHr | O85: Hàng ngày
A86: 12.16 | H86: Số nghỉ việc theo cấp độ nhân viên | K86: Người | N86: DWH/SkyHr | O86: Hàng ngày
A87: 12.17 | H87: Số nghỉ việc theo lý do nghỉ việc | K87: Người | N87: DWH/SkyHr | O87: Hàng ngày
A88: 12.2 | H88: Số tuyển mới theo nhóm tuổi | K88: Người | N88: DWH/SkyHr | O88: Hàng ngày
A89: 12.3 | H89: Số tuyển mới theo giới tính | K89: Người | N89: DWH/SkyHr | O89: Hàng ngày
A90: 12.4 | H90: Số tuyển mới theo các khối | K90: Người | N90: DWH/SkyHr | O90: Hàng ngày
... A95: 12.9 | H95: Tỷ lệ nghỉ việc tự nguyện | K95: Người | N95: DWH/SkyHr | O95: Hàng ngày
A96: 13 | B96: Ban TCNL | C96: Mr Trường, Mr Quang Mr | D96: GRI 403-9 | E96: =VLOOKUP(D96,'95 Chỉ tiêu'!$B$4:$F$177,2,0) -> #N/A | F96: Labor Conditions | G96: Work-related injuries | H96: Tổng số vụ tai nạn | K96: Trường hợp | M96: - Thời gian: Năm, Quý, Tháng | N96: Excel/ Nhập thủ công
A97: 13.1 | H97: Số người bị thương | K97: Người | N97: Excel/ Nhập thủ công
A98: 13.2 | H98: Số vụ có người chết | K98: Người | N98: Excel/ Nhập thủ công
A99: 13.3 | H99: Số người chết | K99: Người | N99: Excel/ Nhập thủ công
A100: 13.4 | H100: Cơ cấu yếu tố gây chấn thương | N100: Excel/ Nhập thủ công
A101: 13.5 | H101: Cơ cấu nguyên nhân xảy ra tai nạn | N101: Excel/ Nhập thủ công
A102: 14 | B102: Ban TCNL | C102: Mr Trường, Mr Quang Mr | D102: GRI 405-1 | E102: =VLOOKUP(D102,'95 Chỉ tiêu'!$B$4:$F$177,2,0) -> #N/A | F102: Labor Conditions | G102: Diversity of governance bodies and employees | H102: Tổng số thành viên trong cơ quan quản trị | K102: % | L102: Là tổng số lượng cá nhân đang chính thức tromg cơ quan Hội đồng Quản trị (HĐQT), Ban Giám đốc (BGĐ) và Ban Kiểm soát (BKS). | M102: - Thời gian: Năm | N102: Excel/ Nhập thủ công
A103: 14.1 | H103: Tỷ lệ thành viên nữ | K103: % | N103: Excel/ Nhập thủ công
A104: 14.2 | H104: Số lượng thành viên theo cơ quan quản trị | K104: Người | N104: Excel/ Nhập thủ công
...

Sheet KPI (bỏ)
A1: STT | B1: Tổ/Ban | C1: Mã chỉ tiêu | D1: Tên chỉ tiêu cha (VN) | E1: Tab | F1: Chỉ tiêu con (VN) | G1: Mã chỉ tiêu con | H1: Kế hoạch/Mục tiêu | I1: Nguồn nhập kế hoạch/mục tiêu | J1: KPI đạt khi
A2: 1 | B2: Tổ Khai thác | C2: GRI 302-1 | D2: Năng lượng tiêu thụ trong tổ chức | F2: Tổng nhiên liệu tiêu thụ | G2: CT 1.1 | H2: Không
